Workbook

Sheet Guide
A1: Plan financier : dettes, déménagement, épargne
A3: Comment l'utiliser
A4: 1. Onglet Budget : saisissez vos revenus, charges fixes (hors crédits), dépenses variables et paramètres.
A5: 2. Onglet Crédits : une ligne par crédit (capital restant dû, TAEG, mensualité, durée restante).
A6: 3. Onglet Synthèse : lisez le résultat (marge, dates clés, intérêts économisés, graphique).
A7: 4. Onglet Plan : le détail mois par mois. Calcul = moteur de simulation, ne pas modifier.
A9: Légende
A10: Cellules jaunes / texte bleu = à remplir. Texte noir = formules, ne pas écraser.
A11: Les valeurs pré-remplies sont des EXEMPLES : remplacez-les par vos chiffres.
A13: Logique du plan (ordre de priorité chaque mois)
A14: 1. Mensualités normales de tous les crédits.
A15: 2. Épargne déménagement jusqu'à l'objectif, tant que la date limite n'est pas passée.
... A29: Suivi réel : chaque fin de mois, saisissez vos soldes réels pour comparer avec le plan.

Sheet Synthèse
A1: Synthèse du plan | E1: Graphe 1 : la ligne rouge doit descendre à 0, la violette monter. Graphe 2 : les lignes pleines doivent atteindre leurs pointillés.
A3: SITUATION ACTUELLE
A4: Revenus mensuels | B4: =Budget!B7 -> 2900
A5: Charges fixes + dépenses variables | B5: =Budget!B18+Budget!B25 -> 1725
A6: Mensualités de crédit | B6: =Crédits!E11 -> 731.45
A7: Marge mensuelle disponible | B7: =B4-B5-B6 -> 443.55 | C7: Ce qui reste chaque mois pour épargner / rembourser
A8: Taux d'endettement | B8: =IFERROR(B6/B4,0) -> 0.25222414 | C8: Repère bancaire : 35 % max
A9: Alerte endettement | B9: =IF(B8>0.35,"Au-dessus de 35 %",IF(B8>0.3,"Proche du seuil","OK")) -> OK
A10: Total restant dû | B10: =Crédits!C11 -> 16400
A11: TAEG moyen pondéré | B11: =Crédits!D11 -> 0.060106707
A13: OBJECTIF DÉMÉNAGEMENT
A14: Objectif | B14: =Budget!B29 -> 4000
A15: Épargne mensuelle nécessaire (approx.) | B15: =IFERROR(MAX(0,Budget!B29-Budget!B31)/MAX(1,DATEDIF(Budget!B28,Budget!B30,"m")+1),0) -> 583.33333 | C15: Montant restant / nombre de mois jusqu'à la date limite
A16: Montant atteint à la date limite | B16: {=IFERROR(INDEX(Plan!H5:H304,MATCH(Budget!B30,Plan!B5:B304,1)),Budget!B31)} -> 3511.3
A17: Objectif atteint le | B17: {=IFERROR(INDEX(Plan!B5:B304,MATCH(1,Plan!R5:R304,0)),"Non atteint")} -> Non atteint
A18: Statut | B18: =IF(B16>=B14,"Objectif tenu","Objectif NON tenu : réduire dépenses ou décaler la date") -> Objectif NON tenu : réduire dépenses ou décaler la date
A20: FONDS D'URGENCE
A21: Cible | B21: =Budget!B32 -> 4000
A22: Cible atteinte le | B22: {=IFERROR(INDEX(Plan!B5:B304,MATCH(1,Plan!S5:S304,0)),"Non atteint (25 ans)")} -> 46692
A24: DETTES
A25: Sans dette le (avec le plan) | B25: {=IF(Crédits!C11<=0,"Aucune dette",IFERROR(INDEX(Plan!B5:B304,MATCH(1,Plan!T5:T304,0)),"Au-delà de 25 ans"))} -> 47088
A26: Intérêts payés sans remb. anticipé | B26: =SUM(Calcul!BB3:BB302) -> 1480.9951 | C26: Estimation TAEG/12
A27: Intérêts payés avec le plan | B27: =SUM(Calcul!BA3:BA302) -> 1086.6235
A28: Intérêts économisés | B28: =B26-B27 -> 394.37161 | C28: Avant éventuelles IRA
A30: ÉPARGNE (horizon 12 mois)
A31: Épargne libre cumulée à 12 mois | B31: =Plan!O16 -> 264.52
A32: Fonds d'urgence à 12 mois | B32: =Plan!J16 -> 4000
A33: Dettes restantes à 12 mois | B33: =Plan!P16 -> 9615.07
A34: Mois avec budget négatif | B34: =COUNTIF(Plan!Q5:Q304,"Budget négatif !") -> 0 | C34: Doit être 0
A36: SUIVI RÉEL (dernier mois saisi)
A37: Dernier mois renseigné | B37: {=IF(MAX('Suivi réel'!V6:V29)=0,"Aucune saisie",INDEX('Suivi réel'!A:A,MAX('Suivi réel'!V6:V29)))} -> Aucune saisie
A38: Écart dettes (réel − prévu) | B38: {=IF(MAX('Suivi réel'!V6:V29)=0,0,INDEX('Suivi réel'!O:O,MAX('Suivi réel'!V6:V29)))} -> 0
A39: Écart épargne (réel − prévu) | B39: {=IF(MAX('Suivi réel'!V6:V29)=0,0,INDEX('Suivi réel'!R:R,MAX('Suivi réel'!V6:V29)))} -> 0
A40: Statut | B40: {=IF(MAX('Suivi réel'!V6:V29)=0,"—",INDEX('Suivi réel'!U:U,MAX('Suivi réel'!V6:V29)))} -> —

Sheet Budget
A1: Budget mensuel & paramètres
A3: REVENUS NETS MENSUELS
A4: Salaire net (après impôt à la source) | B4: 2800 | C4: Valeurs d'exemple : remplacez par vos chiffres
A5: Primes / 13e mois (lissés par mois) | B5: 0
A6: Autres revenus | B6: 100
A7: Total revenus | B7: =SUM(B4:B6) -> 2900
A9: CHARGES FIXES (hors mensualités de crédit)
A10: Loyer | B10: 850
A11: Charges / énergie | B11: 60
A12: Assurances (habitation, santé...) | B12: 35
A13: Internet / mobile | B13: 30
A14: Transport (Navigo, carburant...) | B14: 75
A15: Abonnements (streaming, sport...) | B15: 25
A16: Impôts / taxes mensualisés | B16: 0
A17: Autres charges fixes | B17: 0
A18: Total charges fixes | B18: =SUM(B10:B17) -> 1075
A20: DÉPENSES VARIABLES (moyenne sur 3 mois)
A21: Courses | B21: 350
A22: Loisirs / sorties / restaurants | B22: 150
A23: Shopping | B23: 100
A24: Divers | B24: 50
A25: Total dépenses variables | B25: =SUM(B21:B24) -> 650
A27: PARAMÈTRES DU PLAN
A28: Date de début du plan | B28: 46388 | C28: 1er mois simulé
A29: Objectif épargne déménagement | B29: 4000 | C29: Montant à réunir
A30: Date limite déménagement | B30: 46568 | C30: Plus d'épargne déménagement après cette date
A31: Déjà épargné pour le déménagement | B31: 500 | C31: Montant de départ
A32: Fonds d'urgence cible | B32: 4000 | C32: Conseil : 3 mois de dépenses (voir ligne 33)
A33: Suggestion : 3 mois de dépenses | B33: =3*(B18+B25+Crédits!E11) -> 7369.35 | C33: Charges + variables + mensualités, x3
A34: Épargne de précaution déjà disponible | B34: 800 | C34: Montant de départ du fonds d'urgence
A35: Taux seuil (épargne sans risque) | B35: 0.024 | C35: EXEMPLE : mettez le taux actuel du Livret A. Crédit au TAEG supérieur = remb. anticipé rentable
A36: % du reste affecté au remb. anticipé | B36: 0.6 | C36: Le reste va en épargne libre (0 % = aucun remb. anticipé)

Sheet Crédits
A1: Mes crédits
A2: Remplissez une ligne par crédit (jaune). Laissez vides les lignes inutilisées. Valeurs d'exemple à remplacer.
A4: Nom du crédit | B4: Type | C4: Capital restant dû | D4: TAEG | E4: Mensualité | F4: Durée restante (mois) | G4: Coût total restant | H4: Intérêts restants estimés | I4: Date de fin prévue | J4: Remb. anticipé rentable ? | K4: Priorité remb. anticipé | L4: Conseil
A5: Prêt auto | B5: Prêt affecté | C5: 8200 | D5: 0.049 | E5: 245.3 | G5: =IF(C5="","",E5*F5) -> 0 | H5: =IF(C5="","",MAX(0,E5*F5-C5)) -> 0 | I5: =IF(OR(C5="",F5=""),"",EDATE(Budget!$B$28,F5)) | J5: =IF(N(C5)<=0,"",IF(N(D5)>Budget!$B$35,"Oui","Non")) -> Oui | K5: =IF(J5="Oui",COUNTIFS($J$5:$J$10,"Oui",$D$5:$D$10,">"&D5)+COUNTIFS($J$4:J4,"Oui",$D$4:D4,D5)+1,"") -> 3 | L5: =IF(N(C5)<=0,"",IF(N(D5)>=0.1,"Taux élevé : à solder en priorité",IF(J5="Oui","Remb. anticipé intéressant (vérifier IRA)","Garder, épargner plutôt"))) -> Remb. anticipé intéressant (vérifier IRA)
A6: Carte revolving | B6: Revolving | C6: 1850 | D6: 0.189 | E6: 72.4 | G6: =IF(C6="","",E6*F6) -> 0 | H6: =IF(C6="","",MAX(0,E6*F6-C6)) -> 0 | I6: =IF(OR(C6="",F6=""),"",EDATE(Budget!$B$28,F6)) | J6: =IF(N(C6)<=0,"",IF(N(D6)>Budget!$B$35,"Oui","Non")) -> Oui | K6: =IF(J6="Oui",COUNTIFS($J$5:$J$10,"Oui",$D$5:$D$10,">"&D6)+COUNTIFS($J$4:J5,"Oui",$D$4:D5,D6)+1,"") -> 1 | L6: =IF(N(C6)<=0,"",IF(N(D6)>=0.1,"Taux élevé : à solder en priorité",IF(J6="Oui","Remb. anticipé intéressant (vérifier IRA)","Garder, épargner plutôt"))) -> Taux élevé : à solder en priorité
A7: Prêt travaux | B7: Prêt personnel | C7: 3400 | D7: 0.0615 | E7: 118.75 | G7: =IF(C7="","",E7*F7) -> 0 | H7: =IF(C7="","",MAX(0,E7*F7-C7)) -> 0 | I7: =IF(OR(C7="",F7=""),"",EDATE(Budget!$B$28,F7)) | J7: =IF(N(C7)<=0,"",IF(N(D7)>Budget!$B$35,"Oui","Non")) -> Oui | K7: =IF(J7="Oui",COUNTIFS($J$5:$J$10,"Oui",$D$5:$D$10,">"&D7)+COUNTIFS($J$4:J6,"Oui",$D$4:D6,D7)+1,"") -> 2 | L7: =IF(N(C7)<=0,"",IF(N(D7)>=0.1,"Taux élevé : à solder en priorité",IF(J7="Oui","Remb. anticipé intéressant (vérifier IRA)","Garder, épargner plutôt"))) -> Remb. anticipé intéressant (vérifier IRA)
A8: Prêt étudiant | B8: Prêt étudiant | C8: 2100 | D8: 0.012 | E8: 95 | G8: =IF(C8="","",E8*F8) -> 0 | H8: =IF(C8="","",MAX(0,E8*F8-C8)) -> 0 | I8: =IF(OR(C8="",F8=""),"",EDATE(Budget!$B$28,F8)) | J8: =IF(N(C8)<=0,"",IF(N(D8)>Budget!$B$35,"Oui","Non")) -> Non | K8: =IF(J8="Oui",COUNTIFS($J$5:$J$10,"Oui",$D$5:$D$10,">"&D8)+COUNTIFS($J$4:J7,"Oui",$D$4:D7,D8)+1,"") | L8: =IF(N(C8)<=0,"",IF(N(D8)>=0.1,"Taux élevé : à solder en priorité",IF(J8="Oui","Remb. anticipé intéressant (vérifier IRA)","Garder, épargner plutôt"))) -> Garder, épargner plutôt
A9: Dette perso A | B9: Dette personnelle | C9: 600 | D9: 0 | E9: 150 | G9: =IF(C9="","",E9*F9) -> 0 | H9: =IF(C9="","",MAX(0,E9*F9-C9)) -> 0 | I9: =IF(OR(C9="",F9=""),"",EDATE(Budget!$B$28,F9)) | J9: =IF(N(C9)<=0,"",IF(N(D9)>Budget!$B$35,"Oui","Non")) -> Non | K9: =IF(J9="Oui",COUNTIFS($J$5:$J$10,"Oui",$D$5:$D$10,">"&D9)+COUNTIFS($J$4:J8,"Oui",$D$4:D8,D9)+1,"") | L9: =IF(N(C9)<=0,"",IF(N(D9)>=0.1,"Taux élevé : à solder en priorité",IF(J9="Oui","Remb. anticipé intéressant (vérifier IRA)","Garder, épargner plutôt"))) -> Garder, épargner plutôt
A10: Dette perso B | B10: Dette personnelle | C10: 250 | D10: 0 | E10: 50 | G10: =IF(C10="","",E10*F10) -> 0 | H10: =IF(C10="","",MAX(0,E10*F10-C10)) -> 0 | I10: =IF(OR(C10="",F10=""),"",EDATE(Budget!$B$28,F10)) | J10: =IF(N(C10)<=0,"",IF(N(D10)>Budget!$B$35,"Oui","Non")) -> Non | K10: =IF(J10="Oui",COUNTIFS($J$5:$J$10,"Oui",$D$5:$D$10,">"&D10)+COUNTIFS($J$4:J9,"Oui",$D$4:D9,D10)+1,"") | L10: =IF(N(C10)<=0,"",IF(N(D10)>=0.1,"Taux élevé : à solder en priorité",IF(J10="Oui","Remb. anticipé intéressant (vérifier IRA)","Garder, épargner plutôt"))) -> Garder, épargner plutôt
A11: TOTAL | C11: =SUM(C5:C10) -> 16400 | D11: =IFERROR(SUMPRODUCT(C5:C10,D5:D10)/C11,0) -> 0.060106707 | E11: =SUM(E5:E10) -> 731.45 | G11: =SUM(G5:G10) -> 0 | H11: =SUM(H5:H10) -> 0
A13: TAEG : taux annuel effectif global, indiqué sur l'offre de prêt ou le relevé annuel.
A14: Priorité 1 = crédit à rembourser par anticipation en premier (TAEG le plus élevé, au-dessus du taux seuil).

Sheet Suivi réel
A1: État des lieux : ma progression réelle
A2: Chaque début de mois, relevez vos soldes réels (banque) et remplissez les cellules JAUNES de la ligne du mois. Le reste se calcule et se compare au Plan.
A4: MOIS | B4: BUDGET RÉEL DU MOIS | D4: SOLDES D'ÉPARGNE RÉELS (fin de mois) | G4: CAPITAL RESTANT DÛ RÉEL (relevé banque) | M4: COMPARAISON AVEC LE PLAN (automatique) | X4: COMMENT FAIRE CHAQUE MOIS
A5: Mois | B5: Revenus réels | C5: Dépenses réelles (hors crédits) | D5: Épargne déménagement | E5: Fonds d'urgence | F5: Épargne libre | G5: =IF(Crédits!A5="","Crédit 1",Crédits!A5) -> Prêt auto | H5: =IF(Crédits!A6="","Crédit 2",Crédits!A6) -> Carte revolving | I5: =IF(Crédits!A7="","Crédit 3",Crédits!A7) -> Prêt travaux | J5: =IF(Crédits!A8="","Crédit 4",Crédits!A8) -> Prêt étudiant | K5: =IF(Crédits!A9="","Crédit 5",Crédits!A9) -> Dette perso A | L5: =IF(Crédits!A10="","Crédit 6",Crédits!A10) -> Dette perso B | M5: Dettes réelles | N5: Dettes prévues | O5: Écart dettes | P5: Épargne réelle totale | Q5: Épargne prévue totale | R5: Écart épargne | S5: % objectif déménag. | T5: % dettes remboursées | U5: Statut | X5: 1. Ouvrez vos comptes en fin de mois.
A6: =Plan!B5 -> 46388 | M6: =IF(COUNT(B6:L6)>0,SUM(G6:L6),"") | N6: =IF(COUNT(B6:L6)>0,Plan!P5,"") | O6: =IF(COUNT(B6:L6)>0,M6-N6,"") | P6: =IF(COUNT(B6:L6)>0,SUM(D6:F6),"") | Q6: =IF(COUNT(B6:L6)>0,Plan!H5+Plan!J5+Plan!O5,"") | R6: =IF(COUNT(B6:L6)>0,P6-Q6,"") | S6: =IF(COUNT(B6:L6)>0,IFERROR(MIN(1,D6/Budget!$B$29),0),"") | T6: =IF(COUNT(B6:L6)>0,IFERROR(MAX(0,1-M6/Crédits!$C$11),0),"") | U6: =IF(COUNT(B6:L6)>0,IF(AND(O6<=10,R6>=-10),"✅ Dans les temps",IF(AND(O6>10,R6<-10),"🔴 En retard","🟠 Mitigé")),"") | V6: =IF(COUNT(B6:L6)>0,ROW(),0) -> 0 | X6: 2. Remplissez la ligne du mois (cellules jaunes).
A7: =Plan!B6 -> 46419 | M7: =IF(COUNT(B7:L7)>0,SUM(G7:L7),"") | N7: =IF(COUNT(B7:L7)>0,Plan!P6,"") | O7: =IF(COUNT(B7:L7)>0,M7-N7,"") | P7: =IF(COUNT(B7:L7)>0,SUM(D7:F7),"") | Q7: =IF(COUNT(B7:L7)>0,Plan!H6+Plan!J6+Plan!O6,"") | R7: =IF(COUNT(B7:L7)>0,P7-Q7,"") | S7: =IF(COUNT(B7:L7)>0,IFERROR(MIN(1,D7/Budget!$B$29),0),"") | T7: =IF(COUNT(B7:L7)>0,IFERROR(MAX(0,1-M7/Crédits!$C$11),0),"") | U7: =IF(COUNT(B7:L7)>0,IF(AND(O7<=10,R7>=-10),"✅ Dans les temps",IF(AND(O7>10,R7<-10),"🔴 En retard","🟠 Mitigé")),"") | V7: =IF(COUNT(B7:L7)>0,ROW(),0) -> 0 | X7: 3. Lisez l'écart et le statut.
A8: =Plan!B7 -> 46447 | M8: =IF(COUNT(B8:L8)>0,SUM(G8:L8),"") | N8: =IF(COUNT(B8:L8)>0,Plan!P7,"") | O8: =IF(COUNT(B8:L8)>0,M8-N8,"") | P8: =IF(COUNT(B8:L8)>0,SUM(D8:F8),"") | Q8: =IF(COUNT(B8:L8)>0,Plan!H7+Plan!J7+Plan!O7,"") | R8: =IF(COUNT(B8:L8)>0,P8-Q8,"") | S8: =IF(COUNT(B8:L8)>0,IFERROR(MIN(1,D8/Budget!$B$29),0),"") | T8: =IF(COUNT(B8:L8)>0,IFERROR(MAX(0,1-M8/Crédits!$C$11),0),"") | U8: =IF(COUNT(B8:L8)>0,IF(AND(O8<=10,R8>=-10),"✅ Dans les temps",IF(AND(O8>10,R8<-10),"🔴 En retard","🟠 Mitigé")),"") | V8: =IF(COUNT(B8:L8)>0,ROW(),0) -> 0
A9: =Plan!B8 -> 46478 | M9: =IF(COUNT(B9:L9)>0,SUM(G9:L9),"") | N9: =IF(COUNT(B9:L9)>0,Plan!P8,"") | O9: =IF(COUNT(B9:L9)>0,M9-N9,"") | P9: =IF(COUNT(B9:L9)>0,SUM(D9:F9),"") | Q9: =IF(COUNT(B9:L9)>0,Plan!H8+Plan!J8+Plan!O8,"") | R9: =IF(COUNT(B9:L9)>0,P9-Q9,"") | S9: =IF(COUNT(B9:L9)>0,IFERROR(MIN(1,D9/Budget!$B$29),0),"") | T9: =IF(COUNT(B9:L9)>0,IFERROR(MAX(0,1-M9/Crédits!$C$11),0),"") | U9: =IF(COUNT(B9:L9)>0,IF(AND(O9<=10,R9>=-10),"✅ Dans les temps",IF(AND(O9>10,R9<-10),"🔴 En retard","🟠 Mitigé")),"") | V9: =IF(COUNT(B9:L9)>0,ROW(),0) -> 0 | X9: Écart dettes : vert si ≤ prévu.
A10: =Plan!B9 -> 46508 | M10: =IF(COUNT(B10:L10)>0,SUM(G10:L10),"") | N10: =IF(COUNT(B10:L10)>0,Plan!P9,"") | O10: =IF(COUNT(B10:L10)>0,M10-N10,"") | P10: =IF(COUNT(B10:L10)>0,SUM(D10:F10),"") | Q10: =IF(COUNT(B10:L10)>0,Plan!H9+Plan!J9+Plan!O9,"") | R10: =IF(COUNT(B10:L10)>0,P10-Q10,"") | S10: =IF(COUNT(B10:L10)>0,IFERROR(MIN(1,D10/Budget!$B$29),0),"") | T10: =IF(COUNT(B10:L10)>0,IFERROR(MAX(0,1-M10/Crédits!$C$11),0),"") | U10: =IF(COUNT(B10:L10)>0,IF(AND(O10<=10,R10>=-10),"✅ Dans les temps",IF(AND(O10>10,R10<-10),"🔴 En retard","🟠 Mitigé")),"") | V10: =IF(COUNT(B10:L10)>0,ROW(),0) -> 0 | X10: Écart épargne : vert si ≥ prévu.
A11: =Plan!B10 -> 46539 | M11: =IF(COUNT(B11:L11)>0,SUM(G11:L11),"") | N11: =IF(COUNT(B11:L11)>0,Plan!P10,"") | O11: =IF(COUNT(B11:L11)>0,M11-N11,"") | P11: =IF(COUNT(B11:L11)>0,SUM(D11:F11),"") | Q11: =IF(COUNT(B11:L11)>0,Plan!H10+Plan!J10+Plan!O10,"") | R11: =IF(COUNT(B11:L11)>0,P11-Q11,"") | S11: =IF(COUNT(B11:L11)>0,IFERROR(MIN(1,D11/Budget!$B$29),0),"") | T11: =IF(COUNT(B11:L11)>0,IFERROR(MAX(0,1-M11/Crédits!$C$11),0),"") | U11: =IF(COUNT(B11:L11)>0,IF(AND(O11<=10,R11>=-10),"✅ Dans les temps",IF(AND(O11>10,R11<-10),"🔴 En retard","🟠 Mitigé")),"") | V11: =IF(COUNT(B11:L11)>0,ROW(),0) -> 0 | X11: Mois en cours surligné en jaune.
A12: =Plan!B11 -> 46569 | M12: =IF(COUNT(B12:L12)>0,SUM(G12:L12),"") | N12: =IF(COUNT(B12:L12)>0,Plan!P11,"") | O12: =IF(COUNT(B12:L12)>0,M12-N12,"") | P12: =IF(COUNT(B12:L12)>0,SUM(D12:F12),"") | Q12: =IF(COUNT(B12:L12)>0,Plan!H11+Plan!J11+Plan!O11,"") | R12: =IF(COUNT(B12:L12)>0,P12-Q12,"") | S12: =IF(COUNT(B12:L12)>0,IFERROR(MIN(1,D12/Budget!$B$29),0),"") | T12: =IF(COUNT(B12:L12)>0,IFERROR(MAX(0,1-M12/Crédits!$C$11),0),"") | U12: =IF(COUNT(B12:L12)>0,IF(AND(O12<=10,R12>=-10),"✅ Dans les temps",IF(AND(O12>10,R12<-10),"🔴 En retard","🟠 Mitigé")),"") | V12: =IF(COUNT(B12:L12)>0,ROW(),0) -> 0 | X12: Une colonne vide = laissez vide.
A13: =Plan!B12 -> 46600 | M13: =IF(COUNT(B13:L13)>0,SUM(G13:L13),"") | N13: =IF(COUNT(B13:L13)>0,Plan!P12,"") | O13: =IF(COUNT(B13:L13)>0,M13-N13,"") | P13: =IF(COUNT(B13:L13)>0,SUM(D13:F13),"") | Q13: =IF(COUNT(B13:L13)>0,Plan!H12+Plan!J12+Plan!O12,"") | R13: =IF(COUNT(B13:L13)>0,P13-Q13,"") | S13: =IF(COUNT(B13:L13)>0,IFERROR(MIN(1,D13/Budget!$B$29),0),"") | T13: =IF(COUNT(B13:L13)>0,IFERROR(MAX(0,1-M13/Crédits!$C$11),0),"") | U13: =IF(COUNT(B13:L13)>0,IF(AND(O13<=10,R13>=-10),"✅ Dans les temps",IF(AND(O13>10,R13<-10),"🔴 En retard","🟠 Mitigé")),"") | V13: =IF(COUNT(B13:L13)>0,ROW(),0) -> 0
A14: =Plan!B13 -> 46631 | M14: =IF(COUNT(B14:L14)>0,SUM(G14:L14),"") | N14: =IF(COUNT(B14:L14)>0,Plan!P13,"") | O14: =IF(COUNT(B14:L14)>0,M14-N14,"") | P14: =IF(COUNT(B14:L14)>0,SUM(D14:F14),"") | Q14: =IF(COUNT(B14:L14)>0,Plan!H13+Plan!J13+Plan!O13,"") | R14: =IF(COUNT(B14:L14)>0,P14-Q14,"") | S14: =IF(COUNT(B14:L14)>0,IFERROR(MIN(1,D14/Budget!$B$29),0),"") | T14: =IF(COUNT(B14:L14)>0,IFERROR(MAX(0,1-M14/Crédits!$C$11),0),"") | U14: =IF(COUNT(B14:L14)>0,IF(AND(O14<=10,R14>=-10),"✅ Dans les temps",IF(AND(O14>10,R14<-10),"🔴 En retard","🟠 Mitigé")),"") | V14: =IF(COUNT(B14:L14)>0,ROW(),0) -> 0 | X14: Si vous prenez du retard, ajustez
A15: =Plan!B14 -> 46661 | M15: =IF(COUNT(B15:L15)>0,SUM(G15:L15),"") | N15: =IF(COUNT(B15:L15)>0,Plan!P14,"") | O15: =IF(COUNT(B15:L15)>0,M15-N15,"") | P15: =IF(COUNT(B15:L15)>0,SUM(D15:F15),"") | Q15: =IF(COUNT(B15:L15)>0,Plan!H14+Plan!J14+Plan!O14,"") | R15: =IF(COUNT(B15:L15)>0,P15-Q15,"") | S15: =IF(COUNT(B15:L15)>0,IFERROR(MIN(1,D15/Budget!$B$29),0),"") | T15: =IF(COUNT(B15:L15)>0,IFERROR(MAX(0,1-M15/Crédits!$C$11),0),"") | U15: =IF(COUNT(B15:L15)>0,IF(AND(O15<=10,R15>=-10),"✅ Dans les temps",IF(AND(O15>10,R15<-10),"🔴 En retard","🟠 Mitigé")),"") | V15: =IF(COUNT(B15:L15)>0,ROW(),0) -> 0 | X15: Budget (dépenses) pour recalculer.
A16: =Plan!B15 -> 46692 | M16: =IF(COUNT(B16:L16)>0,SUM(G16:L16),"") | N16: =IF(COUNT(B16:L16)>0,Plan!P15,"") | O16: =IF(COUNT(B16:L16)>0,M16-N16,"") | P16: =IF(COUNT(B16:L16)>0,SUM(D16:F16),"") | Q16: =IF(COUNT(B16:L16)>0,Plan!H15+Plan!J15+Plan!O15,"") | R16: =IF(COUNT(B16:L16)>0,P16-Q16,"") | S16: =IF(COUNT(B16:L16)>0,IFERROR(MIN(1,D16/Budget!$B$29),0),"") | T16: =IF(COUNT(B16:L16)>0,IFERROR(MAX(0,1-M16/Crédits!$C$11),0),"") | U16: =IF(COUNT(B16:L16)>0,IF(AND(O16<=10,R16>=-10),"✅ Dans les temps",IF(AND(O16>10,R16<-10),"🔴 En retard","🟠 Mitigé")),"") | V16: =IF(COUNT(B16:L16)>0,ROW(),0) -> 0
A17: =Plan!B16 -> 46722 | M17: =IF(COUNT(B17:L17)>0,SUM(G17:L17),"") | N17: =IF(COUNT(B17:L17)>0,Plan!P16,"") | O17: =IF(COUNT(B17:L17)>0,M17-N17,"") | P17: =IF(COUNT(B17:L17)>0,SUM(D17:F17),"") | Q17: =IF(COUNT(B17:L17)>0,Plan!H16+Plan!J16+Plan!O16,"") | R17: =IF(COUNT(B17:L17)>0,P17-Q17,"") | S17: =IF(COUNT(B17:L17)>0,IFERROR(MIN(1,D17/Budget!$B$29),0),"") | T17: =IF(COUNT(B17:L17)>0,IFERROR(MAX(0,1-M17/Crédits!$C$11),0),"") | U17: =IF(COUNT(B17:L17)>0,IF(AND(O17<=10,R17>=-10),"✅ Dans les temps",IF(AND(O17>10,R17<-10),"🔴 En retard","🟠 Mitigé")),"") | V17: =IF(COUNT(B17:L17)>0,ROW(),0) -> 0
A18: =Plan!B17 -> 46753 | M18: =IF(COUNT(B18:L18)>0,SUM(G18:L18),"") | N18: =IF(COUNT(B18:L18)>0,Plan!P17,"") | O18: =IF(COUNT(B18:L18)>0,M18-N18,"") | P18: =IF(COUNT(B18:L18)>0,SUM(D18:F18),"") | Q18: =IF(COUNT(B18:L18)>0,Plan!H17+Plan!J17+Plan!O17,"") | R18: =IF(COUNT(B18:L18)>0,P18-Q18,"") | S18: =IF(COUNT(B18:L18)>0,IFERROR(MIN(1,D18/Budget!$B$29),0),"") | T18: =IF(COUNT(B18:L18)>0,IFERROR(MAX(0,1-M18/Crédits!$C$11),0),"") | U18: =IF(COUNT(B18:L18)>0,IF(AND(O18<=10,R18>=-10),"✅ Dans les temps",IF(AND(O18>10,R18<-10),"🔴 En retard","🟠 Mitigé")),"") | V18: =IF(COUNT(B18:L18)>0,ROW(),0) -> 0
A19: =Plan!B18 -> 46784 | M19: =IF(COUNT(B19:L19)>0,SUM(G19:L19),"") | N19: =IF(COUNT(B19:L19)>0,Plan!P18,"") | O19: =IF(COUNT(B19:L19)>0,M19-N19,"") | P19: =IF(COUNT(B19:L19)>0,SUM(D19:F19),"") | Q19: =IF(COUNT(B19:L19)>0,Plan!H18+Plan!J18+Plan!O18,"") | R19: =IF(COUNT(B19:L19)>0,P19-Q19,"") | S19: =IF(COUNT(B19:L19)>0,IFERROR(MIN(1,D19/Budget!$B$29),0),"") | T19: =IF(COUNT(B19:L19)>0,IFERROR(MAX(0,1-M19/Crédits!$C$11),0),"") | U19: =IF(COUNT(B19:L19)>0,IF(AND(O19<=10,R19>=-10),"✅ Dans les temps",IF(AND(O19>10,R19<-10),"🔴 En retard","🟠 Mitigé")),"") | V19: =IF(COUNT(B19:L19)>0,ROW(),0) -> 0
A20: =Plan!B19 -> 46813 | M20: =IF(COUNT(B20:L20)>0,SUM(G20:L20),"") | N20: =IF(COUNT(B20:L20)>0,Plan!P19,"") | O20: =IF(COUNT(B20:L20)>0,M20-N20,"") | P20: =IF(COUNT(B20:L20)>0,SUM(D20:F20),"") | Q20: =IF(COUNT(B20:L20)>0,Plan!H19+Plan!J19+Plan!O19,"") | R20: =IF(COUNT(B20:L20)>0,P20-Q20,"") | S20: =IF(COUNT(B20:L20)>0,IFERROR(MIN(1,D20/Budget!$B$29),0),"") | T20: =IF(COUNT(B20:L20)>0,IFERROR(MAX(0,1-M20/Crédits!$C$11),0),"") | U20: =IF(COUNT(B20:L20)>0,IF(AND(O20<=10,R20>=-10),"✅ Dans les temps",IF(AND(O20>10,R20<-10),"🔴 En retard","🟠 Mitigé")),"") | V20: =IF(COUNT(B20:L20)>0,ROW(),0) -> 0
A21: =Plan!B20 -> 46844 | M21: =IF(COUNT(B21:L21)>0,SUM(G21:L21),"") | N21: =IF(COUNT(B21:L21)>0,Plan!P20,"") | O21: =IF(COUNT(B21:L21)>0,M21-N21,"") | P21: =IF(COUNT(B21:L21)>0,SUM(D21:F21),"") | Q21: =IF(COUNT(B21:L21)>0,Plan!H20+Plan!J20+Plan!O20,"") | R21: =IF(COUNT(B21:L21)>0,P21-Q21,"") | S21: =IF(COUNT(B21:L21)>0,IFERROR(MIN(1,D21/Budget!$B$29),0),"") | T21: =IF(COUNT(B21:L21)>0,IFERROR(MAX(0,1-M21/Crédits!$C$11),0),"") | U21: =IF(COUNT(B21:L21)>0,IF(AND(O21<=10,R21>=-10),"✅ Dans les temps",IF(AND(O21>10,R21<-10),"🔴 En retard","🟠 Mitigé")),"") | V21: =IF(COUNT(B21:L21)>0,ROW(),0) -> 0
A22: =Plan!B21 -> 46874 | M22: =IF(COUNT(B22:L22)>0,SUM(G22:L22),"") | N22: =IF(COUNT(B22:L22)>0,Plan!P21,"") | O22: =IF(COUNT(B22:L22)>0,M22-N22,"") | P22: =IF(COUNT(B22:L22)>0,SUM(D22:F22),"") | Q22: =IF(COUNT(B22:L22)>0,Plan!H21+Plan!J21+Plan!O21,"") | R22: =IF(COUNT(B22:L22)>0,P22-Q22,"") | S22: =IF(COUNT(B22:L22)>0,IFERROR(MIN(1,D22/Budget!$B$29),0),"") | T22: =IF(COUNT(B22:L22)>0,IFERROR(MAX(0,1-M22/Crédits!$C$11),0),"") | U22: =IF(COUNT(B22:L22)>0,IF(AND(O22<=10,R22>=-10),"✅ Dans les temps",IF(AND(O22>10,R22<-10),"🔴 En retard","🟠 Mitigé")),"") | V22: =IF(COUNT(B22:L22)>0,ROW(),0) -> 0
A23: =Plan!B22 -> 46905 | M23: =IF(COUNT(B23:L23)>0,SUM(G23:L23),"") | N23: =IF(COUNT(B23:L23)>0,Plan!P22,"") | O23: =IF(COUNT(B23:L23)>0,M23-N23,"") | P23: =IF(COUNT(B23:L23)>0,SUM(D23:F23),"") | Q23: =IF(COUNT(B23:L23)>0,Plan!H22+Plan!J22+Plan!O22,"") | R23: =IF(COUNT(B23:L23)>0,P23-Q23,"") | S23: =IF(COUNT(B23:L23)>0,IFERROR(MIN(1,D23/Budget!$B$29),0),"") | T23: =IF(COUNT(B23:L23)>0,IFERROR(MAX(0,1-M23/Crédits!$C$11),0),"") | U23: =IF(COUNT(B23:L23)>0,IF(AND(O23<=10,R23>=-10),"✅ Dans les temps",IF(AND(O23>10,R23<-10),"🔴 En retard","🟠 Mitigé")),"") | V23: =IF(COUNT(B23:L23)>0,ROW(),0) -> 0
A24: =Plan!B23 -> 46935 | M24: =IF(COUNT(B24:L24)>0,SUM(G24:L24),"") | N24: =IF(COUNT(B24:L24)>0,Plan!P23,"") | O24: =IF(COUNT(B24:L24)>0,M24-N24,"") | P24: =IF(COUNT(B24:L24)>0,SUM(D24:F24),"") | Q24: =IF(COUNT(B24:L24)>0,Plan!H23+Plan!J23+Plan!O23,"") | R24: =IF(COUNT(B24:L24)>0,P24-Q24,"") | S24: =IF(COUNT(B24:L24)>0,IFERROR(MIN(1,D24/Budget!$B$29),0),"") | T24: =IF(COUNT(B24:L24)>0,IFERROR(MAX(0,1-M24/Crédits!$C$11),0),"") | U24: =IF(COUNT(B24:L24)>0,IF(AND(O24<=10,R24>=-10),"✅ Dans les temps",IF(AND(O24>10,R24<-10),"🔴 En retard","🟠 Mitigé")),"") | V24: =IF(COUNT(B24:L24)>0,ROW(),0) -> 0
A25: =Plan!B24 -> 46966 | M25: =IF(COUNT(B25:L25)>0,SUM(G25:L25),"") | N25: =IF(COUNT(B25:L25)>0,Plan!P24,"") | O25: =IF(COUNT(B25:L25)>0,M25-N25,"") | P25: =IF(COUNT(B25:L25)>0,SUM(D25:F25),"") | Q25: =IF(COUNT(B25:L25)>0,Plan!H24+Plan!J24+Plan!O24,"") | R25: =IF(COUNT(B25:L25)>0,P25-Q25,"") | S25: =IF(COUNT(B25:L25)>0,IFERROR(MIN(1,D25/Budget!$B$29),0),"") | T25: =IF(COUNT(B25:L25)>0,IFERROR(MAX(0,1-M25/Crédits!$C$11),0),"") | U25: =IF(COUNT(B25:L25)>0,IF(AND(O25<=10,R25>=-10),"✅ Dans les temps",IF(AND(O25>10,R25<-10),"🔴 En retard","🟠 Mitigé")),"") | V25: =IF(COUNT(B25:L25)>0,ROW(),0) -> 0
A26: =Plan!B25 -> 46997 | M26: =IF(COUNT(B26:L26)>0,SUM(G26:L26),"") | N26: =IF(COUNT(B26:L26)>0,Plan!P25,"") | O26: =IF(COUNT(B26:L26)>0,M26-N26,"") | P26: =IF(COUNT(B26:L26)>0,SUM(D26:F26),"") | Q26: =IF(COUNT(B26:L26)>0,Plan!H25+Plan!J25+Plan!O25,"") | R26: =IF(COUNT(B26:L26)>0,P26-Q26,"") | S26: =IF(COUNT(B26:L26)>0,IFERROR(MIN(1,D26/Budget!$B$29),0),"") | T26: =IF(COUNT(B26:L26)>0,IFERROR(MAX(0,1-M26/Crédits!$C$11),0),"") | U26: =IF(COUNT(B26:L26)>0,IF(AND(O26<=10,R26>=-10),"✅ Dans les temps",IF(AND(O26>10,R26<-10),"🔴 En retard","🟠 Mitigé")),"") | V26: =IF(COUNT(B26:L26)>0,ROW(),0) -> 0
A27: =Plan!B26 -> 47027 | M27: =IF(COUNT(B27:L27)>0,SUM(G27:L27),"") | N27: =IF(COUNT(B27:L27)>0,Plan!P26,"") | O27: =IF(COUNT(B27:L27)>0,M27-N27,"") | P27: =IF(COUNT(B27:L27)>0,SUM(D27:F27),"") | Q27: =IF(COUNT(B27:L27)>0,Plan!H26+Plan!J26+Plan!O26,"") | R27: =IF(COUNT(B27:L27)>0,P27-Q27,"") | S27: =IF(COUNT(B27:L27)>0,IFERROR(MIN(1,D27/Budget!$B$29),0),"") | T27: =IF(COUNT(B27:L27)>0,IFERROR(MAX(0,1-M27/Crédits!$C$11),0),"") | U27: =IF(COUNT(B27:L27)>0,IF(AND(O27<=10,R27>=-10),"✅ Dans les temps",IF(AND(O27>10,R27<-10),"🔴 En retard","🟠 Mitigé")),"") | V27: =IF(COUNT(B27:L27)>0,ROW(),0) -> 0
... A29: =Plan!B28 -> 47088 | M29: =IF(COUNT(B29:L29)>0,SUM(G29:L29),"") | N29: =IF(COUNT(B29:L29)>0,Plan!P28,"") | O29: =IF(COUNT(B29:L29)>0,M29-N29,"") | P29: =IF(COUNT(B29:L29)>0,SUM(D29:F29),"") | Q29: =IF(COUNT(B29:L29)>0,Plan!H28+Plan!J28+Plan!O28,"") | R29: =IF(COUNT(B29:L29)>0,P29-Q29,"") | S29: =IF(COUNT(B29:L29)>0,IFERROR(MIN(1,D29/Budget!$B$29),0),"") | T29: =IF(COUNT(B29:L29)>0,IFERROR(MAX(0,1-M29/Crédits!$C$11),0),"") | U29: =IF(COUNT(B29:L29)>0,IF(AND(O29<=10,R29>=-10),"✅ Dans les temps",IF(AND(O29>10,R29<-10),"🔴 En retard","🟠 Mitigé")),"") | V29: =IF(COUNT(B29:L29)>0,ROW(),0) -> 0

Sheet Plan
A1: Plan mois par mois (LECTURE SEULE : rien à remplir ici)
A2: Chaque ligne = 1 mois. Lire de gauche à droite : l'argent disponible est réparti dans l'ordre 1 → 2 → 3 → 4. Pour changer le résultat, modifiez Budget ou Crédits.
A3: PÉRIODE | C3: ① ARGENT DU MOIS : revenus − dépenses − crédits = Disponible | G3: ② DÉMÉNAGEMENT | I3: ③ FONDS D'URGENCE | K3: ④ CE QUI RESTE : remb. anticipé + épargne libre | P3: DETTES | V3: COMMENT LIRE CET ONGLET
A4: Mois | B4: Date | C4: Revenus | D4: Dépenses (fixes + var.) | E4: Mensualités crédits | F4: Disponible | G4: → Déménagement | H4: Cumul déménagement | I4: → Fonds d'urgence | J4: Cumul fonds d'urgence | K4: Reste | L4: → Remb. anticipé | M4: Non utilisé (dettes soldées) | N4: → Épargne libre | O4: Cumul épargne libre | P4: Dettes restantes | Q4: Alerte | R4: flag_dem | S4: flag_fu | T4: flag_dette | V4: Rien à saisir : tout se calcule depuis Budget et Crédits. | AA4: Objectif déménagement | AB4: Cible fonds d'urgence
A5: 1 | B5: =EDATE(Budget!$B$28,A5-1) -> 46388 | C5: =Budget!$B$7 -> 2900 | D5: =Budget!$B$18+Budget!$B$25 -> 1725 | E5: =Calcul!AX3 -> 731.45 | F5: =C5-D5-E5 -> 443.55 | G5: =IF(B5<=Budget!$B$30,MAX(0,MIN(F5,Budget!$B$29-Budget!$B$31)),0) -> 443.55 | H5: =Budget!$B$31+G5 -> 943.55 | I5: =MAX(0,MIN(F5-G5,Budget!$B$32-Budget!$B$34)) -> 0 | J5: =Budget!$B$34+I5 -> 800 | K5: =MAX(0,F5-G5-I5) -> 0 | L5: =K5*Budget!$B$36 -> 0 | M5: =MAX(0,L5-Calcul!AY3) -> 0 | N5: =K5-L5+M5 -> 0 | O5: =0+N5 -> 0 | P5: =Calcul!AZ3 -> 15750.7 | Q5: =IF(F5<0,"Budget négatif !","") | R5: =IF(H5>=Budget!$B$29,1,0) -> 0 | S5: =IF(J5>=Budget!$B$32,1,0) -> 0 | T5: =IF(P5<=0.01,1,0) -> 0 | V5: Chaque mois, le Disponible (①) est réparti dans l'ordre : | AA5: =Budget!$B$29 -> 4000 | AB5: =Budget!$B$32 -> 4000
A6: 2 | B6: =EDATE(Budget!$B$28,A6-1) -> 46419 | C6: =Budget!$B$7 -> 2900 | D6: =Budget!$B$18+Budget!$B$25 -> 1725 | E6: =Calcul!AX4 -> 731.45 | F6: =C6-D6-E6 -> 443.55 | G6: =IF(B6<=Budget!$B$30,MAX(0,MIN(F6,Budget!$B$29-H5)),0) -> 443.55 | H6: =H5+G6 -> 1387.1 | I6: =MAX(0,MIN(F6-G6,Budget!$B$32-J5)) -> 0 | J6: =J5+I6 -> 800 | K6: =MAX(0,F6-G6-I6) -> 0 | L6: =K6*Budget!$B$36 -> 0 | M6: =MAX(0,L6-Calcul!AY4) -> 0 | N6: =K6-L6+M6 -> 0 | O6: =O5+N6 -> 0 | P6: =Calcul!AZ4 -> 15099.25 | Q6: =IF(F6<0,"Budget négatif !","") | R6: =IF(H6>=Budget!$B$29,1,0) -> 0 | S6: =IF(J6>=Budget!$B$32,1,0) -> 0 | T6: =IF(P6<=0.01,1,0) -> 0 | V6: ① Argent du mois | AA6: =Budget!$B$29 -> 4000 | AB6: =Budget!$B$32 -> 4000
A7: 3 | B7: =EDATE(Budget!$B$28,A7-1) -> 46447 | C7: =Budget!$B$7 -> 2900 | D7: =Budget!$B$18+Budget!$B$25 -> 1725 | E7: =Calcul!AX5 -> 731.45 | F7: =C7-D7-E7 -> 443.55 | G7: =IF(B7<=Budget!$B$30,MAX(0,MIN(F7,Budget!$B$29-H6)),0) -> 443.55 | H7: =H6+G7 -> 1830.65 | I7: =MAX(0,MIN(F7-G7,Budget!$B$32-J6)) -> 0 | J7: =J6+I7 -> 800 | K7: =MAX(0,F7-G7-I7) -> 0 | L7: =K7*Budget!$B$36 -> 0 | M7: =MAX(0,L7-Calcul!AY5) -> 0 | N7: =K7-L7+M7 -> 0 | O7: =O6+N7 -> 0 | P7: =Calcul!AZ5 -> 14445.6 | Q7: =IF(F7<0,"Budget négatif !","") | R7: =IF(H7>=Budget!$B$29,1,0) -> 0 | S7: =IF(J7>=Budget!$B$32,1,0) -> 0 | T7: =IF(P7<=0.01,1,0) -> 0 | V7: ② Déménagement, jusqu'à l'objectif | AA7: =Budget!$B$29 -> 4000 | AB7: =Budget!$B$32 -> 4000
A8: 4 | B8: =EDATE(Budget!$B$28,A8-1) -> 46478 | C8: =Budget!$B$7 -> 2900 | D8: =Budget!$B$18+Budget!$B$25 -> 1725 | E8: =Calcul!AX6 -> 731.45 | F8: =C8-D8-E8 -> 443.55 | G8: =IF(B8<=Budget!$B$30,MAX(0,MIN(F8,Budget!$B$29-H7)),0) -> 443.55 | H8: =H7+G8 -> 2274.2 | I8: =MAX(0,MIN(F8-G8,Budget!$B$32-J7)) -> 0 | J8: =J7+I8 -> 800 | K8: =MAX(0,F8-G8-I8) -> 0 | L8: =K8*Budget!$B$36 -> 0 | M8: =MAX(0,L8-Calcul!AY6) -> 0 | N8: =K8-L8+M8 -> 0 | O8: =O7+N8 -> 0 | P8: =Calcul!AZ6 -> 13789.77 | Q8: =IF(F8<0,"Budget négatif !","") | R8: =IF(H8>=Budget!$B$29,1,0) -> 0 | S8: =IF(J8>=Budget!$B$32,1,0) -> 0 | T8: =IF(P8<=0.01,1,0) -> 0 | V8: ③ Fonds d'urgence, jusqu'à la cible | AA8: =Budget!$B$29 -> 4000 | AB8: =Budget!$B$32 -> 4000
A9: 5 | B9: =EDATE(Budget!$B$28,A9-1) -> 46508 | C9: =Budget!$B$7 -> 2900 | D9: =Budget!$B$18+Budget!$B$25 -> 1725 | E9: =Calcul!AX7 -> 581.45 | F9: =C9-D9-E9 -> 593.55 | G9: =IF(B9<=Budget!$B$30,MAX(0,MIN(F9,Budget!$B$29-H8)),0) -> 593.55 | H9: =H8+G9 -> 2867.75 | I9: =MAX(0,MIN(F9-G9,Budget!$B$32-J8)) -> 0 | J9: =J8+I9 -> 800 | K9: =MAX(0,F9-G9-I9) -> 0 | L9: =K9*Budget!$B$36 -> 0 | M9: =MAX(0,L9-Calcul!AY7) -> 0 | N9: =K9-L9+M9 -> 0 | O9: =O8+N9 -> 0 | P9: =Calcul!AZ7 -> 13281.73 | Q9: =IF(F9<0,"Budget négatif !","") | R9: =IF(H9>=Budget!$B$29,1,0) -> 0 | S9: =IF(J9>=Budget!$B$32,1,0) -> 0 | T9: =IF(P9<=0.01,1,0) -> 0 | V9: ④ Remb. anticipé + épargne libre | AA9: =Budget!$B$29 -> 4000 | AB9: =Budget!$B$32 -> 4000
A10: 6 | B10: =EDATE(Budget!$B$28,A10-1) -> 46539 | C10: =Budget!$B$7 -> 2900 | D10: =Budget!$B$18+Budget!$B$25 -> 1725 | E10: =Calcul!AX8 -> 531.45 | F10: =C10-D10-E10 -> 643.55 | G10: =IF(B10<=Budget!$B$30,MAX(0,MIN(F10,Budget!$B$29-H9)),0) -> 643.55 | H10: =H9+G10 -> 3511.3 | I10: =MAX(0,MIN(F10-G10,Budget!$B$32-J9)) -> 0 | J10: =J9+I10 -> 800 | K10: =MAX(0,F10-G10-I10) -> 0 | L10: =K10*Budget!$B$36 -> 0 | M10: =MAX(0,L10-Calcul!AY8) -> 0 | N10: =K10-L10+M10 -> 0 | O10: =O9+N10 -> 0 | P10: =Calcul!AZ8 -> 12821.45 | Q10: =IF(F10<0,"Budget négatif !","") | R10: =IF(H10>=Budget!$B$29,1,0) -> 0 | S10: =IF(J10>=Budget!$B$32,1,0) -> 0 | T10: =IF(P10<=0.01,1,0) -> 0 | V10: Dettes restantes | AA10: =Budget!$B$29 -> 4000 | AB10: =Budget!$B$32 -> 4000
A11: 7 | B11: =EDATE(Budget!$B$28,A11-1) -> 46569 | C11: =Budget!$B$7 -> 2900 | D11: =Budget!$B$18+Budget!$B$25 -> 1725 | E11: =Calcul!AX9 -> 531.45 | F11: =C11-D11-E11 -> 643.55 | G11: =IF(B11<=Budget!$B$30,MAX(0,MIN(F11,Budget!$B$29-H10)),0) -> 0 | H11: =H10+G11 -> 3511.3 | I11: =MAX(0,MIN(F11-G11,Budget!$B$32-J10)) -> 643.55 | J11: =J10+I11 -> 1443.55 | K11: =MAX(0,F11-G11-I11) -> 0 | L11: =K11*Budget!$B$36 -> 0 | M11: =MAX(0,L11-Calcul!AY9) -> 0 | N11: =K11-L11+M11 -> 0 | O11: =O10+N11 -> 0 | P11: =Calcul!AZ9 -> 12358.93 | Q11: =IF(F11<0,"Budget négatif !","") | R11: =IF(H11>=Budget!$B$29,1,0) -> 0 | S11: =IF(J11>=Budget!$B$32,1,0) -> 0 | T11: =IF(P11<=0.01,1,0) -> 0 | AA11: =Budget!$B$29 -> 4000 | AB11: =Budget!$B$32 -> 4000
A12: 8 | B12: =EDATE(Budget!$B$28,A12-1) -> 46600 | C12: =Budget!$B$7 -> 2900 | D12: =Budget!$B$18+Budget!$B$25 -> 1725 | E12: =Calcul!AX10 -> 531.45 | F12: =C12-D12-E12 -> 643.55 | G12: =IF(B12<=Budget!$B$30,MAX(0,MIN(F12,Budget!$B$29-H11)),0) -> 0 | H12: =H11+G12 -> 3511.3 | I12: =MAX(0,MIN(F12-G12,Budget!$B$32-J11)) -> 643.55 | J12: =J11+I12 -> 2087.1 | K12: =MAX(0,F12-G12-I12) -> 0 | L12: =K12*Budget!$B$36 -> 0 | M12: =MAX(0,L12-Calcul!AY10) -> 0 | N12: =K12-L12+M12 -> 0 | O12: =O11+N12 -> 0 | P12: =Calcul!AZ10 -> 11894.15 | Q12: =IF(F12<0,"Budget négatif !","") | R12: =IF(H12>=Budget!$B$29,1,0) -> 0 | S12: =IF(J12>=Budget!$B$32,1,0) -> 0 | T12: =IF(P12<=0.01,1,0) -> 0 | V12: Cellule verte = objectif atteint / dette soldée | AA12: =Budget!$B$29 -> 4000 | AB12: =Budget!$B$32 -> 4000
A13: 9 | B13: =EDATE(Budget!$B$28,A13-1) -> 46631 | C13: =Budget!$B$7 -> 2900 | D13: =Budget!$B$18+Budget!$B$25 -> 1725 | E13: =Calcul!AX11 -> 531.45 | F13: =C13-D13-E13 -> 643.55 | G13: =IF(B13<=Budget!$B$30,MAX(0,MIN(F13,Budget!$B$29-H12)),0) -> 0 | H13: =H12+G13 -> 3511.3 | I13: =MAX(0,MIN(F13-G13,Budget!$B$32-J12)) -> 643.55 | J13: =J12+I13 -> 2730.65 | K13: =MAX(0,F13-G13-I13) -> 0 | L13: =K13*Budget!$B$36 -> 0 | M13: =MAX(0,L13-Calcul!AY11) -> 0 | N13: =K13-L13+M13 -> 0 | O13: =O12+N13 -> 0 | P13: =Calcul!AZ11 -> 11427.09 | Q13: =IF(F13<0,"Budget négatif !","") | R13: =IF(H13>=Budget!$B$29,1,0) -> 0 | S13: =IF(J13>=Budget!$B$32,1,0) -> 0 | T13: =IF(P13<=0.01,1,0) -> 0 | V13: Ligne rouge = budget négatif ce mois | AA13: =Budget!$B$29 -> 4000 | AB13: =Budget!$B$32 -> 4000
A14: 10 | B14: =EDATE(Budget!$B$28,A14-1) -> 46661 | C14: =Budget!$B$7 -> 2900 | D14: =Budget!$B$18+Budget!$B$25 -> 1725 | E14: =Calcul!AX12 -> 531.45 | F14: =C14-D14-E14 -> 643.55 | G14: =IF(B14<=Budget!$B$30,MAX(0,MIN(F14,Budget!$B$29-H13)),0) -> 0 | H14: =H13+G14 -> 3511.3 | I14: =MAX(0,MIN(F14-G14,Budget!$B$32-J13)) -> 643.55 | J14: =J13+I14 -> 3374.2 | K14: =MAX(0,F14-G14-I14) -> 0 | L14: =K14*Budget!$B$36 -> 0 | M14: =MAX(0,L14-Calcul!AY12) -> 0 | N14: =K14-L14+M14 -> 0 | O14: =O13+N14 -> 0 | P14: =Calcul!AZ12 -> 10957.72 | Q14: =IF(F14<0,"Budget négatif !","") | R14: =IF(H14>=Budget!$B$29,1,0) -> 0 | S14: =IF(J14>=Budget!$B$32,1,0) -> 0 | T14: =IF(P14<=0.01,1,0) -> 0 | V14: Trait orange = mois de la date limite déménagement | AA14: =Budget!$B$29 -> 4000 | AB14: =Budget!$B$32 -> 4000
A15: 11 | B15: =EDATE(Budget!$B$28,A15-1) -> 46692 | C15: =Budget!$B$7 -> 2900 | D15: =Budget!$B$18+Budget!$B$25 -> 1725 | E15: =Calcul!AX13 -> 531.45 | F15: =C15-D15-E15 -> 643.55 | G15: =IF(B15<=Budget!$B$30,MAX(0,MIN(F15,Budget!$B$29-H14)),0) -> 0 | H15: =H14+G15 -> 3511.3 | I15: =MAX(0,MIN(F15-G15,Budget!$B$32-J14)) -> 625.8 | J15: =J14+I15 -> 4000 | K15: =MAX(0,F15-G15-I15) -> 17.75 | L15: =K15*Budget!$B$36 -> 10.65 | M15: =MAX(0,L15-Calcul!AY13) -> 0 | N15: =K15-L15+M15 -> 7.1 | O15: =O14+N15 -> 7.1 | P15: =Calcul!AZ13 -> 10475.39 | Q15: =IF(F15<0,"Budget négatif !","") | R15: =IF(H15>=Budget!$B$29,1,0) -> 0 | S15: =IF(J15>=Budget!$B$32,1,0) -> 1 | T15: =IF(P15<=0.01,1,0) -> 0 | V15: Colonnes en gras = résultats clés | AA15: =Budget!$B$29 -> 4000 | AB15: =Budget!$B$32 -> 4000
A16: 12 | B16: =EDATE(Budget!$B$28,A16-1) -> 46722 | C16: =Budget!$B$7 -> 2900 | D16: =Budget!$B$18+Budget!$B$25 -> 1725 | E16: =Calcul!AX14 -> 531.45 | F16: =C16-D16-E16 -> 643.55 | G16: =IF(B16<=Budget!$B$30,MAX(0,MIN(F16,Budget!$B$29-H15)),0) -> 0 | H16: =H15+G16 -> 3511.3 | I16: =MAX(0,MIN(F16-G16,Budget!$B$32-J15)) -> 0 | J16: =J15+I16 -> 4000 | K16: =MAX(0,F16-G16-I16) -> 643.55 | L16: =K16*Budget!$B$36 -> 386.13 | M16: =MAX(0,L16-Calcul!AY14) -> 0 | N16: =K16-L16+M16 -> 257.42 | O16: =O15+N16 -> 264.52 | P16: =Calcul!AZ14 -> 9615.07 | Q16: =IF(F16<0,"Budget négatif !","") | R16: =IF(H16>=Budget!$B$29,1,0) -> 0 | S16: =IF(J16>=Budget!$B$32,1,0) -> 1 | T16: =IF(P16<=0.01,1,0) -> 0 | V16: Survolez un titre de colonne pour son explication. | AA16: =Budget!$B$29 -> 4000 | AB16: =Budget!$B$32 -> 4000
A17: 13 | B17: =EDATE(Budget!$B$28,A17-1) -> 46753 | C17: =Budget!$B$7 -> 2900 | D17: =Budget!$B$18+Budget!$B$25 -> 1725 | E17: =Calcul!AX15 -> 531.45 | F17: =C17-D17-E17 -> 643.55 | G17: =IF(B17<=Budget!$B$30,MAX(0,MIN(F17,Budget!$B$29-H16)),0) -> 0 | H17: =H16+G17 -> 3511.3 | I17: =MAX(0,MIN(F17-G17,Budget!$B$32-J16)) -> 0 | J17: =J16+I17 -> 4000 | K17: =MAX(0,F17-G17-I17) -> 643.55 | L17: =K17*Budget!$B$36 -> 386.13 | M17: =MAX(0,L17-Calcul!AY15) -> 0 | N17: =K17-L17+M17 -> 257.42 | O17: =O16+N17 -> 521.94 | P17: =Calcul!AZ15 -> 8746.31 | Q17: =IF(F17<0,"Budget négatif !","") | R17: =IF(H17>=Budget!$B$29,1,0) -> 0 | S17: =IF(J17>=Budget!$B$32,1,0) -> 1 | T17: =IF(P17<=0.01,1,0) -> 0 | AA17: =Budget!$B$29 -> 4000 | AB17: =Budget!$B$32 -> 4000
A18: 14 | B18: =EDATE(Budget!$B$28,A18-1) -> 46784 | C18: =Budget!$B$7 -> 2900 | D18: =Budget!$B$18+Budget!$B$25 -> 1725 | E18: =Calcul!AX16 -> 531.45 | F18: =C18-D18-E18 -> 643.55 | G18: =IF(B18<=Budget!$B$30,MAX(0,MIN(F18,Budget!$B$29-H17)),0) -> 0 | H18: =H17+G18 -> 3511.3 | I18: =MAX(0,MIN(F18-G18,Budget!$B$32-J17)) -> 0 | J18: =J17+I18 -> 4000 | K18: =MAX(0,F18-G18-I18) -> 643.55 | L18: =K18*Budget!$B$36 -> 386.13 | M18: =MAX(0,L18-Calcul!AY16) -> 0 | N18: =K18-L18+M18 -> 257.42 | O18: =O17+N18 -> 779.36 | P18: =Calcul!AZ16 -> 7869 | Q18: =IF(F18<0,"Budget négatif !","") | R18: =IF(H18>=Budget!$B$29,1,0) -> 0 | S18: =IF(J18>=Budget!$B$32,1,0) -> 1 | T18: =IF(P18<=0.01,1,0) -> 0 | AA18: =Budget!$B$29 -> 4000 | AB18: =Budget!$B$32 -> 4000
A19: 15 | B19: =EDATE(Budget!$B$28,A19-1) -> 46813 | C19: =Budget!$B$7 -> 2900 | D19: =Budget!$B$18+Budget!$B$25 -> 1725 | E19: =Calcul!AX17 -> 459.05 | F19: =C19-D19-E19 -> 715.95 | G19: =IF(B19<=Budget!$B$30,MAX(0,MIN(F19,Budget!$B$29-H18)),0) -> 0 | H19: =H18+G19 -> 3511.3 | I19: =MAX(0,MIN(F19-G19,Budget!$B$32-J18)) -> 0 | J19: =J18+I19 -> 4000 | K19: =MAX(0,F19-G19-I19) -> 715.95 | L19: =K19*Budget!$B$36 -> 429.57 | M19: =MAX(0,L19-Calcul!AY17) -> 0 | N19: =K19-L19+M19 -> 286.38 | O19: =O18+N19 -> 1065.74 | P19: =Calcul!AZ17 -> 7012.08 | Q19: =IF(F19<0,"Budget négatif !","") | R19: =IF(H19>=Budget!$B$29,1,0) -> 0 | S19: =IF(J19>=Budget!$B$32,1,0) -> 1 | T19: =IF(P19<=0.01,1,0) -> 0 | AA19: =Budget!$B$29 -> 4000 | AB19: =Budget!$B$32 -> 4000
A20: 16 | B20: =EDATE(Budget!$B$28,A20-1) -> 46844 | C20: =Budget!$B$7 -> 2900 | D20: =Budget!$B$18+Budget!$B$25 -> 1725 | E20: =Calcul!AX18 -> 459.05 | F20: =C20-D20-E20 -> 715.95 | G20: =IF(B20<=Budget!$B$30,MAX(0,MIN(F20,Budget!$B$29-H19)),0) -> 0 | H20: =H19+G20 -> 3511.3 | I20: =MAX(0,MIN(F20-G20,Budget!$B$32-J19)) -> 0 | J20: =J19+I20 -> 4000 | K20: =MAX(0,F20-G20-I20) -> 715.95 | L20: =K20*Budget!$B$36 -> 429.57 | M20: =MAX(0,L20-Calcul!AY18) -> 0 | N20: =K20-L20+M20 -> 286.38 | O20: =O19+N20 -> 1352.12 | P20: =Calcul!AZ18 -> 6151.39 | Q20: =IF(F20<0,"Budget négatif !","") | R20: =IF(H20>=Budget!$B$29,1,0) -> 0 | S20: =IF(J20>=Budget!$B$32,1,0) -> 1 | T20: =IF(P20<=0.01,1,0) -> 0 | AA20: =Budget!$B$29 -> 4000 | AB20: =Budget!$B$32 -> 4000
A21: 17 | B21: =EDATE(Budget!$B$28,A21-1) -> 46874 | C21: =Budget!$B$7 -> 2900 | D21: =Budget!$B$18+Budget!$B$25 -> 1725 | E21: =Calcul!AX19 -> 459.05 | F21: =C21-D21-E21 -> 715.95 | G21: =IF(B21<=Budget!$B$30,MAX(0,MIN(F21,Budget!$B$29-H20)),0) -> 0 | H21: =H20+G21 -> 3511.3 | I21: =MAX(0,MIN(F21-G21,Budget!$B$32-J20)) -> 0 | J21: =J20+I21 -> 4000 | K21: =MAX(0,F21-G21-I21) -> 715.95 | L21: =K21*Budget!$B$36 -> 429.57 | M21: =MAX(0,L21-Calcul!AY19) -> 0 | N21: =K21-L21+M21 -> 286.38 | O21: =O20+N21 -> 1638.5 | P21: =Calcul!AZ19 -> 5286.9 | Q21: =IF(F21<0,"Budget négatif !","") | R21: =IF(H21>=Budget!$B$29,1,0) -> 0 | S21: =IF(J21>=Budget!$B$32,1,0) -> 1 | T21: =IF(P21<=0.01,1,0) -> 0 | AA21: =Budget!$B$29 -> 4000 | AB21: =Budget!$B$32 -> 4000
A22: 18 | B22: =EDATE(Budget!$B$28,A22-1) -> 46905 | C22: =Budget!$B$7 -> 2900 | D22: =Budget!$B$18+Budget!$B$25 -> 1725 | E22: =Calcul!AX20 -> 459.05 | F22: =C22-D22-E22 -> 715.95 | G22: =IF(B22<=Budget!$B$30,MAX(0,MIN(F22,Budget!$B$29-H21)),0) -> 0 | H22: =H21+G22 -> 3511.3 | I22: =MAX(0,MIN(F22-G22,Budget!$B$32-J21)) -> 0 | J22: =J21+I22 -> 4000 | K22: =MAX(0,F22-G22-I22) -> 715.95 | L22: =K22*Budget!$B$36 -> 429.57 | M22: =MAX(0,L22-Calcul!AY20) -> 0 | N22: =K22-L22+M22 -> 286.38 | O22: =O21+N22 -> 1924.88 | P22: =Calcul!AZ20 -> 4418.62 | Q22: =IF(F22<0,"Budget négatif !","") | R22: =IF(H22>=Budget!$B$29,1,0) -> 0 | S22: =IF(J22>=Budget!$B$32,1,0) -> 1 | T22: =IF(P22<=0.01,1,0) -> 0 | AA22: =Budget!$B$29 -> 4000 | AB22: =Budget!$B$32 -> 4000
A23: 19 | B23: =EDATE(Budget!$B$28,A23-1) -> 46935 | C23: =Budget!$B$7 -> 2900 | D23: =Budget!$B$18+Budget!$B$25 -> 1725 | E23: =Calcul!AX21 -> 340.3 | F23: =C23-D23-E23 -> 834.7 | G23: =IF(B23<=Budget!$B$30,MAX(0,MIN(F23,Budget!$B$29-H22)),0) -> 0 | H23: =H22+G23 -> 3511.3 | I23: =MAX(0,MIN(F23-G23,Budget!$B$32-J22)) -> 0 | J23: =J22+I23 -> 4000 | K23: =MAX(0,F23-G23-I23) -> 834.7 | L23: =K23*Budget!$B$36 -> 500.82 | M23: =MAX(0,L23-Calcul!AY21) -> 0 | N23: =K23-L23+M23 -> 333.88 | O23: =O22+N23 -> 2258.76 | P23: =Calcul!AZ21 -> 3594.26 | Q23: =IF(F23<0,"Budget négatif !","") | R23: =IF(H23>=Budget!$B$29,1,0) -> 0 | S23: =IF(J23>=Budget!$B$32,1,0) -> 1 | T23: =IF(P23<=0.01,1,0) -> 0 | AA23: =Budget!$B$29 -> 4000 | AB23: =Budget!$B$32 -> 4000
A24: 20 | B24: =EDATE(Budget!$B$28,A24-1) -> 46966 | C24: =Budget!$B$7 -> 2900 | D24: =Budget!$B$18+Budget!$B$25 -> 1725 | E24: =Calcul!AX22 -> 340.3 | F24: =C24-D24-E24 -> 834.7 | G24: =IF(B24<=Budget!$B$30,MAX(0,MIN(F24,Budget!$B$29-H23)),0) -> 0 | H24: =H23+G24 -> 3511.3 | I24: =MAX(0,MIN(F24-G24,Budget!$B$32-J23)) -> 0 | J24: =J23+I24 -> 4000 | K24: =MAX(0,F24-G24-I24) -> 834.7 | L24: =K24*Budget!$B$36 -> 500.82 | M24: =MAX(0,L24-Calcul!AY22) -> 0 | N24: =K24-L24+M24 -> 333.88 | O24: =O23+N24 -> 2592.64 | P24: =Calcul!AZ22 -> 2766.83 | Q24: =IF(F24<0,"Budget négatif !","") | R24: =IF(H24>=Budget!$B$29,1,0) -> 0 | S24: =IF(J24>=Budget!$B$32,1,0) -> 1 | T24: =IF(P24<=0.01,1,0) -> 0 | AA24: =Budget!$B$29 -> 4000 | AB24: =Budget!$B$32 -> 4000
A25: 21 | B25: =EDATE(Budget!$B$28,A25-1) -> 46997 | C25: =Budget!$B$7 -> 2900 | D25: =Budget!$B$18+Budget!$B$25 -> 1725 | E25: =Calcul!AX23 -> 340.3 | F25: =C25-D25-E25 -> 834.7 | G25: =IF(B25<=Budget!$B$30,MAX(0,MIN(F25,Budget!$B$29-H24)),0) -> 0 | H25: =H24+G25 -> 3511.3 | I25: =MAX(0,MIN(F25-G25,Budget!$B$32-J24)) -> 0 | J25: =J24+I25 -> 4000 | K25: =MAX(0,F25-G25-I25) -> 834.7 | L25: =K25*Budget!$B$36 -> 500.82 | M25: =MAX(0,L25-Calcul!AY23) -> 0 | N25: =K25-L25+M25 -> 333.88 | O25: =O24+N25 -> 2926.52 | P25: =Calcul!AZ23 -> 1936.31 | Q25: =IF(F25<0,"Budget négatif !","") | R25: =IF(H25>=Budget!$B$29,1,0) -> 0 | S25: =IF(J25>=Budget!$B$32,1,0) -> 1 | T25: =IF(P25<=0.01,1,0) -> 0 | AA25: =Budget!$B$29 -> 4000 | AB25: =Budget!$B$32 -> 4000
A26: 22 | B26: =EDATE(Budget!$B$28,A26-1) -> 47027 | C26: =Budget!$B$7 -> 2900 | D26: =Budget!$B$18+Budget!$B$25 -> 1725 | E26: =Calcul!AX24 -> 340.3 | F26: =C26-D26-E26 -> 834.7 | G26: =IF(B26<=Budget!$B$30,MAX(0,MIN(F26,Budget!$B$29-H25)),0) -> 0 | H26: =H25+G26 -> 3511.3 | I26: =MAX(0,MIN(F26-G26,Budget!$B$32-J25)) -> 0 | J26: =J25+I26 -> 4000 | K26: =MAX(0,F26-G26-I26) -> 834.7 | L26: =K26*Budget!$B$36 -> 500.82 | M26: =MAX(0,L26-Calcul!AY24) -> 0 | N26: =K26-L26+M26 -> 333.88 | O26: =O25+N26 -> 3260.4 | P26: =Calcul!AZ24 -> 1102.7 | Q26: =IF(F26<0,"Budget négatif !","") | R26: =IF(H26>=Budget!$B$29,1,0) -> 0 | S26: =IF(J26>=Budget!$B$32,1,0) -> 1 | T26: =IF(P26<=0.01,1,0) -> 0 | AA26: =Budget!$B$29 -> 4000 | AB26: =Budget!$B$32 -> 4000
A27: 23 | B27: =EDATE(Budget!$B$28,A27-1) -> 47058 | C27: =Budget!$B$7 -> 2900 | D27: =Budget!$B$18+Budget!$B$25 -> 1725 | E27: =Calcul!AX25 -> 279.92459 | F27: =C27-D27-E27 -> 895.07541 | G27: =IF(B27<=Budget!$B$30,MAX(0,MIN(F27,Budget!$B$29-H26)),0) -> 0 | H27: =H26+G27 -> 3511.3 | I27: =MAX(0,MIN(F27-G27,Budget!$B$32-J26)) -> 0 | J27: =J26+I27 -> 4000 | K27: =MAX(0,F27-G27-I27) -> 895.07541 | L27: =K27*Budget!$B$36 -> 537.04525 | M27: =MAX(0,L27-Calcul!AY25) -> 0 | N27: =K27-L27+M27 -> 358.03016 | O27: =O26+N27 -> 3618.4302 | P27: =Calcul!AZ25 -> 290.12 | Q27: =IF(F27<0,"Budget négatif !","") | R27: =IF(H27>=Budget!$B$29,1,0) -> 0 | S27: =IF(J27>=Budget!$B$32,1,0) -> 1 | T27: =IF(P27<=0.01,1,0) -> 0 | AA27: =Budget!$B$29 -> 4000 | AB27: =Budget!$B$32 -> 4000
A28: 24 | B28: =EDATE(Budget!$B$28,A28-1) -> 47088 | C28: =Budget!$B$7 -> 2900 | D28: =Budget!$B$18+Budget!$B$25 -> 1725 | E28: =Calcul!AX26 -> 245.3 | F28: =C28-D28-E28 -> 929.7 | G28: =IF(B28<=Budget!$B$30,MAX(0,MIN(F28,Budget!$B$29-H27)),0) -> 0 | H28: =H27+G28 -> 3511.3 | I28: =MAX(0,MIN(F28-G28,Budget!$B$32-J27)) -> 0 | J28: =J27+I28 -> 4000 | K28: =MAX(0,F28-G28-I28) -> 929.7 | L28: =K28*Budget!$B$36 -> 557.82 | M28: =MAX(0,L28-Calcul!AY26) -> 511.82 | N28: =K28-L28+M28 -> 883.7 | O28: =O27+N28 -> 4502.1302 | P28: =Calcul!AZ26 -> 0 | Q28: =IF(F28<0,"Budget négatif !","") | R28: =IF(H28>=Budget!$B$29,1,0) -> 0 | S28: =IF(J28>=Budget!$B$32,1,0) -> 1 | T28: =IF(P28<=0.01,1,0) -> 1 | AA28: =Budget!$B$29 -> 4000 | AB28: =Budget!$B$32 -> 4000
... A304: 300 | B304: =EDATE(Budget!$B$28,A304-1) -> 55488 | C304: =Budget!$B$7 -> 2900 | D304: =Budget!$B$18+Budget!$B$25 -> 1725 | E304: =Calcul!AX302 -> 0 | F304: =C304-D304-E304 -> 1175 | G304: =IF(B304<=Budget!$B$30,MAX(0,MIN(F304,Budget!$B$29-H303)),0) -> 0 | H304: =H303+G304 -> 3511.3 | I304: =MAX(0,MIN(F304-G304,Budget!$B$32-J303)) -> 0 | J304: =J303+I304 -> 4000 | K304: =MAX(0,F304-G304-I304) -> 1175 | L304: =K304*Budget!$B$36 -> 705 | M304: =MAX(0,L304-Calcul!AY302) -> 705 | N304: =K304-L304+M304 -> 1175 | O304: =O303+N304 -> 328802.13 | P304: =Calcul!AZ302 -> 0 | Q304: =IF(F304<0,"Budget négatif !","") | R304: =IF(H304>=Budget!$B$29,1,0) -> 0 | S304: =IF(J304>=Budget!$B$32,1,0) -> 1 | T304: =IF(P304<=0.01,1,0) -> 1 | AA304: =Budget!$B$29 -> 4000 | AB304: =Budget!$B$32 -> 4000

Sheet Calcul
A1: ⚠ Onglet technique : ne rien modifier | B1: =IF(Crédits!A5="","Crédit 1",Crédits!A5) -> Prêt auto | J1: =IF(Crédits!A6="","Crédit 2",Crédits!A6) -> Carte revolving | R1: =IF(Crédits!A7="","Crédit 3",Crédits!A7) -> Prêt travaux | Z1: =IF(Crédits!A8="","Crédit 4",Crédits!A8) -> Prêt étudiant | AH1: =IF(Crédits!A9="","Crédit 5",Crédits!A9) -> Dette perso A | AP1: =IF(Crédits!A10="","Crédit 6",Crédits!A10) -> Dette perso B | AX1: TOTAUX (repris dans l'onglet Plan)
A2: Mois (survolez pour la légende) | B2: Solde début | C2: Intérêts | D2: Mensualité payée | E2: Solde après mens. | F2: Remb. anticipé | G2: Solde fin | H2: Solde fin sans anticip. | I2: Intérêts sans anticip. | J2: Solde début | K2: Intérêts | L2: Mensualité payée | M2: Solde après mens. | N2: Remb. anticipé | O2: Solde fin | P2: Solde fin sans anticip. | Q2: Intérêts sans anticip. | R2: Solde début | S2: Intérêts | T2: Mensualité payée | U2: Solde après mens. | V2: Remb. anticipé | W2: Solde fin | X2: Solde fin sans anticip. | Y2: Intérêts sans anticip. | Z2: Solde début | AA2: Intérêts | AB2: Mensualité payée | AC2: Solde après mens. | AD2: Remb. anticipé | AE2: Solde fin | AF2: Solde fin sans anticip. | AG2: Intérêts sans anticip. | AH2: Solde début | AI2: Intérêts | AJ2: Mensualité payée | AK2: Solde après mens. | AL2: Remb. anticipé | AM2: Solde fin | AN2: Solde fin sans anticip. | AO2: Intérêts sans anticip. | AP2: Solde début | AQ2: Intérêts | AR2: Mensualité payée | AS2: Solde après mens. | AT2: Remb. anticipé | AU2: Solde fin | AV2: Solde fin sans anticip. | AW2: Intérêts sans anticip. | AX2: Total mensualités | AY2: Total remb. anticipé | AZ2: Total dettes fin | BA2: Total intérêts | BB2: Total intérêts sans anticip.
A3: 1 | B3: =MAX(0,N(Crédits!$C$5)) -> 8200 | C3: =B3*N(Crédits!$D$5)/12 -> 33.483333 | D3: =MIN(N(Crédits!$E$5),B3+C3) -> 245.3 | E3: =ROUND(B3+C3-D3,2) -> 7988.18 | F3: =IF(Crédits!$K$5="",0,MAX(0,MIN(E3,Plan!$L$5-(IF(Crédits!$K$6="",0,IF(Crédits!$K$6<Crédits!$K$5,M3,0))+IF(Crédits!$K$7="",0,IF(Crédits!$K$7<Crédits!$K$5,U3,0))+IF(Crédits!$K$8="",0,IF(Crédits!$K$8<Crédits!$K$5,AC3,0))+IF(Crédits!$K$9="",0,IF(Crédits!$K$9<Crédits!$K$5,AK3,0))+IF(Crédits!$K$10="",0,IF(Crédits!$K$10<Crédits!$K$5,AS3,0)))))) -> 0 | G3: =ROUND(E3-F3,2) -> 7988.18 | H3: =ROUND(MAX(0,N(Crédits!$C$5))+I3-MIN(N(Crédits!$E$5),MAX(0,N(Crédits!$C$5))+I3),2) -> 7988.18 | I3: =MAX(0,N(Crédits!$C$5))*N(Crédits!$D$5)/12 -> 33.483333 | J3: =MAX(0,N(Crédits!$C$6)) -> 1850 | K3: =J3*N(Crédits!$D$6)/12 -> 29.1375 | L3: =MIN(N(Crédits!$E$6),J3+K3) -> 72.4 | M3: =ROUND(J3+K3-L3,2) -> 1806.74 | N3: =IF(Crédits!$K$6="",0,MAX(0,MIN(M3,Plan!$L$5-(IF(Crédits!$K$5="",0,IF(Crédits!$K$5<Crédits!$K$6,E3,0))+IF(Crédits!$K$7="",0,IF(Crédits!$K$7<Crédits!$K$6,U3,0))+IF(Crédits!$K$8="",0,IF(Crédits!$K$8<Crédits!$K$6,AC3,0))+IF(Crédits!$K$9="",0,IF(Crédits!$K$9<Crédits!$K$6,AK3,0))+IF(Crédits!$K$10="",0,IF(Crédits!$K$10<Crédits!$K$6,AS3,0)))))) -> 0 | O3: =ROUND(M3-N3,2) -> 1806.74 | P3: =ROUND(MAX(0,N(Crédits!$C$6))+Q3-MIN(N(Crédits!$E$6),MAX(0,N(Crédits!$C$6))+Q3),2) -> 1806.74 | Q3: =MAX(0,N(Crédits!$C$6))*N(Crédits!$D$6)/12 -> 29.1375 | R3: =MAX(0,N(Crédits!$C$7)) -> 3400 | S3: =R3*N(Crédits!$D$7)/12 -> 17.425 | T3: =MIN(N(Crédits!$E$7),R3+S3) -> 118.75 | U3: =ROUND(R3+S3-T3,2) -> 3298.68 | V3: =IF(Crédits!$K$7="",0,MAX(0,MIN(U3,Plan!$L$5-(IF(Crédits!$K$5="",0,IF(Crédits!$K$5<Crédits!$K$7,E3,0))+IF(Crédits!$K$6="",0,IF(Crédits!$K$6<Crédits!$K$7,M3,0))+IF(Crédits!$K$8="",0,IF(Crédits!$K$8<Crédits!$K$7,AC3,0))+IF(Crédits!$K$9="",0,IF(Crédits!$K$9<Crédits!$K$7,AK3,0))+IF(Crédits!$K$10="",0,IF(Crédits!$K$10<Crédits!$K$7,AS3,0)))))) -> 0 | W3: =ROUND(U3-V3,2) -> 3298.68 | X3: =ROUND(MAX(0,N(Crédits!$C$7))+Y3-MIN(N(Crédits!$E$7),MAX(0,N(Crédits!$C$7))+Y3),2) -> 3298.68 | Y3: =MAX(0,N(Crédits!$C$7))*N(Crédits!$D$7)/12 -> 17.425 | Z3: =MAX(0,N(Crédits!$C$8)) -> 2100 | AA3: =Z3*N(Crédits!$D$8)/12 -> 2.1 | AB3: =MIN(N(Crédits!$E$8),Z3+AA3) -> 95 | AC3: =ROUND(Z3+AA3-AB3,2) -> 2007.1 | AD3: =IF(Crédits!$K$8="",0,MAX(0,MIN(AC3,Plan!$L$5-(IF(Crédits!$K$5="",0,IF(Crédits!$K$5<Crédits!$K$8,E3,0))+IF(Crédits!$K$6="",0,IF(Crédits!$K$6<Crédits!$K$8,M3,0))+IF(Crédits!$K$7="",0,IF(Crédits!$K$7<Crédits!$K$8,U3,0))+IF(Crédits!$K$9="",0,IF(Crédits!$K$9<Crédits!$K$8,AK3,0))+IF(Crédits!$K$10="",0,IF(Crédits!$K$10<Crédits!$K$8,AS3,0)))))) -> 0 | AE3: =ROUND(AC3-AD3,2) -> 2007.1 | AF3: =ROUND(MAX(0,N(Crédits!$C$8))+AG3-MIN(N(Crédits!$E$8),MAX(0,N(Crédits!$C$8))+AG3),2) -> 2007.1 | AG3: =MAX(0,N(Crédits!$C$8))*N(Crédits!$D$8)/12 -> 2.1 | AH3: =MAX(0,N(Crédits!$C$9)) -> 600 | AI3: =AH3*N(Crédits!$D$9)/12 -> 0 | AJ3: =MIN(N(Crédits!$E$9),AH3+AI3) -> 150 | AK3: =ROUND(AH3+AI3-AJ3,2) -> 450 | AL3: =IF(Crédits!$K$9="",0,MAX(0,MIN(AK3,Plan!$L$5-(IF(Crédits!$K$5="",0,IF(Crédits!$K$5<Crédits!$K$9,E3,0))+IF(Crédits!$K$6="",0,IF(Crédits!$K$6<Crédits!$K$9,M3,0))+IF(Crédits!$K$7="",0,IF(Crédits!$K$7<Crédits!$K$9,U3,0))+IF(Crédits!$K$8="",0,IF(Crédits!$K$8<Crédits!$K$9,AC3,0))+IF(Crédits!$K$10="",0,IF(Crédits!$K$10<Crédits!$K$9,AS3,0)))))) -> 0 | AM3: =ROUND(AK3-AL3,2) -> 450 | AN3: =ROUND(MAX(0,N(Crédits!$C$9))+AO3-MIN(N(Crédits!$E$9),MAX(0,N(Crédits!$C$9))+AO3),2) -> 450 | AO3: =MAX(0,N(Crédits!$C$9))*N(Crédits!$D$9)/12 -> 0 | AP3: =MAX(0,N(Crédits!$C$10)) -> 250 | AQ3: =AP3*N(Crédits!$D$10)/12 -> 0 | AR3: =MIN(N(Crédits!$E$10),AP3+AQ3) -> 50 | AS3: =ROUND(AP3+AQ3-AR3,2) -> 200 | AT3: =IF(Crédits!$K$10="",0,MAX(0,MIN(AS3,Plan!$L$5-(IF(Crédits!$K$5="",0,IF(Crédits!$K$5<Crédits!$K$10,E3,0))+IF(Crédits!$K$6="",0,IF(Crédits!$K$6<Crédits!$K$10,M3,0))+IF(Crédits!$K$7="",0,IF(Crédits!$K$7<Crédits!$K$10,U3,0))+IF(Crédits!$K$8="",0,IF(Crédits!$K$8<Crédits!$K$10,AC3,0))+IF(Crédits!$K$9="",0,IF(Crédits!$K$9<Crédits!$K$10,AK3,0)))))) -> 0 | AU3: =ROUND(AS3-AT3,2) -> 200 | AV3: =ROUND(MAX(0,N(Crédits!$C$10))+AW3-MIN(N(Crédits!$E$10),MAX(0,N(Crédits!$C$10))+AW3),2) -> 200 | AW3: =MAX(0,N(Crédits!$C$10))*N(Crédits!$D$10)/12 -> 0 | AX3: =D3+L3+T3+AB3+AJ3+AR3 -> 731.45 | AY3: =F3+N3+V3+AD3+AL3+AT3 -> 0 | AZ3: =G3+O3+W3+AE3+AM3+AU3 -> 15750.7 | BA3: =C3+K3+S3+AA3+AI3+AQ3 -> 82.145833 | BB3: =I3+Q3+Y3+AG3+AO3+AW3 -> 82.145833
A4: 2 | B4: =G3 -> 7988.18 | C4: =B4*N(Crédits!$D$5)/12 -> 32.618402 | D4: =MIN(N(Crédits!$E$5),B4+C4) -> 245.3 | E4: =ROUND(B4+C4-D4,2) -> 7775.5 | F4: =IF(Crédits!$K$5="",0,MAX(0,MIN(E4,Plan!$L$6-(IF(Crédits!$K$6="",0,IF(Crédits!$K$6<Crédits!$K$5,M4,0))+IF(Crédits!$K$7="",0,IF(Crédits!$K$7<Crédits!$K$5,U4,0))+IF(Crédits!$K$8="",0,IF(Crédits!$K$8<Crédits!$K$5,AC4,0))+IF(Crédits!$K$9="",0,IF(Crédits!$K$9<Crédits!$K$5,AK4,0))+IF(Crédits!$K$10="",0,IF(Crédits!$K$10<Crédits!$K$5,AS4,0)))))) -> 0 | G4: =ROUND(E4-F4,2) -> 7775.5 | H4: =ROUND(H3+I4-MIN(N(Crédits!$E$5),H3+I4),2) -> 7775.5 | I4: =H3*N(Crédits!$D$5)/12 -> 32.618402 | J4: =O3 -> 1806.74 | K4: =J4*N(Crédits!$D$6)/12 -> 28.456155 | L4: =MIN(N(Crédits!$E$6),J4+K4) -> 72.4 | M4: =ROUND(J4+K4-L4,2) -> 1762.8 | N4: =IF(Crédits!$K$6="",0,MAX(0,MIN(M4,Plan!$L$6-(IF(Crédits!$K$5="",0,IF(Crédits!$K$5<Crédits!$K$6,E4,0))+IF(Crédits!$K$7="",0,IF(Crédits!$K$7<Crédits!$K$6,U4,0))+IF(Crédits!$K$8="",0,IF(Crédits!$K$8<Crédits!$K$6,AC4,0))+IF(Crédits!$K$9="",0,IF(Crédits!$K$9<Crédits!$K$6,AK4,0))+IF(Crédits!$K$10="",0,IF(Crédits!$K$10<Crédits!$K$6,AS4,0)))))) -> 0 | O4: =ROUND(M4-N4,2) -> 1762.8 | P4: =ROUND(P3+Q4-MIN(N(Crédits!$E$6),P3+Q4),2) -> 1762.8 | Q4: =P3*N(Crédits!$D$6)/12 -> 28.456155 | R4: =W3 -> 3298.68 | S4: =R4*N(Crédits!$D$7)/12 -> 16.905735 | T4: =MIN(N(Crédits!$E$7),R4+S4) -> 118.75 | U4: =ROUND(R4+S4-T4,2) -> 3196.84 | V4: =IF(Crédits!$K$7="",0,MAX(0,MIN(U4,Plan!$L$6-(IF(Crédits!$K$5="",0,IF(Crédits!$K$5<Crédits!$K$7,E4,0))+IF(Crédits!$K$6="",0,IF(Crédits!$K$6<Crédits!$K$7,M4,0))+IF(Crédits!$K$8="",0,IF(Crédits!$K$8<Crédits!$K$7,AC4,0))+IF(Crédits!$K$9="",0,IF(Crédits!$K$9<Crédits!$K$7,AK4,0))+IF(Crédits!$K$10="",0,IF(Crédits!$K$10<Crédits!$K$7,AS4,0)))))) -> 0 | W4: =ROUND(U4-V4,2) -> 3196.84 | X4: =ROUND(X3+Y4-MIN(N(Crédits!$E$7),X3+Y4),2) -> 3196.84 | Y4: =X3*N(Crédits!$D$7)/12 -> 16.905735 | Z4: =AE3 -> 2007.1 | AA4: =Z4*N(Crédits!$D$8)/12 -> 2.0071 | AB4: =MIN(N(Crédits!$E$8),Z4+AA4) -> 95 | AC4: =ROUND(Z4+AA4-AB4,2) -> 1914.11 | AD4: =IF(Crédits!$K$8="",0,MAX(0,MIN(AC4,Plan!$L$6-(IF(Crédits!$K$5="",0,IF(Crédits!$K$5<Crédits!$K$8,E4,0))+IF(Crédits!$K$6="",0,IF(Crédits!$K$6<Crédits!$K$8,M4,0))+IF(Crédits!$K$7="",0,IF(Crédits!$K$7<Crédits!$K$8,U4,0))+IF(Crédits!$K$9="",0,IF(Crédits!$K$9<Crédits!$K$8,AK4,0))+IF(Crédits!$K$10="",0,IF(Crédits!$K$10<Crédits!$K$8,AS4,0)))))) -> 0 | AE4: =ROUND(AC4-AD4,2) -> 1914.11 | AF4: =ROUND(AF3+AG4-MIN(N(Crédits!$E$8),AF3+AG4),2) -> 1914.11 | AG4: =AF3*N(Crédits!$D$8)/12 -> 2.0071 | AH4: =AM3 -> 450 | AI4: =AH4*N(Crédits!$D$9)/12 -> 0 | AJ4: =MIN(N(Crédits!$E$9),AH4+AI4) -> 150 | AK4: =ROUND(AH4+AI4-AJ4,2) -> 300 | AL4: =IF(Crédits!$K$9="",0,MAX(0,MIN(AK4,Plan!$L$6-(IF(Crédits!$K$5="",0,IF(Crédits!$K$5<Crédits!$K$9,E4,0))+IF(Crédits!$K$6="",0,IF(Crédits!$K$6<Crédits!$K$9,M4,0))+IF(Crédits!$K$7="",0,IF(Crédits!$K$7<Crédits!$K$9,U4,0))+IF(Crédits!$K$8="",0,IF(Crédits!$K$8<Crédits!$K$9,AC4,0))+IF(Crédits!$K$10="",0,IF(Crédits!$K$10<Crédits!$K$9,AS4,0)))))) -> 0 | AM4: =ROUND(AK4-AL4,2) -> 300 | AN4: =ROUND(AN3+AO4-MIN(N(Crédits!$E$9),AN3+AO4),2) -> 300 | AO4: =AN3*N(Crédits!$D$9)/12 -> 0 | AP4: =AU3 -> 200 | AQ4: =AP4*N(Crédits!$D$10)/12 -> 0 | AR4: =MIN(N(Crédits!$E$10),AP4+AQ4) -> 50 | AS4: =ROUND(AP4+AQ4-AR4,2) -> 150 | AT4: =IF(Crédits!$K$10="",0,MAX(0,MIN(AS4,Plan!$L$6-(IF(Crédits!$K$5="",0,IF(Crédits!$K$5<Crédits!$K$10,E4,0))+IF(Crédits!$K$6="",0,IF(Crédits!$K$6<Crédits!$K$10,M4,0))+IF(Crédits!$K$7="",0,IF(Crédits!$K$7<Crédits!$K$10,U4,0))+IF(Crédits!$K$8="",0,IF(Crédits!$K$8<Crédits!$K$10,AC4,0))+IF(Crédits!$K$9="",0,IF(Crédits!$K$9<Crédits!$K$10,AK4,0)))))) -> 0 | AU4: =ROUND(AS4-AT4,2) -> 150 | AV4: =ROUND(AV3+AW4-MIN(N(Crédits!$E$10),AV3+AW4),2) -> 150 | AW4: =AV3*N(Crédits!$D$10)/12 -> 0 | AX4: =D4+L4+T4+AB4+AJ4+AR4 -> 731.45 | AY4: =F4+N4+V4+AD4+AL4+AT4 -> 0 | AZ4: =G4+O4+W4+AE4+AM4+AU4 -> 15099.25 | BA4: =C4+K4+S4+AA4+AI4+AQ4 -> 79.987392 | BB4: =I4+Q4+Y4+AG4+AO4+AW4 -> 79.987392
A5: 3 | B5: =G4 -> 7775.5 | C5: =B5*N(Crédits!$D$5)/12 -> 31.749958 | D5: =MIN(N(Crédits!$E$5),B5+C5) -> 245.3 | E5: =ROUND(B5+C5-D5,2) -> 7561.95 | F5: =IF(Crédits!$K$5="",0,MAX(0,MIN(E5,Plan!$L$7-(IF(Crédits!$K$6="",0,IF(Crédits!$K$6<Crédits!$K$5,M5,0))+IF(Crédits!$K$7="",0,IF(Crédits!$K$7<Crédits!$K$5,U5,0))+IF(Crédits!$K$8="",0,IF(Crédits!$K$8<Crédits!$K$5,AC5,0))+IF(Crédits!$K$9="",0,IF(Crédits!$K$9<Crédits!$K$5,AK5,0))+IF(Crédits!$K$10="",0,IF(Crédits!$K$10<Crédits!$K$5,AS5,0)))))) -> 0 | G5: =ROUND(E5-F5,2) -> 7561.95 | H5: =ROUND(H4+I5-MIN(N(Crédits!$E$5),H4+I5),2) -> 7561.95 | I5: =H4*N(Crédits!$D$5)/12 -> 31.749958 | J5: =O4 -> 1762.8 | K5: =J5*N(Crédits!$D$6)/12 -> 27.7641 | L5: =MIN(N(Crédits!$E$6),J5+K5) -> 72.4 | M5: =ROUND(J5+K5-L5,2) -> 1718.16 | N5: =IF(Crédits!$K$6="",0,MAX(0,MIN(M5,Plan!$L$7-(IF(Crédits!$K$5="",0,IF(Crédits!$K$5<Crédits!$K$6,E5,0))+IF(Crédits!$K$7="",0,IF(Crédits!$K$7<Crédits!$K$6,U5,0))+IF(Crédits!$K$8="",0,IF(Crédits!$K$8<Crédits!$K$6,AC5,0))+IF(Crédits!$K$9="",0,IF(Crédits!$K$9<Crédits!$K$6,AK5,0))+IF(Crédits!$K$10="",0,IF(Crédits!$K$10<Crédits!$K$6,AS5,0)))))) -> 0 | O5: =ROUND(M5-N5,2) -> 1718.16 | P5: =ROUND(P4+Q5-MIN(N(Crédits!$E$6),P4+Q5),2) -> 1718.16 | Q5: =P4*N(Crédits!$D$6)/12 -> 27.7641 | R5: =W4 -> 3196.84 | S5: =R5*N(Crédits!$D$7)/12 -> 16.383805 | T5: =MIN(N(Crédits!$E$7),R5+S5) -> 118.75 | U5: =ROUND(R5+S5-T5,2) -> 3094.47 | V5: =IF(Crédits!$K$7="",0,MAX(0,MIN(U5,Plan!$L$7-(IF(Crédits!$K$5="",0,IF(Crédits!$K$5<Crédits!$K$7,E5,0))+IF(Crédits!$K$6="",0,IF(Crédits!$K$6<Crédits!$K$7,M5,0))+IF(Crédits!$K$8="",0,IF(Crédits!$K$8<Crédits!$K$7,AC5,0))+IF(Crédits!$K$9="",0,IF(Crédits!$K$9<Crédits!$K$7,AK5,0))+IF(Crédits!$K$10="",0,IF(Crédits!$K$10<Crédits!$K$7,AS5,0)))))) -> 0 | W5: =ROUND(U5-V5,2) -> 3094.47 | X5: =ROUND(X4+Y5-MIN(N(Crédits!$E$7),X4+Y5),2) -> 3094.47 | Y5: =X4*N(Crédits!$D$7)/12 -> 16.383805 | Z5: =AE4 -> 1914.11 | AA5: =Z5*N(Crédits!$D$8)/12 -> 1.91411 | AB5: =MIN(N(Crédits!$E$8),Z5+AA5) -> 95 | AC5: =ROUND(Z5+AA5-AB5,2) -> 1821.02 | AD5: =IF(Crédits!$K$8="",0,MAX(0,MIN(AC5,Plan!$L$7-(IF(Crédits!$K$5="",0,IF(Crédits!$K$5<Crédits!$K$8,E5,0))+IF(Crédits!$K$6="",0,IF(Crédits!$K$6<Crédits!$K$8,M5,0))+IF(Crédits!$K$7="",0,IF(Crédits!$K$7<Crédits!$K$8,U5,0))+IF(Crédits!$K$9="",0,IF(Crédits!$K$9<Crédits!$K$8,AK5,0))+IF(Crédits!$K$10="",0,IF(Crédits!$K$10<Crédits!$K$8,AS5,0)))))) -> 0 | AE5: =ROUND(AC5-AD5,2) -> 1821.02 | AF5: =ROUND(AF4+AG5-MIN(N(Crédits!$E$8),AF4+AG5),2) -> 1821.02 | AG5: =AF4*N(Crédits!$D$8)/12 -> 1.91411 | AH5: =AM4 -> 300 | AI5: =AH5*N(Crédits!$D$9)/12 -> 0 | AJ5: =MIN(N(Crédits!$E$9),AH5+AI5) -> 150 | AK5: =ROUND(AH5+AI5-AJ5,2) -> 150 | AL5: =IF(Crédits!$K$9="",0,MAX(0,MIN(AK5,Plan!$L$7-(IF(Crédits!$K$5="",0,IF(Crédits!$K$5<Crédits!$K$9,E5,0))+IF(Crédits!$K$6="",0,IF(Crédits!$K$6<Crédits!$K$9,M5,0))+IF(Crédits!$K$7="",0,IF(Crédits!$K$7<Crédits!$K$9,U5,0))+IF(Crédits!$K$8="",0,IF(Crédits!$K$8<Crédits!$K$9,AC5,0))+IF(Crédits!$K$10="",0,IF(Crédits!$K$10<Crédits!$K$9,AS5,0)))))) -> 0 | AM5: =ROUND(AK5-AL5,2) -> 150 | AN5: =ROUND(AN4+AO5-MIN(N(Crédits!$E$9),AN4+AO5),2) -> 150 | AO5: =AN4*N(Crédits!$D$9)/12 -> 0 | AP5: =AU4 -> 150 | AQ5: =AP5*N(Crédits!$D$10)/12 -> 0 | AR5: =MIN(N(Crédits!$E$10),AP5+AQ5) -> 50 | AS5: =ROUND(AP5+AQ5-AR5,2) -> 100 | AT5: =IF(Crédits!$K$10="",0,MAX(0,MIN(AS5,Plan!$L$7-(IF(Crédits!$K$5="",0,IF(Crédits!$K$5<Crédits!$K$10,E5,0))+IF(Crédits!$K$6="",0,IF(Crédits!$K$6<Crédits!$K$10,M5,0))+IF(Crédits!$K$7="",0,IF(Crédits!$K$7<Crédits!$K$10,U5,0))+IF(Crédits!$K$8="",0,IF(Crédits!$K$8<Crédits!$K$10,AC5,0))+IF(Crédits!$K$9="",0,IF(Crédits!$K$9<Crédits!$K$10,AK5,0)))))) -> 0 | AU5: =ROUND(AS5-AT5,2) -> 100 | AV5: =ROUND(AV4+AW5-MIN(N(Crédits!$E$10),AV4+AW5),2) -> 100 | AW5: =AV4*N(Crédits!$D$10)/12 -> 0 | AX5: =D5+L5+T5+AB5+AJ5+AR5 -> 731.45 | AY5: =F5+N5+V5+AD5+AL5+AT5 -> 0 | AZ5: =G5+O5+W5+AE5+AM5+AU5 -> 14445.6 | BA5: =C5+K5+S5+AA5+AI5+AQ5 -> 77.811973 | BB5: =I5+Q5+Y5+AG5+AO5+AW5 -> 77.811973
A6: 4 | B6: =G5 -> 7561.95 | C6: =B6*N(Crédits!$D$5)/12 -> 30.877962 | D6: =MIN(N(Crédits!$E$5),B6+C6) -> 245.3 | E6: =ROUND(B6+C6-D6,2) -> 7347.53 | F6: =IF(Crédits!$K$5="",0,MAX(0,MIN(E6,Plan!$L$8-(IF(Crédits!$K$6="",0,IF(Crédits!$K$6<Crédits!$K$5,M6,0))+IF(Crédits!$K$7="",0,IF(Crédits!$K$7<Crédits!$K$5,U6,0))+IF(Crédits!$K$8="",0,IF(Crédits!$K$8<Crédits!$K$5,AC6,0))+IF(Crédits!$K$9="",0,IF(Crédits!$K$9<Crédits!$K$5,AK6,0))+IF(Crédits!$K$10="",0,IF(Crédits!$K$10<Crédits!$K$5,AS6,0)))))) -> 0 | G6: =ROUND(E6-F6,2) -> 7347.53 | H6: =ROUND(H5+I6-MIN(N(Crédits!$E$5),H5+I6),2) -> 7347.53 | I6: =H5*N(Crédits!$D$5)/12 -> 30.877962 | J6: =O5 -> 1718.16 | K6: =J6*N(Crédits!$D$6)/12 -> 27.06102 | L6: =MIN(N(Crédits!$E$6),J6+K6) -> 72.4 | M6: =ROUND(J6+K6-L6,2) -> 1672.82 | N6: =IF(Crédits!$K$6="",0,MAX(0,MIN(M6,Plan!$L$8-(IF(Crédits!$K$5="",0,IF(Crédits!$K$5<Crédits!$K$6,E6,0))+IF(Crédits!$K$7="",0,IF(Crédits!$K$7<Crédits!$K$6,U6,0))+IF(Crédits!$K$8="",0,IF(Crédits!$K$8<Crédits!$K$6,AC6,0))+IF(Crédits!$K$9="",0,IF(Crédits!$K$9<Crédits!$K$6,AK6,0))+IF(Crédits!$K$10="",0,IF(Crédits!$K$10<Crédits!$K$6,AS6,0)))))) -> 0 | O6: =ROUND(M6-N6,2) -> 1672.82 | P6: =ROUND(P5+Q6-MIN(N(Crédits!$E$6),P5+Q6),2) -> 1672.82 | Q6: =P5*N(Crédits!$D$6)/12 -> 27.06102 | R6: =W5 -> 3094.47 | S6: =R6*N(Crédits!$D$7)/12 -> 15.859159 | T6: =MIN(N(Crédits!$E$7),R6+S6) -> 118.75 | U6: =ROUND(R6+S6-T6,2) -> 2991.58 | V6: =IF(Crédits!$K$7="",0,MAX(0,MIN(U6,Plan!$L$8-(IF(Crédits!$K$5="",0,IF(Crédits!$K$5<Crédits!$K$7,E6,0))+IF(Crédits!$K$6="",0,IF(Crédits!$K$6<Crédits!$K$7,M6,0))+IF(Crédits!$K$8="",0,IF(Crédits!$K$8<Crédits!$K$7,AC6,0))+IF(Crédits!$K$9="",0,IF(Crédits!$K$9<Crédits!$K$7,AK6,0))+IF(Crédits!$K$10="",0,IF(Crédits!$K$10<Crédits!$K$7,AS6,0)))))) -> 0 | W6: =ROUND(U6-V6,2) -> 2991.58 | X6: =ROUND(X5+Y6-MIN(N(Crédits!$E$7),X5+Y6),2) -> 2991.58 | Y6: =X5*N(Crédits!$D$7)/12 -> 15.859159 | Z6: =AE5 -> 1821.02 | AA6: =Z6*N(Crédits!$D$8)/12 -> 1.82102 | AB6: =MIN(N(Crédits!$E$8),Z6+AA6) -> 95 | AC6: =ROUND(Z6+AA6-AB6,2) -> 1727.84 | AD6: =IF(Crédits!$K$8="",0,MAX(0,MIN(AC6,Plan!$L$8-(IF(Crédits!$K$5="",0,IF(Crédits!$K$5<Crédits!$K$8,E6,0))+IF(Crédits!$K$6="",0,IF(Crédits!$K$6<Crédits!$K$8,M6,0))+IF(Crédits!$K$7="",0,IF(Crédits!$K$7<Crédits!$K$8,U6,0))+IF(Crédits!$K$9="",0,IF(Crédits!$K$9<Crédits!$K$8,AK6,0))+IF(Crédits!$K$10="",0,IF(Crédits!$K$10<Crédits!$K$8,AS6,0)))))) -> 0 | AE6: =ROUND(AC6-AD6,2) -> 1727.84 | AF6: =ROUND(AF5+AG6-MIN(N(Crédits!$E$8),AF5+AG6),2) -> 1727.84 | AG6: =AF5*N(Crédits!$D$8)/12 -> 1.82102 | AH6: =AM5 -> 150 | AI6: =AH6*N(Crédits!$D$9)/12 -> 0 | AJ6: =MIN(N(Crédits!$E$9),AH6+AI6) -> 150 | AK6: =ROUND(AH6+AI6-AJ6,2) -> 0 | AL6: =IF(Crédits!$K$9="",0,MAX(0,MIN(AK6,Plan!$L$8-(IF(Crédits!$K$5="",0,IF(Crédits!$K$5<Crédits!$K$9,E6,0))+IF(Crédits!$K$6="",0,IF(Crédits!$K$6<Crédits!$K$9,M6,0))+IF(Crédits!$K$7="",0,IF(Crédits!$K$7<Crédits!$K$9,U6,0))+IF(Crédits!$K$8="",0,IF(Crédits!$K$8<Crédits!$K$9,AC6,0))+IF(Crédits!$K$10="",0,IF(Crédits!$K$10<Crédits!$K$9,AS6,0)))))) -> 0 | AM6: =ROUND(AK6-AL6,2) -> 0 | AN6: =ROUND(AN5+AO6-MIN(N(Crédits!$E$9),AN5+AO6),2) -> 0 | AO6: =AN5*N(Crédits!$D$9)/12 -> 0 | AP6: =AU5 -> 100 | AQ6: =AP6*N(Crédits!$D$10)/12 -> 0 | AR6: =MIN(N(Crédits!$E$10),AP6+AQ6) -> 50 | AS6: =ROUND(AP6+AQ6-AR6,2) -> 50 | AT6: =IF(Crédits!$K$10="",0,MAX(0,MIN(AS6,Plan!$L$8-(IF(Crédits!$K$5="",0,IF(Crédits!$K$5<Crédits!$K$10,E6,0))+IF(Crédits!$K$6="",0,IF(Crédits!$K$6<Crédits!$K$10,M6,0))+IF(Crédits!$K$7="",0,IF(Crédits!$K$7<Crédits!$K$10,U6,0))+IF(Crédits!$K$8="",0,IF(Crédits!$K$8<Crédits!$K$10,AC6,0))+IF(Crédits!$K$9="",0,IF(Crédits!$K$9<Crédits!$K$10,AK6,0)))))) -> 0 | AU6: =ROUND(AS6-AT6,2) -> 50 | AV6: =ROUND(AV5+AW6-MIN(N(Crédits!$E$10),AV5+AW6),2) -> 50 | AW6: =AV5*N(Crédits!$D$10)/12 -> 0 | AX6: =D6+L6+T6+AB6+AJ6+AR6 -> 731.45 | AY6: =F6+N6+V6+AD6+AL6+AT6 -> 0 | AZ6: =G6+O6+W6+AE6+AM6+AU6 -> 13789.77 | BA6: =C6+K6+S6+AA6+AI6+AQ6 -> 75.619161 | BB6: =I6+Q6+Y6+AG6+AO6+AW6 -> 75.619161
A7: 5 | B7: =G6 -> 7347.53 | C7: =B7*N(Crédits!$D$5)/12 -> 30.002414 | D7: =MIN(N(Crédits!$E$5),B7+C7) -> 245.3 | E7: =ROUND(B7+C7-D7,2) -> 7132.23 | F7: =IF(Crédits!$K$5="",0,MAX(0,MIN(E7,Plan!$L$9-(IF(Crédits!$K$6="",0,IF(Crédits!$K$6<Crédits!$K$5,M7,0))+IF(Crédits!$K$7="",0,IF(Crédits!$K$7<Crédits!$K$5,U7,0))+IF(Crédits!$K$8="",0,IF(Crédits!$K$8<Crédits!$K$5,AC7,0))+IF(Crédits!$K$9="",0,IF(Crédits!$K$9<Crédits!$K$5,AK7,0))+IF(Crédits!$K$10="",0,IF(Crédits!$K$10<Crédits!$K$5,AS7,0)))))) -> 0 | G7: =ROUND(E7-F7,2) -> 7132.23 | H7: =ROUND(H6+I7-MIN(N(Crédits!$E$5),H6+I7),2) -> 7132.23 | I7: =H6*N(Crédits!$D$5)/12 -> 30.002414 | J7: =O6 -> 1672.82 | K7: =J7*N(Crédits!$D$6)/12 -> 26.346915 | L7: =MIN(N(Crédits!$E$6),J7+K7) -> 72.4 | M7: =ROUND(J7+K7-L7,2) -> 1626.77 | N7: =IF(Crédits!$K$6="",0,MAX(0,MIN(M7,Plan!$L$9-(IF(Crédits!$K$5="",0,IF(Crédits!$K$5<Crédits!$K$6,E7,0))+IF(Crédits!$K$7="",0,IF(Crédits!$K$7<Crédits!$K$6,U7,0))+IF(Crédits!$K$8="",0,IF(Crédits!$K$8<Crédits!$K$6,AC7,0))+IF(Crédits!$K$9="",0,IF(Crédits!$K$9<Crédits!$K$6,AK7,0))+IF(Crédits!$K$10="",0,IF(Crédits!$K$10<Crédits!$K$6,AS7,0)))))) -> 0 | O7: =ROUND(M7-N7,2) -> 1626.77 | P7: =ROUND(P6+Q7-MIN(N(Crédits!$E$6),P6+Q7),2) -> 1626.77 | Q7: =P6*N(Crédits!$D$6)/12 -> 26.346915 | R7: =W6 -> 2991.58 | S7: =R7*N(Crédits!$D$7)/12 -> 15.331848 | T7: =MIN(N(Crédits!$E$7),R7+S7) -> 118.75 | U7: =ROUND(R7+S7-T7,2) -> 2888.16 | V7: =IF(Crédits!$K$7="",0,MAX(0,MIN(U7,Plan!$L$9-(IF(Crédits!$K$5="",0,IF(Crédits!$K$5<Crédits!$K$7,E7,0))+IF(Crédits!$K$6="",0,IF(Crédits!$K$6<Crédits!$K$7,M7,0))+IF(Crédits!$K$8="",0,IF(Crédits!$K$8<Crédits!$K$7,AC7,0))+IF(Crédits!$K$9="",0,IF(Crédits!$K$9<Crédits!$K$7,AK7,0))+IF(Crédits!$K$10="",0,IF(Crédits!$K$10<Crédits!$K$7,AS7,0)))))) -> 0 | W7: =ROUND(U7-V7,2) -> 2888.16 | X7: =ROUND(X6+Y7-MIN(N(Crédits!$E$7),X6+Y7),2) -> 2888.16 | Y7: =X6*N(Crédits!$D$7)/12 -> 15.331848 | Z7: =AE6 -> 1727.84 | AA7: =Z7*N(Crédits!$D$8)/12 -> 1.72784 | AB7: =MIN(N(Crédits!$E$8),Z7+AA7) -> 95 | AC7: =ROUND(Z7+AA7-AB7,2) -> 1634.57 | AD7: =IF(Crédits!$K$8="",0,MAX(0,MIN(AC7,Plan!$L$9-(IF(Crédits!$K$5="",0,IF(Crédits!$K$5<Crédits!$K$8,E7,0))+IF(Crédits!$K$6="",0,IF(Crédits!$K$6<Crédits!$K$8,M7,0))+IF(Crédits!$K$7="",0,IF(Crédits!$K$7<Crédits!$K$8,U7,0))+IF(Crédits!$K$9="",0,IF(Crédits!$K$9<Crédits!$K$8,AK7,0))+IF(Crédits!$K$10="",0,IF(Crédits!$K$10<Crédits!$K$8,AS7,0)))))) -> 0 | AE7: =ROUND(AC7-AD7,2) -> 1634.57 | AF7: =ROUND(AF6+AG7-MIN(N(Crédits!$E$8),AF6+AG7),2) -> 1634.57 | AG7: =AF6*N(Crédits!$D$8)/12 -> 1.72784 | AH7: =AM6 -> 0 | AI7: =AH7*N(Crédits!$D$9)/12 -> 0 | AJ7: =MIN(N(Crédits!$E$9),AH7+AI7) -> 0 | AK7: =ROUND(AH7+AI7-AJ7,2) -> 0 | AL7: =IF(Crédits!$K$9="",0,MAX(0,MIN(AK7,Plan!$L$9-(IF(Crédits!$K$5="",0,IF(Crédits!$K$5<Crédits!$K$9,E7,0))+IF(Crédits!$K$6="",0,IF(Crédits!$K$6<Crédits!$K$9,M7,0))+IF(Crédits!$K$7="",0,IF(Crédits!$K$7<Crédits!$K$9,U7,0))+IF(Crédits!$K$8="",0,IF(Crédits!$K$8<Crédits!$K$9,AC7,0))+IF(Crédits!$K$10="",0,IF(Crédits!$K$10<Crédits!$K$9,AS7,0)))))) -> 0 | AM7: =ROUND(AK7-AL7,2) -> 0 | AN7: =ROUND(AN6+AO7-MIN(N(Crédits!$E$9),AN6+AO7),2) -> 0 | AO7: =AN6*N(Crédits!$D$9)/12 -> 0 | AP7: =AU6 -> 50 | AQ7: =AP7*N(Crédits!$D$10)/12 -> 0 | AR7: =MIN(N(Crédits!$E$10),AP7+AQ7) -> 50 | AS7: =ROUND(AP7+AQ7-AR7,2) -> 0 | AT7: =IF(Crédits!$K$10="",0,MAX(0,MIN(AS7,Plan!$L$9-(IF(Crédits!$K$5="",0,IF(Crédits!$K$5<Crédits!$K$10,E7,0))+IF(Crédits!$K$6="",0,IF(Crédits!$K$6<Crédits!$K$10,M7,0))+IF(Crédits!$K$7="",0,IF(Crédits!$K$7<Crédits!$K$10,U7,0))+IF(Crédits!$K$8="",0,IF(Crédits!$K$8<Crédits!$K$10,AC7,0))+IF(Crédits!$K$9="",0,IF(Crédits!$K$9<Crédits!$K$10,AK7,0)))))) -> 0 | AU7: =ROUND(AS7-AT7,2) -> 0 | AV7: =ROUND(AV6+AW7-MIN(N(Crédits!$E$10),AV6+AW7),2) -> 0 | AW7: =AV6*N(Crédits!$D$10)/12 -> 0 | AX7: =D7+L7+T7+AB7+AJ7+AR7 -> 581.45 | AY7: =F7+N7+V7+AD7+AL7+AT7 -> 0 | AZ7: =G7+O7+W7+AE7+AM7+AU7 -> 13281.73 | BA7: =C7+K7+S7+AA7+AI7+AQ7 -> 73.409017 | BB7: =I7+Q7+Y7+AG7+AO7+AW7 -> 73.409017
A8: 6 | B8: =G7 -> 7132.23 | C8: =B8*N(Crédits!$D$5)/12 -> 29.123272 | D8: =MIN(N(Crédits!$E$5),B8+C8) -> 245.3 | E8: =ROUND(B8+C8-D8,2) -> 6916.05 | F8: =IF(Crédits!$K$5="",0,MAX(0,MIN(E8,Plan!$L$10-(IF(Crédits!$K$6="",0,IF(Crédits!$K$6<Crédits!$K$5,M8,0))+IF(Crédits!$K$7="",0,IF(Crédits!$K$7<Crédits!$K$5,U8,0))+IF(Crédits!$K$8="",0,IF(Crédits!$K$8<Crédits!$K$5,AC8,0))+IF(Crédits!$K$9="",0,IF(Crédits!$K$9<Crédits!$K$5,AK8,0))+IF(Crédits!$K$10="",0,IF(Crédits!$K$10<Crédits!$K$5,AS8,0)))))) -> 0 | G8: =ROUND(E8-F8,2) -> 6916.05 | H8: =ROUND(H7+I8-MIN(N(Crédits!$E$5),H7+I8),2) -> 6916.05 | I8: =H7*N(Crédits!$D$5)/12 -> 29.123272 | J8: =O7 -> 1626.77 | K8: =J8*N(Crédits!$D$6)/12 -> 25.621627 | L8: =MIN(N(Crédits!$E$6),J8+K8) -> 72.4 | M8: =ROUND(J8+K8-L8,2) -> 1579.99 | N8: =IF(Crédits!$K$6="",0,MAX(0,MIN(M8,Plan!$L$10-(IF(Crédits!$K$5="",0,IF(Crédits!$K$5<Crédits!$K$6,E8,0))+IF(Crédits!$K$7="",0,IF(Crédits!$K$7<Crédits!$K$6,U8,0))+IF(Crédits!$K$8="",0,IF(Crédits!$K$8<Crédits!$K$6,AC8,0))+IF(Crédits!$K$9="",0,IF(Crédits!$K$9<Crédits!$K$6,AK8,0))+IF(Crédits!$K$10="",0,IF(Crédits!$K$10<Crédits!$K$6,AS8,0)))))) -> 0 | O8: =ROUND(M8-N8,2) -> 1579.99 | P8: =ROUND(P7+Q8-MIN(N(Crédits!$E$6),P7+Q8),2) -> 1579.99 | Q8: =P7*N(Crédits!$D$6)/12 -> 25.621627 | R8: =W7 -> 2888.16 | S8: =R8*N(Crédits!$D$7)/12 -> 14.80182 | T8: =MIN(N(Crédits!$E$7),R8+S8) -> 118.75 | U8: =ROUND(R8+S8-T8,2) -> 2784.21 | V8: =IF(Crédits!$K$7="",0,MAX(0,MIN(U8,Plan!$L$10-(IF(Crédits!$K$5="",0,IF(Crédits!$K$5<Crédits!$K$7,E8,0))+IF(Crédits!$K$6="",0,IF(Crédits!$K$6<Crédits!$K$7,M8,0))+IF(Crédits!$K$8="",0,IF(Crédits!$K$8<Crédits!$K$7,AC8,0))+IF(Crédits!$K$9="",0,IF(Crédits!$K$9<Crédits!$K$7,AK8,0))+IF(Crédits!$K$10="",0,IF(Crédits!$K$10<Crédits!$K$7,AS8,0)))))) -> 0 | W8: =ROUND(U8-V8,2) -> 2784.21 | X8: =ROUND(X7+Y8-MIN(N(Crédits!$E$7),X7+Y8),2) -> 2784.21 | Y8: =X7*N(Crédits!$D$7)/12 -> 14.80182 | Z8: =AE7 -> 1634.57 | AA8: =Z8*N(Crédits!$D$8)/12 -> 1.63457 | AB8: =MIN(N(Crédits!$E$8),Z8+AA8) -> 95 | AC8: =ROUND(Z8+AA8-AB8,2) -> 1541.2 | AD8: =IF(Crédits!$K$8="",0,MAX(0,MIN(AC8,Plan!$L$10-(IF(Crédits!$K$5="",0,IF(Crédits!$K$5<Crédits!$K$8,E8,0))+IF(Crédits!$K$6="",0,IF(Crédits!$K$6<Crédits!$K$8,M8,0))+IF(Crédits!$K$7="",0,IF(Crédits!$K$7<Crédits!$K$8,U8,0))+IF(Crédits!$K$9="",0,IF(Crédits!$K$9<Crédits!$K$8,AK8,0))+IF(Crédits!$K$10="",0,IF(Crédits!$K$10<Crédits!$K$8,AS8,0)))))) -> 0 | AE8: =ROUND(AC8-AD8,2) -> 1541.2 | AF8: =ROUND(AF7+AG8-MIN(N(Crédits!$E$8),AF7+AG8),2) -> 1541.2 | AG8: =AF7*N(Crédits!$D$8)/12 -> 1.63457 | AH8: =AM7 -> 0 | AI8: =AH8*N(Crédits!$D$9)/12 -> 0 | AJ8: =MIN(N(Crédits!$E$9),AH8+AI8) -> 0 | AK8: =ROUND(AH8+AI8-AJ8,2) -> 0 | AL8: =IF(Crédits!$K$9="",0,MAX(0,MIN(AK8,Plan!$L$10-(IF(Crédits!$K$5="",0,IF(Crédits!$K$5<Crédits!$K$9,E8,0))+IF(Crédits!$K$6="",0,IF(Crédits!$K$6<Crédits!$K$9,M8,0))+IF(Crédits!$K$7="",0,IF(Crédits!$K$7<Crédits!$K$9,U8,0))+IF(Crédits!$K$8="",0,IF(Crédits!$K$8<Crédits!$K$9,AC8,0))+IF(Crédits!$K$10="",0,IF(Crédits!$K$10<Crédits!$K$9,AS8,0)))))) -> 0 | AM8: =ROUND(AK8-AL8,2) -> 0 | AN8: =ROUND(AN7+AO8-MIN(N(Crédits!$E$9),AN7+AO8),2) -> 0 | AO8: =AN7*N(Crédits!$D$9)/12 -> 0 | AP8: =AU7 -> 0 | AQ8: =AP8*N(Crédits!$D$10)/12 -> 0 | AR8: =MIN(N(Crédits!$E$10),AP8+AQ8) -> 0 | AS8: =ROUND(AP8+AQ8-AR8,2) -> 0 | AT8: =IF(Crédits!$K$10="",0,MAX(0,MIN(AS8,Plan!$L$10-(IF(Crédits!$K$5="",0,IF(Crédits!$K$5<Crédits!$K$10,E8,0))+IF(Crédits!$K$6="",0,IF(Crédits!$K$6<Crédits!$K$10,M8,0))+IF(Crédits!$K$7="",0,IF(Crédits!$K$7<Crédits!$K$10,U8,0))+IF(Crédits!$K$8="",0,IF(Crédits!$K$8<Crédits!$K$10,AC8,0))+IF(Crédits!$K$9="",0,IF(Crédits!$K$9<Crédits!$K$10,AK8,0)))))) -> 0 | AU8: =ROUND(AS8-AT8,2) -> 0 | AV8: =ROUND(AV7+AW8-MIN(N(Crédits!$E$10),AV7+AW8),2) -> 0 | AW8: =AV7*N(Crédits!$D$10)/12 -> 0 | AX8: =D8+L8+T8+AB8+AJ8+AR8 -> 531.45 | AY8: =F8+N8+V8+AD8+AL8+AT8 -> 0 | AZ8: =G8+O8+W8+AE8+AM8+AU8 -> 12821.45 | BA8: =C8+K8+S8+AA8+AI8+AQ8 -> 71.18129 | BB8: =I8+Q8+Y8+AG8+AO8+AW8 -> 71.18129
A9: 7 | B9: =G8 -> 6916.05 | C9: =B9*N(Crédits!$D$5)/12 -> 28.240538 | D9: =MIN(N(Crédits!$E$5),B9+C9) -> 245.3 | E9: =ROUND(B9+C9-D9,2) -> 6698.99 | F9: =IF(Crédits!$K$5="",0,MAX(0,MIN(E9,Plan!$L$11-(IF(Crédits!$K$6="",0,IF(Crédits!$K$6<Crédits!$K$5,M9,0))+IF(Crédits!$K$7="",0,IF(Crédits!$K$7<Crédits!$K$5,U9,0))+IF(Crédits!$K$8="",0,IF(Crédits!$K$8<Crédits!$K$5,AC9,0))+IF(Crédits!$K$9="",0,IF(Crédits!$K$9<Crédits!$K$5,AK9,0))+IF(Crédits!$K$10="",0,IF(Crédits!$K$10<Crédits!$K$5,AS9,0)))))) -> 0 | G9: =ROUND(E9-F9,2) -> 6698.99 | H9: =ROUND(H8+I9-MIN(N(Crédits!$E$5),H8+I9),2) -> 6698.99 | I9: =H8*N(Crédits!$D$5)/12 -> 28.240538 | J9: =O8 -> 1579.99 | K9: =J9*N(Crédits!$D$6)/12 -> 24.884843 | L9: =MIN(N(Crédits!$E$6),J9+K9) -> 72.4 | M9: =ROUND(J9+K9-L9,2) -> 1532.47 | N9: =IF(Crédits!$K$6="",0,MAX(0,MIN(M9,Plan!$L$11-(IF(Crédits!$K$5="",0,IF(Crédits!$K$5<Crédits!$K$6,E9,0))+IF(Crédits!$K$7="",0,IF(Crédits!$K$7<Crédits!$K$6,U9,0))+IF(Crédits!$K$8="",0,IF(Crédits!$K$8<Crédits!$K$6,AC9,0))+IF(Crédits!$K$9="",0,IF(Crédits!$K$9<Crédits!$K$6,AK9,0))+IF(Crédits!$K$10="",0,IF(Crédits!$K$10<Crédits!$K$6,AS9,0)))))) -> 0 | O9: =ROUND(M9-N9,2) -> 1532.47 | P9: =ROUND(P8+Q9-MIN(N(Crédits!$E$6),P8+Q9),2) -> 1532.47 | Q9: =P8*N(Crédits!$D$6)/12 -> 24.884843 | R9: =W8 -> 2784.21 | S9: =R9*N(Crédits!$D$7)/12 -> 14.269076 | T9: =MIN(N(Crédits!$E$7),R9+S9) -> 118.75 | U9: =ROUND(R9+S9-T9,2) -> 2679.73 | V9: =IF(Crédits!$K$7="",0,MAX(0,MIN(U9,Plan!$L$11-(IF(Crédits!$K$5="",0,IF(Crédits!$K$5<Crédits!$K$7,E9,0))+IF(Crédits!$K$6="",0,IF(Crédits!$K$6<Crédits!$K$7,M9,0))+IF(Crédits!$K$8="",0,IF(Crédits!$K$8<Crédits!$K$7,AC9,0))+IF(Crédits!$K$9="",0,IF(Crédits!$K$9<Crédits!$K$7,AK9,0))+IF(Crédits!$K$10="",0,IF(Crédits!$K$10<Crédits!$K$7,AS9,0)))))) -> 0 | W9: =ROUND(U9-V9,2) -> 2679.73 | X9: =ROUND(X8+Y9-MIN(N(Crédits!$E$7),X8+Y9),2) -> 2679.73 | Y9: =X8*N(Crédits!$D$7)/12 -> 14.269076 | Z9: =AE8 -> 1541.2 | AA9: =Z9*N(Crédits!$D$8)/12 -> 1.5412 | AB9: =MIN(N(Crédits!$E$8),Z9+AA9) -> 95 | AC9: =ROUND(Z9+AA9-AB9,2) -> 1447.74 | AD9: =IF(Crédits!$K$8="",0,MAX(0,MIN(AC9,Plan!$L$11-(IF(Crédits!$K$5="",0,IF(Crédits!$K$5<Crédits!$K$8,E9,0))+IF(Crédits!$K$6="",0,IF(Crédits!$K$6<Crédits!$K$8,M9,0))+IF(Crédits!$K$7="",0,IF(Crédits!$K$7<Crédits!$K$8,U9,0))+IF(Crédits!$K$9="",0,IF(Crédits!$K$9<Crédits!$K$8,AK9,0))+IF(Crédits!$K$10="",0,IF(Crédits!$K$10<Crédits!$K$8,AS9,0)))))) -> 0 | AE9: =ROUND(AC9-AD9,2) -> 1447.74 | AF9: =ROUND(AF8+AG9-MIN(N(Crédits!$E$8),AF8+AG9),2) -> 1447.74 | AG9: =AF8*N(Crédits!$D$8)/12 -> 1.5412 | AH9: =AM8 -> 0 | AI9: =AH9*N(Crédits!$D$9)/12 -> 0 | AJ9: =MIN(N(Crédits!$E$9),AH9+AI9) -> 0 | AK9: =ROUND(AH9+AI9-AJ9,2) -> 0 | AL9: =IF(Crédits!$K$9="",0,MAX(0,MIN(AK9,Plan!$L$11-(IF(Crédits!$K$5="",0,IF(Crédits!$K$5<Crédits!$K$9,E9,0))+IF(Crédits!$K$6="",0,IF(Crédits!$K$6<Crédits!$K$9,M9,0))+IF(Crédits!$K$7="",0,IF(Crédits!$K$7<Crédits!$K$9,U9,0))+IF(Crédits!$K$8="",0,IF(Crédits!$K$8<Crédits!$K$9,AC9,0))+IF(Crédits!$K$10="",0,IF(Crédits!$K$10<Crédits!$K$9,AS9,0)))))) -> 0 | AM9: =ROUND(AK9-AL9,2) -> 0 | AN9: =ROUND(AN8+AO9-MIN(N(Crédits!$E$9),AN8+AO9),2) -> 0 | AO9: =AN8*N(Crédits!$D$9)/12 -> 0 | AP9: =AU8 -> 0 | AQ9: =AP9*N(Crédits!$D$10)/12 -> 0 | AR9: =MIN(N(Crédits!$E$10),AP9+AQ9) -> 0 | AS9: =ROUND(AP9+AQ9-AR9,2) -> 0 | AT9: =IF(Crédits!$K$10="",0,MAX(0,MIN(AS9,Plan!$L$11-(IF(Crédits!$K$5="",0,IF(Crédits!$K$5<Crédits!$K$10,E9,0))+IF(Crédits!$K$6="",0,IF(Crédits!$K$6<Crédits!$K$10,M9,0))+IF(Crédits!$K$7="",0,IF(Crédits!$K$7<Crédits!$K$10,U9,0))+IF(Crédits!$K$8="",0,IF(Crédits!$K$8<Crédits!$K$10,AC9,0))+IF(Crédits!$K$9="",0,IF(Crédits!$K$9<Crédits!$K$10,AK9,0)))))) -> 0 | AU9: =ROUND(AS9-AT9,2) -> 0 | AV9: =ROUND(AV8+AW9-MIN(N(Crédits!$E$10),AV8+AW9),2) -> 0 | AW9: =AV8*N(Crédits!$D$10)/12 -> 0 | AX9: =D9+L9+T9+AB9+AJ9+AR9 -> 531.45 | AY9: =F9+N9+V9+AD9+AL9+AT9 -> 0 | AZ9: =G9+O9+W9+AE9+AM9+AU9 -> 12358.93 | BA9: =C9+K9+S9+AA9+AI9+AQ9 -> 68.935656 | BB9: =I9+Q9+Y9+AG9+AO9+AW9 -> 68.935656
A10: 8 | B10: =G9 -> 6698.99 | C10: =B10*N(Crédits!$D$5)/12 -> 27.354209 | D10: =MIN(N(Crédits!$E$5),B10+C10) -> 245.3 | E10: =ROUND(B10+C10-D10,2) -> 6481.04 | F10: =IF(Crédits!$K$5="",0,MAX(0,MIN(E10,Plan!$L$12-(IF(Crédits!$K$6="",0,IF(Crédits!$K$6<Crédits!$K$5,M10,0))+IF(Crédits!$K$7="",0,IF(Crédits!$K$7<Crédits!$K$5,U10,0))+IF(Crédits!$K$8="",0,IF(Crédits!$K$8<Crédits!$K$5,AC10,0))+IF(Crédits!$K$9="",0,IF(Crédits!$K$9<Crédits!$K$5,AK10,0))+IF(Crédits!$K$10="",0,IF(Crédits!$K$10<Crédits!$K$5,AS10,0)))))) -> 0 | G10: =ROUND(E10-F10,2) -> 6481.04 | H10: =ROUND(H9+I10-MIN(N(Crédits!$E$5),H9+I10),2) -> 6481.04 | I10: =H9*N(Crédits!$D$5)/12 -> 27.354209 | J10: =O9 -> 1532.47 | K10: =J10*N(Crédits!$D$6)/12 -> 24.136403 | L10: =MIN(N(Crédits!$E$6),J10+K10) -> 72.4 | M10: =ROUND(J10+K10-L10,2) -> 1484.21 | N10: =IF(Crédits!$K$6="",0,MAX(0,MIN(M10,Plan!$L$12-(IF(Crédits!$K$5="",0,IF(Crédits!$K$5<Crédits!$K$6,E10,0))+IF(Crédits!$K$7="",0,IF(Crédits!$K$7<Crédits!$K$6,U10,0))+IF(Crédits!$K$8="",0,IF(Crédits!$K$8<Crédits!$K$6,AC10,0))+IF(Crédits!$K$9="",0,IF(Crédits!$K$9<Crédits!$K$6,AK10,0))+IF(Crédits!$K$10="",0,IF(Crédits!$K$10<Crédits!$K$6,AS10,0)))))) -> 0 | O10: =ROUND(M10-N10,2) -> 1484.21 | P10: =ROUND(P9+Q10-MIN(N(Crédits!$E$6),P9+Q10),2) -> 1484.21 | Q10: =P9*N(Crédits!$D$6)/12 -> 24.136403 | R10: =W9 -> 2679.73 | S10: =R10*N(Crédits!$D$7)/12 -> 13.733616 | T10: =MIN(N(Crédits!$E$7),R10+S10) -> 118.75 | U10: =ROUND(R10+S10-T10,2) -> 2574.71 | V10: =IF(Crédits!$K$7="",0,MAX(0,MIN(U10,Plan!$L$12-(IF(Crédits!$K$5="",0,IF(Crédits!$K$5<Crédits!$K$7,E10,0))+IF(Crédits!$K$6="",0,IF(Crédits!$K$6<Crédits!$K$7,M10,0))+IF(Crédits!$K$8="",0,IF(Crédits!$K$8<Crédits!$K$7,AC10,0))+IF(Crédits!$K$9="",0,IF(Crédits!$K$9<Crédits!$K$7,AK10,0))+IF(Crédits!$K$10="",0,IF(Crédits!$K$10<Crédits!$K$7,AS10,0)))))) -> 0 | W10: =ROUND(U10-V10,2) -> 2574.71 | X10: =ROUND(X9+Y10-MIN(N(Crédits!$E$7),X9+Y10),2) -> 2574.71 | Y10: =X9*N(Crédits!$D$7)/12 -> 13.733616 | Z10: =AE9 -> 1447.74 | AA10: =Z10*N(Crédits!$D$8)/12 -> 1.44774 | AB10: =MIN(N(Crédits!$E$8),Z10+AA10) -> 95 | AC10: =ROUND(Z10+AA10-AB10,2) -> 1354.19 | AD10: =IF(Crédits!$K$8="",0,MAX(0,MIN(AC10,Plan!$L$12-(IF(Crédits!$K$5="",0,IF(Crédits!$K$5<Crédits!$K$8,E10,0))+IF(Crédits!$K$6="",0,IF(Crédits!$K$6<Crédits!$K$8,M10,0))+IF(Crédits!$K$7="",0,IF(Crédits!$K$7<Crédits!$K$8,U10,0))+IF(Crédits!$K$9="",0,IF(Crédits!$K$9<Crédits!$K$8,AK10,0))+IF(Crédits!$K$10="",0,IF(Crédits!$K$10<Crédits!$K$8,AS10,0)))))) -> 0 | AE10: =ROUND(AC10-AD10,2) -> 1354.19 | AF10: =ROUND(AF9+AG10-MIN(N(Crédits!$E$8),AF9+AG10),2) -> 1354.19 | AG10: =AF9*N(Crédits!$D$8)/12 -> 1.44774 | AH10: =AM9 -> 0 | AI10: =AH10*N(Crédits!$D$9)/12 -> 0 | AJ10: =MIN(N(Crédits!$E$9),AH10+AI10) -> 0 | AK10: =ROUND(AH10+AI10-AJ10,2) -> 0 | AL10: =IF(Crédits!$K$9="",0,MAX(0,MIN(AK10,Plan!$L$12-(IF(Crédits!$K$5="",0,IF(Crédits!$K$5<Crédits!$K$9,E10,0))+IF(Crédits!$K$6="",0,IF(Crédits!$K$6<Crédits!$K$9,M10,0))+IF(Crédits!$K$7="",0,IF(Crédits!$K$7<Crédits!$K$9,U10,0))+IF(Crédits!$K$8="",0,IF(Crédits!$K$8<Crédits!$K$9,AC10,0))+IF(Crédits!$K$10="",0,IF(Crédits!$K$10<Crédits!$K$9,AS10,0)))))) -> 0 | AM10: =ROUND(AK10-AL10,2) -> 0 | AN10: =ROUND(AN9+AO10-MIN(N(Crédits!$E$9),AN9+AO10),2) -> 0 | AO10: =AN9*N(Crédits!$D$9)/12 -> 0 | AP10: =AU9 -> 0 | AQ10: =AP10*N(Crédits!$D$10)/12 -> 0 | AR10: =MIN(N(Crédits!$E$10),AP10+AQ10) -> 0 | AS10: =ROUND(AP10+AQ10-AR10,2) -> 0 | AT10: =IF(Crédits!$K$10="",0,MAX(0,MIN(AS10,Plan!$L$12-(IF(Crédits!$K$5="",0,IF(Crédits!$K$5<Crédits!$K$10,E10,0))+IF(Crédits!$K$6="",0,IF(Crédits!$K$6<Crédits!$K$10,M10,0))+IF(Crédits!$K$7="",0,IF(Crédits!$K$7<Crédits!$K$10,U10,0))+IF(Crédits!$K$8="",0,IF(Crédits!$K$8<Crédits!$K$10,AC10,0))+IF(Crédits!$K$9="",0,IF(Crédits!$K$9<Crédits!$K$10,AK10,0)))))) -> 0 | AU10: =ROUND(AS10-AT10,2) -> 0 | AV10: =ROUND(AV9+AW10-MIN(N(Crédits!$E$10),AV9+AW10),2) -> 0 | AW10: =AV9*N(Crédits!$D$10)/12 -> 0 | AX10: =D10+L10+T10+AB10+AJ10+AR10 -> 531.45 | AY10: =F10+N10+V10+AD10+AL10+AT10 -> 0 | AZ10: =G10+O10+W10+AE10+AM10+AU10 -> 11894.15 | BA10: =C10+K10+S10+AA10+AI10+AQ10 -> 66.671968 | BB10: =I10+Q10+Y10+AG10+AO10+AW10 -> 66.671968
A11: 9 | B11: =G10 -> 6481.04 | C11: =B11*N(Crédits!$D$5)/12 -> 26.464247 | D11: =MIN(N(Crédits!$E$5),B11+C11) -> 245.3 | E11: =ROUND(B11+C11-D11,2) -> 6262.2 | F11: =IF(Crédits!$K$5="",0,MAX(0,MIN(E11,Plan!$L$13-(IF(Crédits!$K$6="",0,IF(Crédits!$K$6<Crédits!$K$5,M11,0))+IF(Crédits!$K$7="",0,IF(Crédits!$K$7<Crédits!$K$5,U11,0))+IF(Crédits!$K$8="",0,IF(Crédits!$K$8<Crédits!$K$5,AC11,0))+IF(Crédits!$K$9="",0,IF(Crédits!$K$9<Crédits!$K$5,AK11,0))+IF(Crédits!$K$10="",0,IF(Crédits!$K$10<Crédits!$K$5,AS11,0)))))) -> 0 | G11: =ROUND(E11-F11,2) -> 6262.2 | H11: =ROUND(H10+I11-MIN(N(Crédits!$E$5),H10+I11),2) -> 6262.2 | I11: =H10*N(Crédits!$D$5)/12 -> 26.464247 | J11: =O10 -> 1484.21 | K11: =J11*N(Crédits!$D$6)/12 -> 23.376307 | L11: =MIN(N(Crédits!$E$6),J11+K11) -> 72.4 | M11: =ROUND(J11+K11-L11,2) -> 1435.19 | N11: =IF(Crédits!$K$6="",0,MAX(0,MIN(M11,Plan!$L$13-(IF(Crédits!$K$5="",0,IF(Crédits!$K$5<Crédits!$K$6,E11,0))+IF(Crédits!$K$7="",0,IF(Crédits!$K$7<Crédits!$K$6,U11,0))+IF(Crédits!$K$8="",0,IF(Crédits!$K$8<Crédits!$K$6,AC11,0))+IF(Crédits!$K$9="",0,IF(Crédits!$K$9<Crédits!$K$6,AK11,0))+IF(Crédits!$K$10="",0,IF(Crédits!$K$10<Crédits!$K$6,AS11,0)))))) -> 0 | O11: =ROUND(M11-N11,2) -> 1435.19 | P11: =ROUND(P10+Q11-MIN(N(Crédits!$E$6),P10+Q11),2) -> 1435.19 | Q11: =P10*N(Crédits!$D$6)/12 -> 23.376307 | R11: =W10 -> 2574.71 | S11: =R11*N(Crédits!$D$7)/12 -> 13.195389 | T11: =MIN(N(Crédits!$E$7),R11+S11) -> 118.75 | U11: =ROUND(R11+S11-T11,2) -> 2469.16 | V11: =IF(Crédits!$K$7="",0,MAX(0,MIN(U11,Plan!$L$13-(IF(Crédits!$K$5="",0,IF(Crédits!$K$5<Crédits!$K$7,E11,0))+IF(Crédits!$K$6="",0,IF(Crédits!$K$6<Crédits!$K$7,M11,0))+IF(Crédits!$K$8="",0,IF(Crédits!$K$8<Crédits!$K$7,AC11,0))+IF(Crédits!$K$9="",0,IF(Crédits!$K$9<Crédits!$K$7,AK11,0))+IF(Crédits!$K$10="",0,IF(Crédits!$K$10<Crédits!$K$7,AS11,0)))))) -> 0 | W11: =ROUND(U11-V11,2) -> 2469.16 | X11: =ROUND(X10+Y11-MIN(N(Crédits!$E$7),X10+Y11),2) -> 2469.16 | Y11: =X10*N(Crédits!$D$7)/12 -> 13.195389 | Z11: =AE10 -> 1354.19 | AA11: =Z11*N(Crédits!$D$8)/12 -> 1.35419 | AB11: =MIN(N(Crédits!$E$8),Z11+AA11) -> 95 | AC11: =ROUND(Z11+AA11-AB11,2) -> 1260.54 | AD11: =IF(Crédits!$K$8="",0,MAX(0,MIN(AC11,Plan!$L$13-(IF(Crédits!$K$5="",0,IF(Crédits!$K$5<Crédits!$K$8,E11,0))+IF(Crédits!$K$6="",0,IF(Crédits!$K$6<Crédits!$K$8,M11,0))+IF(Crédits!$K$7="",0,IF(Crédits!$K$7<Crédits!$K$8,U11,0))+IF(Crédits!$K$9="",0,IF(Crédits!$K$9<Crédits!$K$8,AK11,0))+IF(Crédits!$K$10="",0,IF(Crédits!$K$10<Crédits!$K$8,AS11,0)))))) -> 0 | AE11: =ROUND(AC11-AD11,2) -> 1260.54 | AF11: =ROUND(AF10+AG11-MIN(N(Crédits!$E$8),AF10+AG11),2) -> 1260.54 | AG11: =AF10*N(Crédits!$D$8)/12 -> 1.35419 | AH11: =AM10 -> 0 | AI11: =AH11*N(Crédits!$D$9)/12 -> 0 | AJ11: =MIN(N(Crédits!$E$9),AH11+AI11) -> 0 | AK11: =ROUND(AH11+AI11-AJ11,2) -> 0 | AL11: =IF(Crédits!$K$9="",0,MAX(0,MIN(AK11,Plan!$L$13-(IF(Crédits!$K$5="",0,IF(Crédits!$K$5<Crédits!$K$9,E11,0))+IF(Crédits!$K$6="",0,IF(Crédits!$K$6<Crédits!$K$9,M11,0))+IF(Crédits!$K$7="",0,IF(Crédits!$K$7<Crédits!$K$9,U11,0))+IF(Crédits!$K$8="",0,IF(Crédits!$K$8<Crédits!$K$9,AC11,0))+IF(Crédits!$K$10="",0,IF(Crédits!$K$10<Crédits!$K$9,AS11,0)))))) -> 0 | AM11: =ROUND(AK11-AL11,2) -> 0 | AN11: =ROUND(AN10+AO11-MIN(N(Crédits!$E$9),AN10+AO11),2) -> 0 | AO11: =AN10*N(Crédits!$D$9)/12 -> 0 | AP11: =AU10 -> 0 | AQ11: =AP11*N(Crédits!$D$10)/12 -> 0 | AR11: =MIN(N(Crédits!$E$10),AP11+AQ11) -> 0 | AS11: =ROUND(AP11+AQ11-AR11,2) -> 0 | AT11: =IF(Crédits!$K$10="",0,MAX(0,MIN(AS11,Plan!$L$13-(IF(Crédits!$K$5="",0,IF(Crédits!$K$5<Crédits!$K$10,E11,0))+IF(Crédits!$K$6="",0,IF(Crédits!$K$6<Crédits!$K$10,M11,0))+IF(Crédits!$K$7="",0,IF(Crédits!$K$7<Crédits!$K$10,U11,0))+IF(Crédits!$K$8="",0,IF(Crédits!$K$8<Crédits!$K$10,AC11,0))+IF(Crédits!$K$9="",0,IF(Crédits!$K$9<Crédits!$K$10,AK11,0)))))) -> 0 | AU11: =ROUND(AS11-AT11,2) -> 0 | AV11: =ROUND(AV10+AW11-MIN(N(Crédits!$E$10),AV10+AW11),2) -> 0 | AW11: =AV10*N(Crédits!$D$10)/12 -> 0 | AX11: =D11+L11+T11+AB11+AJ11+AR11 -> 531.45 | AY11: =F11+N11+V11+AD11+AL11+AT11 -> 0 | AZ11: =G11+O11+W11+AE11+AM11+AU11 -> 11427.09 | BA11: =C11+K11+S11+AA11+AI11+AQ11 -> 64.390133 | BB11: =I11+Q11+Y11+AG11+AO11+AW11 -> 64.390133
A12: 10 | B12: =G11 -> 6262.2 | C12: =B12*N(Crédits!$D$5)/12 -> 25.57065 | D12: =MIN(N(Crédits!$E$5),B12+C12) -> 245.3 | E12: =ROUND(B12+C12-D12,2) -> 6042.47 | F12: =IF(Crédits!$K$5="",0,MAX(0,MIN(E12,Plan!$L$14-(IF(Crédits!$K$6="",0,IF(Crédits!$K$6<Crédits!$K$5,M12,0))+IF(Crédits!$K$7="",0,IF(Crédits!$K$7<Crédits!$K$5,U12,0))+IF(Crédits!$K$8="",0,IF(Crédits!$K$8<Crédits!$K$5,AC12,0))+IF(Crédits!$K$9="",0,IF(Crédits!$K$9<Crédits!$K$5,AK12,0))+IF(Crédits!$K$10="",0,IF(Crédits!$K$10<Crédits!$K$5,AS12,0)))))) -> 0 | G12: =ROUND(E12-F12,2) -> 6042.47 | H12: =ROUND(H11+I12-MIN(N(Crédits!$E$5),H11+I12),2) -> 6042.47 | I12: =H11*N(Crédits!$D$5)/12 -> 25.57065 | J12: =O11 -> 1435.19 | K12: =J12*N(Crédits!$D$6)/12 -> 22.604243 | L12: =MIN(N(Crédits!$E$6),J12+K12) -> 72.4 | M12: =ROUND(J12+K12-L12,2) -> 1385.39 | N12: =IF(Crédits!$K$6="",0,MAX(0,MIN(M12,Plan!$L$14-(IF(Crédits!$K$5="",0,IF(Crédits!$K$5<Crédits!$K$6,E12,0))+IF(Crédits!$K$7="",0,IF(Crédits!$K$7<Crédits!$K$6,U12,0))+IF(Crédits!$K$8="",0,IF(Crédits!$K$8<Crédits!$K$6,AC12,0))+IF(Crédits!$K$9="",0,IF(Crédits!$K$9<Crédits!$K$6,AK12,0))+IF(Crédits!$K$10="",0,IF(Crédits!$K$10<Crédits!$K$6,AS12,0)))))) -> 0 | O12: =ROUND(M12-N12,2) -> 1385.39 | P12: =ROUND(P11+Q12-MIN(N(Crédits!$E$6),P11+Q12),2) -> 1385.39 | Q12: =P11*N(Crédits!$D$6)/12 -> 22.604243 | R12: =W11 -> 2469.16 | S12: =R12*N(Crédits!$D$7)/12 -> 12.654445 | T12: =MIN(N(Crédits!$E$7),R12+S12) -> 118.75 | U12: =ROUND(R12+S12-T12,2) -> 2363.06 | V12: =IF(Crédits!$K$7="",0,MAX(0,MIN(U12,Plan!$L$14-(IF(Crédits!$K$5="",0,IF(Crédits!$K$5<Crédits!$K$7,E12,0))+IF(Crédits!$K$6="",0,IF(Crédits!$K$6<Crédits!$K$7,M12,0))+IF(Crédits!$K$8="",0,IF(Crédits!$K$8<Crédits!$K$7,AC12,0))+IF(Crédits!$K$9="",0,IF(Crédits!$K$9<Crédits!$K$7,AK12,0))+IF(Crédits!$K$10="",0,IF(Crédits!$K$10<Crédits!$K$7,AS12,0)))))) -> 0 | W12: =ROUND(U12-V12,2) -> 2363.06 | X12: =ROUND(X11+Y12-MIN(N(Crédits!$E$7),X11+Y12),2) -> 2363.06 | Y12: =X11*N(Crédits!$D$7)/12 -> 12.654445 | Z12: =AE11 -> 1260.54 | AA12: =Z12*N(Crédits!$D$8)/12 -> 1.26054 | AB12: =MIN(N(Crédits!$E$8),Z12+AA12) -> 95 | AC12: =ROUND(Z12+AA12-AB12,2) -> 1166.8 | AD12: =IF(Crédits!$K$8="",0,MAX(0,MIN(AC12,Plan!$L$14-(IF(Crédits!$K$5="",0,IF(Crédits!$K$5<Crédits!$K$8,E12,0))+IF(Crédits!$K$6="",0,IF(Crédits!$K$6<Crédits!$K$8,M12,0))+IF(Crédits!$K$7="",0,IF(Crédits!$K$7<Crédits!$K$8,U12,0))+IF(Crédits!$K$9="",0,IF(Crédits!$K$9<Crédits!$K$8,AK12,0))+IF(Crédits!$K$10="",0,IF(Crédits!$K$10<Crédits!$K$8,AS12,0)))))) -> 0 | AE12: =ROUND(AC12-AD12,2) -> 1166.8 | AF12: =ROUND(AF11+AG12-MIN(N(Crédits!$E$8),AF11+AG12),2) -> 1166.8 | AG12: =AF11*N(Crédits!$D$8)/12 -> 1.26054 | AH12: =AM11 -> 0 | AI12: =AH12*N(Crédits!$D$9)/12 -> 0 | AJ12: =MIN(N(Crédits!$E$9),AH12+AI12) -> 0 | AK12: =ROUND(AH12+AI12-AJ12,2) -> 0 | AL12: =IF(Crédits!$K$9="",0,MAX(0,MIN(AK12,Plan!$L$14-(IF(Crédits!$K$5="",0,IF(Crédits!$K$5<Crédits!$K$9,E12,0))+IF(Crédits!$K$6="",0,IF(Crédits!$K$6<Crédits!$K$9,M12,0))+IF(Crédits!$K$7="",0,IF(Crédits!$K$7<Crédits!$K$9,U12,0))+IF(Crédits!$K$8="",0,IF(Crédits!$K$8<Crédits!$K$9,AC12,0))+IF(Crédits!$K$10="",0,IF(Crédits!$K$10<Crédits!$K$9,AS12,0)))))) -> 0 | AM12: =ROUND(AK12-AL12,2) -> 0 | AN12: =ROUND(AN11+AO12-MIN(N(Crédits!$E$9),AN11+AO12),2) -> 0 | AO12: =AN11*N(Crédits!$D$9)/12 -> 0 | AP12: =AU11 -> 0 | AQ12: =AP12*N(Crédits!$D$10)/12 -> 0 | AR12: =MIN(N(Crédits!$E$10),AP12+AQ12) -> 0 | AS12: =ROUND(AP12+AQ12-AR12,2) -> 0 | AT12: =IF(Crédits!$K$10="",0,MAX(0,MIN(AS12,Plan!$L$14-(IF(Crédits!$K$5="",0,IF(Crédits!$K$5<Crédits!$K$10,E12,0))+IF(Crédits!$K$6="",0,IF(Crédits!$K$6<Crédits!$K$10,M12,0))+IF(Crédits!$K$7="",0,IF(Crédits!$K$7<Crédits!$K$10,U12,0))+IF(Crédits!$K$8="",0,IF(Crédits!$K$8<Crédits!$K$10,AC12,0))+IF(Crédits!$K$9="",0,IF(Crédits!$K$9<Crédits!$K$10,AK12,0)))))) -> 0 | AU12: =ROUND(AS12-AT12,2) -> 0 | AV12: =ROUND(AV11+AW12-MIN(N(Crédits!$E$10),AV11+AW12),2) -> 0 | AW12: =AV11*N(Crédits!$D$10)/12 -> 0 | AX12: =D12+L12+T12+AB12+AJ12+AR12 -> 531.45 | AY12: =F12+N12+V12+AD12+AL12+AT12 -> 0 | AZ12: =G12+O12+W12+AE12+AM12+AU12 -> 10957.72 | BA12: =C12+K12+S12+AA12+AI12+AQ12 -> 62.089878 | BB12: =I12+Q12+Y12+AG12+AO12+AW12 -> 62.089878
A13: 11 | B13: =G12 -> 6042.47 | C13: =B13*N(Crédits!$D$5)/12 -> 24.673419 | D13: =MIN(N(Crédits!$E$5),B13+C13) -> 245.3 | E13: =ROUND(B13+C13-D13,2) -> 5821.84 | F13: =IF(Crédits!$K$5="",0,MAX(0,MIN(E13,Plan!$L$15-(IF(Crédits!$K$6="",0,IF(Crédits!$K$6<Crédits!$K$5,M13,0))+IF(Crédits!$K$7="",0,IF(Crédits!$K$7<Crédits!$K$5,U13,0))+IF(Crédits!$K$8="",0,IF(Crédits!$K$8<Crédits!$K$5,AC13,0))+IF(Crédits!$K$9="",0,IF(Crédits!$K$9<Crédits!$K$5,AK13,0))+IF(Crédits!$K$10="",0,IF(Crédits!$K$10<Crédits!$K$5,AS13,0)))))) -> 0 | G13: =ROUND(E13-F13,2) -> 5821.84 | H13: =ROUND(H12+I13-MIN(N(Crédits!$E$5),H12+I13),2) -> 5821.84 | I13: =H12*N(Crédits!$D$5)/12 -> 24.673419 | J13: =O12 -> 1385.39 | K13: =J13*N(Crédits!$D$6)/12 -> 21.819893 | L13: =MIN(N(Crédits!$E$6),J13+K13) -> 72.4 | M13: =ROUND(J13+K13-L13,2) -> 1334.81 | N13: =IF(Crédits!$K$6="",0,MAX(0,MIN(M13,Plan!$L$15-(IF(Crédits!$K$5="",0,IF(Crédits!$K$5<Crédits!$K$6,E13,0))+IF(Crédits!$K$7="",0,IF(Crédits!$K$7<Crédits!$K$6,U13,0))+IF(Crédits!$K$8="",0,IF(Crédits!$K$8<Crédits!$K$6,AC13,0))+IF(Crédits!$K$9="",0,IF(Crédits!$K$9<Crédits!$K$6,AK13,0))+IF(Crédits!$K$10="",0,IF(Crédits!$K$10<Crédits!$K$6,AS13,0)))))) -> 10.65 | O13: =ROUND(M13-N13,2) -> 1324.16 | P13: =ROUND(P12+Q13-MIN(N(Crédits!$E$6),P12+Q13),2) -> 1334.81 | Q13: =P12*N(Crédits!$D$6)/12 -> 21.819893 | R13: =W12 -> 2363.06 | S13: =R13*N(Crédits!$D$7)/12 -> 12.110683 | T13: =MIN(N(Crédits!$E$7),R13+S13) -> 118.75 | U13: =ROUND(R13+S13-T13,2) -> 2256.42 | V13: =IF(Crédits!$K$7="",0,MAX(0,MIN(U13,Plan!$L$15-(IF(Crédits!$K$5="",0,IF(Crédits!$K$5<Crédits!$K$7,E13,0))+IF(Crédits!$K$6="",0,IF(Crédits!$K$6<Crédits!$K$7,M13,0))+IF(Crédits!$K$8="",0,IF(Crédits!$K$8<Crédits!$K$7,AC13,0))+IF(Crédits!$K$9="",0,IF(Crédits!$K$9<Crédits!$K$7,AK13,0))+IF(Crédits!$K$10="",0,IF(Crédits!$K$10<Crédits!$K$7,AS13,0)))))) -> 0 | W13: =ROUND(U13-V13,2) -> 2256.42 | X13: =ROUND(X12+Y13-MIN(N(Crédits!$E$7),X12+Y13),2) -> 2256.42 | Y13: =X12*N(Crédits!$D$7)/12 -> 12.110683 | Z13: =AE12 -> 1166.8 | AA13: =Z13*N(Crédits!$D$8)/12 -> 1.1668 | AB13: =MIN(N(Crédits!$E$8),Z13+AA13) -> 95 | AC13: =ROUND(Z13+AA13-AB13,2) -> 1072.97 | AD13: =IF(Crédits!$K$8="",0,MAX(0,MIN(AC13,Plan!$L$15-(IF(Crédits!$K$5="",0,IF(Crédits!$K$5<Crédits!$K$8,E13,0))+IF(Crédits!$K$6="",0,IF(Crédits!$K$6<Crédits!$K$8,M13,0))+IF(Crédits!$K$7="",0,IF(Crédits!$K$7<Crédits!$K$8,U13,0))+IF(Crédits!$K$9="",0,IF(Crédits!$K$9<Crédits!$K$8,AK13,0))+IF(Crédits!$K$10="",0,IF(Crédits!$K$10<Crédits!$K$8,AS13,0)))))) -> 0 | AE13: =ROUND(AC13-AD13,2) -> 1072.97 | AF13: =ROUND(AF12+AG13-MIN(N(Crédits!$E$8),AF12+AG13),2) -> 1072.97 | AG13: =AF12*N(Crédits!$D$8)/12 -> 1.1668 | AH13: =AM12 -> 0 | AI13: =AH13*N(Crédits!$D$9)/12 -> 0 | AJ13: =MIN(N(Crédits!$E$9),AH13+AI13) -> 0 | AK13: =ROUND(AH13+AI13-AJ13,2) -> 0 | AL13: =IF(Crédits!$K$9="",0,MAX(0,MIN(AK13,Plan!$L$15-(IF(Crédits!$K$5="",0,IF(Crédits!$K$5<Crédits!$K$9,E13,0))+IF(Crédits!$K$6="",0,IF(Crédits!$K$6<Crédits!$K$9,M13,0))+IF(Crédits!$K$7="",0,IF(Crédits!$K$7<Crédits!$K$9,U13,0))+IF(Crédits!$K$8="",0,IF(Crédits!$K$8<Crédits!$K$9,AC13,0))+IF(Crédits!$K$10="",0,IF(Crédits!$K$10<Crédits!$K$9,AS13,0)))))) -> 0 | AM13: =ROUND(AK13-AL13,2) -> 0 | AN13: =ROUND(AN12+AO13-MIN(N(Crédits!$E$9),AN12+AO13),2) -> 0 | AO13: =AN12*N(Crédits!$D$9)/12 -> 0 | AP13: =AU12 -> 0 | AQ13: =AP13*N(Crédits!$D$10)/12 -> 0 | AR13: =MIN(N(Crédits!$E$10),AP13+AQ13) -> 0 | AS13: =ROUND(AP13+AQ13-AR13,2) -> 0 | AT13: =IF(Crédits!$K$10="",0,MAX(0,MIN(AS13,Plan!$L$15-(IF(Crédits!$K$5="",0,IF(Crédits!$K$5<Crédits!$K$10,E13,0))+IF(Crédits!$K$6="",0,IF(Crédits!$K$6<Crédits!$K$10,M13,0))+IF(Crédits!$K$7="",0,IF(Crédits!$K$7<Crédits!$K$10,U13,0))+IF(Crédits!$K$8="",0,IF(Crédits!$K$8<Crédits!$K$10,AC13,0))+IF(Crédits!$K$9="",0,IF(Crédits!$K$9<Crédits!$K$10,AK13,0)))))) -> 0 | AU13: =ROUND(AS13-AT13,2) -> 0 | AV13: =ROUND(AV12+AW13-MIN(N(Crédits!$E$10),AV12+AW13),2) -> 0 | AW13: =AV12*N(Crédits!$D$10)/12 -> 0 | AX13: =D13+L13+T13+AB13+AJ13+AR13 -> 531.45 | AY13: =F13+N13+V13+AD13+AL13+AT13 -> 10.65 | AZ13: =G13+O13+W13+AE13+AM13+AU13 -> 10475.39 | BA13: =C13+K13+S13+AA13+AI13+AQ13 -> 59.770794 | BB13: =I13+Q13+Y13+AG13+AO13+AW13 -> 59.770794
A14: 12 | B14: =G13 -> 5821.84 | C14: =B14*N(Crédits!$D$5)/12 -> 23.772513 | D14: =MIN(N(Crédits!$E$5),B14+C14) -> 245.3 | E14: =ROUND(B14+C14-D14,2) -> 5600.31 | F14: =IF(Crédits!$K$5="",0,MAX(0,MIN(E14,Plan!$L$16-(IF(Crédits!$K$6="",0,IF(Crédits!$K$6<Crédits!$K$5,M14,0))+IF(Crédits!$K$7="",0,IF(Crédits!$K$7<Crédits!$K$5,U14,0))+IF(Crédits!$K$8="",0,IF(Crédits!$K$8<Crédits!$K$5,AC14,0))+IF(Crédits!$K$9="",0,IF(Crédits!$K$9<Crédits!$K$5,AK14,0))+IF(Crédits!$K$10="",0,IF(Crédits!$K$10<Crédits!$K$5,AS14,0)))))) -> 0 | G14: =ROUND(E14-F14,2) -> 5600.31 | H14: =ROUND(H13+I14-MIN(N(Crédits!$E$5),H13+I14),2) -> 5600.31 | I14: =H13*N(Crédits!$D$5)/12 -> 23.772513 | J14: =O13 -> 1324.16 | K14: =J14*N(Crédits!$D$6)/12 -> 20.85552 | L14: =MIN(N(Crédits!$E$6),J14+K14) -> 72.4 | M14: =ROUND(J14+K14-L14,2) -> 1272.62 | N14: =IF(Crédits!$K$6="",0,MAX(0,MIN(M14,Plan!$L$16-(IF(Crédits!$K$5="",0,IF(Crédits!$K$5<Crédits!$K$6,E14,0))+IF(Crédits!$K$7="",0,IF(Crédits!$K$7<Crédits!$K$6,U14,0))+IF(Crédits!$K$8="",0,IF(Crédits!$K$8<Crédits!$K$6,AC14,0))+IF(Crédits!$K$9="",0,IF(Crédits!$K$9<Crédits!$K$6,AK14,0))+IF(Crédits!$K$10="",0,IF(Crédits!$K$10<Crédits!$K$6,AS14,0)))))) -> 386.13 | O14: =ROUND(M14-N14,2) -> 886.49 | P14: =ROUND(P13+Q14-MIN(N(Crédits!$E$6),P13+Q14),2) -> 1283.43 | Q14: =P13*N(Crédits!$D$6)/12 -> 21.023257 | R14: =W13 -> 2256.42 | S14: =R14*N(Crédits!$D$7)/12 -> 11.564153 | T14: =MIN(N(Crédits!$E$7),R14+S14) -> 118.75 | U14: =ROUND(R14+S14-T14,2) -> 2149.23 | V14: =IF(Crédits!$K$7="",0,MAX(0,MIN(U14,Plan!$L$16-(IF(Crédits!$K$5="",0,IF(Crédits!$K$5<Crédits!$K$7,E14,0))+IF(Crédits!$K$6="",0,IF(Crédits!$K$6<Crédits!$K$7,M14,0))+IF(Crédits!$K$8="",0,IF(Crédits!$K$8<Crédits!$K$7,AC14,0))+IF(Crédits!$K$9="",0,IF(Crédits!$K$9<Crédits!$K$7,AK14,0))+IF(Crédits!$K$10="",0,IF(Crédits!$K$10<Crédits!$K$7,AS14,0)))))) -> 0 | W14: =ROUND(U14-V14,2) -> 2149.23 | X14: =ROUND(X13+Y14-MIN(N(Crédits!$E$7),X13+Y14),2) -> 2149.23 | Y14: =X13*N(Crédits!$D$7)/12 -> 11.564153 | Z14: =AE13 -> 1072.97 | AA14: =Z14*N(Crédits!$D$8)/12 -> 1.07297 | AB14: =MIN(N(Crédits!$E$8),Z14+AA14) -> 95 | AC14: =ROUND(Z14+AA14-AB14,2) -> 979.04 | AD14: =IF(Crédits!$K$8="",0,MAX(0,MIN(AC14,Plan!$L$16-(IF(Crédits!$K$5="",0,IF(Crédits!$K$5<Crédits!$K$8,E14,0))+IF(Crédits!$K$6="",0,IF(Crédits!$K$6<Crédits!$K$8,M14,0))+IF(Crédits!$K$7="",0,IF(Crédits!$K$7<Crédits!$K$8,U14,0))+IF(Crédits!$K$9="",0,IF(Crédits!$K$9<Crédits!$K$8,AK14,0))+IF(Crédits!$K$10="",0,IF(Crédits!$K$10<Crédits!$K$8,AS14,0)))))) -> 0 | AE14: =ROUND(AC14-AD14,2) -> 979.04 | AF14: =ROUND(AF13+AG14-MIN(N(Crédits!$E$8),AF13+AG14),2) -> 979.04 | AG14: =AF13*N(Crédits!$D$8)/12 -> 1.07297 | AH14: =AM13 -> 0 | AI14: =AH14*N(Crédits!$D$9)/12 -> 0 | AJ14: =MIN(N(Crédits!$E$9),AH14+AI14) -> 0 | AK14: =ROUND(AH14+AI14-AJ14,2) -> 0 | AL14: =IF(Crédits!$K$9="",0,MAX(0,MIN(AK14,Plan!$L$16-(IF(Crédits!$K$5="",0,IF(Crédits!$K$5<Crédits!$K$9,E14,0))+IF(Crédits!$K$6="",0,IF(Crédits!$K$6<Crédits!$K$9,M14,0))+IF(Crédits!$K$7="",0,IF(Crédits!$K$7<Crédits!$K$9,U14,0))+IF(Crédits!$K$8="",0,IF(Crédits!$K$8<Crédits!$K$9,AC14,0))+IF(Crédits!$K$10="",0,IF(Crédits!$K$10<Crédits!$K$9,AS14,0)))))) -> 0 | AM14: =ROUND(AK14-AL14,2) -> 0 | AN14: =ROUND(AN13+AO14-MIN(N(Crédits!$E$9),AN13+AO14),2) -> 0 | AO14: =AN13*N(Crédits!$D$9)/12 -> 0 | AP14: =AU13 -> 0 | AQ14: =AP14*N(Crédits!$D$10)/12 -> 0 | AR14: =MIN(N(Crédits!$E$10),AP14+AQ14) -> 0 | AS14: =ROUND(AP14+AQ14-AR14,2) -> 0 | AT14: =IF(Crédits!$K$10="",0,MAX(0,MIN(AS14,Plan!$L$16-(IF(Crédits!$K$5="",0,IF(Crédits!$K$5<Crédits!$K$10,E14,0))+IF(Crédits!$K$6="",0,IF(Crédits!$K$6<Crédits!$K$10,M14,0))+IF(Crédits!$K$7="",0,IF(Crédits!$K$7<Crédits!$K$10,U14,0))+IF(Crédits!$K$8="",0,IF(Crédits!$K$8<Crédits!$K$10,AC14,0))+IF(Crédits!$K$9="",0,IF(Crédits!$K$9<Crédits!$K$10,AK14,0)))))) -> 0 | AU14: =ROUND(AS14-AT14,2) -> 0 | AV14: =ROUND(AV13+AW14-MIN(N(Crédits!$E$10),AV13+AW14),2) -> 0 | AW14: =AV13*N(Crédits!$D$10)/12 -> 0 | AX14: =D14+L14+T14+AB14+AJ14+AR14 -> 531.45 | AY14: =F14+N14+V14+AD14+AL14+AT14 -> 386.13 | AZ14: =G14+O14+W14+AE14+AM14+AU14 -> 9615.07 | BA14: =C14+K14+S14+AA14+AI14+AQ14 -> 57.265156 | BB14: =I14+Q14+Y14+AG14+AO14+AW14 -> 57.432893
A15: 13 | B15: =G14 -> 5600.31 | C15: =B15*N(Crédits!$D$5)/12 -> 22.867933 | D15: =MIN(N(Crédits!$E$5),B15+C15) -> 245.3 | E15: =ROUND(B15+C15-D15,2) -> 5377.88 | F15: =IF(Crédits!$K$5="",0,MAX(0,MIN(E15,Plan!$L$17-(IF(Crédits!$K$6="",0,IF(Crédits!$K$6<Crédits!$K$5,M15,0))+IF(Crédits!$K$7="",0,IF(Crédits!$K$7<Crédits!$K$5,U15,0))+IF(Crédits!$K$8="",0,IF(Crédits!$K$8<Crédits!$K$5,AC15,0))+IF(Crédits!$K$9="",0,IF(Crédits!$K$9<Crédits!$K$5,AK15,0))+IF(Crédits!$K$10="",0,IF(Crédits!$K$10<Crédits!$K$5,AS15,0)))))) -> 0 | G15: =ROUND(E15-F15,2) -> 5377.88 | H15: =ROUND(H14+I15-MIN(N(Crédits!$E$5),H14+I15),2) -> 5377.88 | I15: =H14*N(Crédits!$D$5)/12 -> 22.867933 | J15: =O14 -> 886.49 | K15: =J15*N(Crédits!$D$6)/12 -> 13.962218 | L15: =MIN(N(Crédits!$E$6),J15+K15) -> 72.4 | M15: =ROUND(J15+K15-L15,2) -> 828.05 | N15: =IF(Crédits!$K$6="",0,MAX(0,MIN(M15,Plan!$L$17-(IF(Crédits!$K$5="",0,IF(Crédits!$K$5<Crédits!$K$6,E15,0))+IF(Crédits!$K$7="",0,IF(Crédits!$K$7<Crédits!$K$6,U15,0))+IF(Crédits!$K$8="",0,IF(Crédits!$K$8<Crédits!$K$6,AC15,0))+IF(Crédits!$K$9="",0,IF(Crédits!$K$9<Crédits!$K$6,AK15,0))+IF(Crédits!$K$10="",0,IF(Crédits!$K$10<Crédits!$K$6,AS15,0)))))) -> 386.13 | O15: =ROUND(M15-N15,2) -> 441.92 | P15: =ROUND(P14+Q15-MIN(N(Crédits!$E$6),P14+Q15),2) -> 1231.24 | Q15: =P14*N(Crédits!$D$6)/12 -> 20.214023 | R15: =W14 -> 2149.23 | S15: =R15*N(Crédits!$D$7)/12 -> 11.014804 | T15: =MIN(N(Crédits!$E$7),R15+S15) -> 118.75 | U15: =ROUND(R15+S15-T15,2) -> 2041.49 | V15: =IF(Crédits!$K$7="",0,MAX(0,MIN(U15,Plan!$L$17-(IF(Crédits!$K$5="",0,IF(Crédits!$K$5<Crédits!$K$7,E15,0))+IF(Crédits!$K$6="",0,IF(Crédits!$K$6<Crédits!$K$7,M15,0))+IF(Crédits!$K$8="",0,IF(Crédits!$K$8<Crédits!$K$7,AC15,0))+IF(Crédits!$K$9="",0,IF(Crédits!$K$9<Crédits!$K$7,AK15,0))+IF(Crédits!$K$10="",0,IF(Crédits!$K$10<Crédits!$K$7,AS15,0)))))) -> 0 | W15: =ROUND(U15-V15,2) -> 2041.49 | X15: =ROUND(X14+Y15-MIN(N(Crédits!$E$7),X14+Y15),2) -> 2041.49 | Y15: =X14*N(Crédits!$D$7)/12 -> 11.014804 | Z15: =AE14 -> 979.04 | AA15: =Z15*N(Crédits!$D$8)/12 -> 0.97904 | AB15: =MIN(N(Crédits!$E$8),Z15+AA15) -> 95 | AC15: =ROUND(Z15+AA15-AB15,2) -> 885.02 | AD15: =IF(Crédits!$K$8="",0,MAX(0,MIN(AC15,Plan!$L$17-(IF(Crédits!$K$5="",0,IF(Crédits!$K$5<Crédits!$K$8,E15,0))+IF(Crédits!$K$6="",0,IF(Crédits!$K$6<Crédits!$K$8,M15,0))+IF(Crédits!$K$7="",0,IF(Crédits!$K$7<Crédits!$K$8,U15,0))+IF(Crédits!$K$9="",0,IF(Crédits!$K$9<Crédits!$K$8,AK15,0))+IF(Crédits!$K$10="",0,IF(Crédits!$K$10<Crédits!$K$8,AS15,0)))))) -> 0 | AE15: =ROUND(AC15-AD15,2) -> 885.02 | AF15: =ROUND(AF14+AG15-MIN(N(Crédits!$E$8),AF14+AG15),2) -> 885.02 | AG15: =AF14*N(Crédits!$D$8)/12 -> 0.97904 | AH15: =AM14 -> 0 | AI15: =AH15*N(Crédits!$D$9)/12 -> 0 | AJ15: =MIN(N(Crédits!$E$9),AH15+AI15) -> 0 | AK15: =ROUND(AH15+AI15-AJ15,2) -> 0 | AL15: =IF(Crédits!$K$9="",0,MAX(0,MIN(AK15,Plan!$L$17-(IF(Crédits!$K$5="",0,IF(Crédits!$K$5<Crédits!$K$9,E15,0))+IF(Crédits!$K$6="",0,IF(Crédits!$K$6<Crédits!$K$9,M15,0))+IF(Crédits!$K$7="",0,IF(Crédits!$K$7<Crédits!$K$9,U15,0))+IF(Crédits!$K$8="",0,IF(Crédits!$K$8<Crédits!$K$9,AC15,0))+IF(Crédits!$K$10="",0,IF(Crédits!$K$10<Crédits!$K$9,AS15,0)))))) -> 0 | AM15: =ROUND(AK15-AL15,2) -> 0 | AN15: =ROUND(AN14+AO15-MIN(N(Crédits!$E$9),AN14+AO15),2) -> 0 | AO15: =AN14*N(Crédits!$D$9)/12 -> 0 | AP15: =AU14 -> 0 | AQ15: =AP15*N(Crédits!$D$10)/12 -> 0 | AR15: =MIN(N(Crédits!$E$10),AP15+AQ15) -> 0 | AS15: =ROUND(AP15+AQ15-AR15,2) -> 0 | AT15: =IF(Crédits!$K$10="",0,MAX(0,MIN(AS15,Plan!$L$17-(IF(Crédits!$K$5="",0,IF(Crédits!$K$5<Crédits!$K$10,E15,0))+IF(Crédits!$K$6="",0,IF(Crédits!$K$6<Crédits!$K$10,M15,0))+IF(Crédits!$K$7="",0,IF(Crédits!$K$7<Crédits!$K$10,U15,0))+IF(Crédits!$K$8="",0,IF(Crédits!$K$8<Crédits!$K$10,AC15,0))+IF(Crédits!$K$9="",0,IF(Crédits!$K$9<Crédits!$K$10,AK15,0)))))) -> 0 | AU15: =ROUND(AS15-AT15,2) -> 0 | AV15: =ROUND(AV14+AW15-MIN(N(Crédits!$E$10),AV14+AW15),2) -> 0 | AW15: =AV14*N(Crédits!$D$10)/12 -> 0 | AX15: =D15+L15+T15+AB15+AJ15+AR15 -> 531.45 | AY15: =F15+N15+V15+AD15+AL15+AT15 -> 386.13 | AZ15: =G15+O15+W15+AE15+AM15+AU15 -> 8746.31 | BA15: =C15+K15+S15+AA15+AI15+AQ15 -> 48.823994 | BB15: =I15+Q15+Y15+AG15+AO15+AW15 -> 55.075799
A16: 14 | B16: =G15 -> 5377.88 | C16: =B16*N(Crédits!$D$5)/12 -> 21.959677 | D16: =MIN(N(Crédits!$E$5),B16+C16) -> 245.3 | E16: =ROUND(B16+C16-D16,2) -> 5154.54 | F16: =IF(Crédits!$K$5="",0,MAX(0,MIN(E16,Plan!$L$18-(IF(Crédits!$K$6="",0,IF(Crédits!$K$6<Crédits!$K$5,M16,0))+IF(Crédits!$K$7="",0,IF(Crédits!$K$7<Crédits!$K$5,U16,0))+IF(Crédits!$K$8="",0,IF(Crédits!$K$8<Crédits!$K$5,AC16,0))+IF(Crédits!$K$9="",0,IF(Crédits!$K$9<Crédits!$K$5,AK16,0))+IF(Crédits!$K$10="",0,IF(Crédits!$K$10<Crédits!$K$5,AS16,0)))))) -> 0 | G16: =ROUND(E16-F16,2) -> 5154.54 | H16: =ROUND(H15+I16-MIN(N(Crédits!$E$5),H15+I16),2) -> 5154.54 | I16: =H15*N(Crédits!$D$5)/12 -> 21.959677 | J16: =O15 -> 441.92 | K16: =J16*N(Crédits!$D$6)/12 -> 6.96024 | L16: =MIN(N(Crédits!$E$6),J16+K16) -> 72.4 | M16: =ROUND(J16+K16-L16,2) -> 376.48 | N16: =IF(Crédits!$K$6="",0,MAX(0,MIN(M16,Plan!$L$18-(IF(Crédits!$K$5="",0,IF(Crédits!$K$5<Crédits!$K$6,E16,0))+IF(Crédits!$K$7="",0,IF(Crédits!$K$7<Crédits!$K$6,U16,0))+IF(Crédits!$K$8="",0,IF(Crédits!$K$8<Crédits!$K$6,AC16,0))+IF(Crédits!$K$9="",0,IF(Crédits!$K$9<Crédits!$K$6,AK16,0))+IF(Crédits!$K$10="",0,IF(Crédits!$K$10<Crédits!$K$6,AS16,0)))))) -> 376.48 | O16: =ROUND(M16-N16,2) -> 0 | P16: =ROUND(P15+Q16-MIN(N(Crédits!$E$6),P15+Q16),2) -> 1178.23 | Q16: =P15*N(Crédits!$D$6)/12 -> 19.39203 | R16: =W15 -> 2041.49 | S16: =R16*N(Crédits!$D$7)/12 -> 10.462636 | T16: =MIN(N(Crédits!$E$7),R16+S16) -> 118.75 | U16: =ROUND(R16+S16-T16,2) -> 1933.2 | V16: =IF(Crédits!$K$7="",0,MAX(0,MIN(U16,Plan!$L$18-(IF(Crédits!$K$5="",0,IF(Crédits!$K$5<Crédits!$K$7,E16,0))+IF(Crédits!$K$6="",0,IF(Crédits!$K$6<Crédits!$K$7,M16,0))+IF(Crédits!$K$8="",0,IF(Crédits!$K$8<Crédits!$K$7,AC16,0))+IF(Crédits!$K$9="",0,IF(Crédits!$K$9<Crédits!$K$7,AK16,0))+IF(Crédits!$K$10="",0,IF(Crédits!$K$10<Crédits!$K$7,AS16,0)))))) -> 9.65 | W16: =ROUND(U16-V16,2) -> 1923.55 | X16: =ROUND(X15+Y16-MIN(N(Crédits!$E$7),X15+Y16),2) -> 1933.2 | Y16: =X15*N(Crédits!$D$7)/12 -> 10.462636 | Z16: =AE15 -> 885.02 | AA16: =Z16*N(Crédits!$D$8)/12 -> 0.88502 | AB16: =MIN(N(Crédits!$E$8),Z16+AA16) -> 95 | AC16: =ROUND(Z16+AA16-AB16,2) -> 790.91 | AD16: =IF(Crédits!$K$8="",0,MAX(0,MIN(AC16,Plan!$L$18-(IF(Crédits!$K$5="",0,IF(Crédits!$K$5<Crédits!$K$8,E16,0))+IF(Crédits!$K$6="",0,IF(Crédits!$K$6<Crédits!$K$8,M16,0))+IF(Crédits!$K$7="",0,IF(Crédits!$K$7<Crédits!$K$8,U16,0))+IF(Crédits!$K$9="",0,IF(Crédits!$K$9<Crédits!$K$8,AK16,0))+IF(Crédits!$K$10="",0,IF(Crédits!$K$10<Crédits!$K$8,AS16,0)))))) -> 0 | AE16: =ROUND(AC16-AD16,2) -> 790.91 | AF16: =ROUND(AF15+AG16-MIN(N(Crédits!$E$8),AF15+AG16),2) -> 790.91 | AG16: =AF15*N(Crédits!$D$8)/12 -> 0.88502 | AH16: =AM15 -> 0 | AI16: =AH16*N(Crédits!$D$9)/12 -> 0 | AJ16: =MIN(N(Crédits!$E$9),AH16+AI16) -> 0 | AK16: =ROUND(AH16+AI16-AJ16,2) -> 0 | AL16: =IF(Crédits!$K$9="",0,MAX(0,MIN(AK16,Plan!$L$18-(IF(Crédits!$K$5="",0,IF(Crédits!$K$5<Crédits!$K$9,E16,0))+IF(Crédits!$K$6="",0,IF(Crédits!$K$6<Crédits!$K$9,M16,0))+IF(Crédits!$K$7="",0,IF(Crédits!$K$7<Crédits!$K$9,U16,0))+IF(Crédits!$K$8="",0,IF(Crédits!$K$8<Crédits!$K$9,AC16,0))+IF(Crédits!$K$10="",0,IF(Crédits!$K$10<Crédits!$K$9,AS16,0)))))) -> 0 | AM16: =ROUND(AK16-AL16,2) -> 0 | AN16: =ROUND(AN15+AO16-MIN(N(Crédits!$E$9),AN15+AO16),2) -> 0 | AO16: =AN15*N(Crédits!$D$9)/12 -> 0 | AP16: =AU15 -> 0 | AQ16: =AP16*N(Crédits!$D$10)/12 -> 0 | AR16: =MIN(N(Crédits!$E$10),AP16+AQ16) -> 0 | AS16: =ROUND(AP16+AQ16-AR16,2) -> 0 | AT16: =IF(Crédits!$K$10="",0,MAX(0,MIN(AS16,Plan!$L$18-(IF(Crédits!$K$5="",0,IF(Crédits!$K$5<Crédits!$K$10,E16,0))+IF(Crédits!$K$6="",0,IF(Crédits!$K$6<Crédits!$K$10,M16,0))+IF(Crédits!$K$7="",0,IF(Crédits!$K$7<Crédits!$K$10,U16,0))+IF(Crédits!$K$8="",0,IF(Crédits!$K$8<Crédits!$K$10,AC16,0))+IF(Crédits!$K$9="",0,IF(Crédits!$K$9<Crédits!$K$10,AK16,0)))))) -> 0 | AU16: =ROUND(AS16-AT16,2) -> 0 | AV16: =ROUND(AV15+AW16-MIN(N(Crédits!$E$10),AV15+AW16),2) -> 0 | AW16: =AV15*N(Crédits!$D$10)/12 -> 0 | AX16: =D16+L16+T16+AB16+AJ16+AR16 -> 531.45 | AY16: =F16+N16+V16+AD16+AL16+AT16 -> 386.13 | AZ16: =G16+O16+W16+AE16+AM16+AU16 -> 7869 | BA16: =C16+K16+S16+AA16+AI16+AQ16 -> 40.267573 | BB16: =I16+Q16+Y16+AG16+AO16+AW16 -> 52.699363
A17: 15 | B17: =G16 -> 5154.54 | C17: =B17*N(Crédits!$D$5)/12 -> 21.047705 | D17: =MIN(N(Crédits!$E$5),B17+C17) -> 245.3 | E17: =ROUND(B17+C17-D17,2) -> 4930.29 | F17: =IF(Crédits!$K$5="",0,MAX(0,MIN(E17,Plan!$L$19-(IF(Crédits!$K$6="",0,IF(Crédits!$K$6<Crédits!$K$5,M17,0))+IF(Crédits!$K$7="",0,IF(Crédits!$K$7<Crédits!$K$5,U17,0))+IF(Crédits!$K$8="",0,IF(Crédits!$K$8<Crédits!$K$5,AC17,0))+IF(Crédits!$K$9="",0,IF(Crédits!$K$9<Crédits!$K$5,AK17,0))+IF(Crédits!$K$10="",0,IF(Crédits!$K$10<Crédits!$K$5,AS17,0)))))) -> 0 | G17: =ROUND(E17-F17,2) -> 4930.29 | H17: =ROUND(H16+I17-MIN(N(Crédits!$E$5),H16+I17),2) -> 4930.29 | I17: =H16*N(Crédits!$D$5)/12 -> 21.047705 | J17: =O16 -> 0 | K17: =J17*N(Crédits!$D$6)/12 -> 0 | L17: =MIN(N(Crédits!$E$6),J17+K17) -> 0 | M17: =ROUND(J17+K17-L17,2) -> 0 | N17: =IF(Crédits!$K$6="",0,MAX(0,MIN(M17,Plan!$L$19-(IF(Crédits!$K$5="",0,IF(Crédits!$K$5<Crédits!$K$6,E17,0))+IF(Crédits!$K$7="",0,IF(Crédits!$K$7<Crédits!$K$6,U17,0))+IF(Crédits!$K$8="",0,IF(Crédits!$K$8<Crédits!$K$6,AC17,0))+IF(Crédits!$K$9="",0,IF(Crédits!$K$9<Crédits!$K$6,AK17,0))+IF(Crédits!$K$10="",0,IF(Crédits!$K$10<Crédits!$K$6,AS17,0)))))) -> 0 | O17: =ROUND(M17-N17,2) -> 0 | P17: =ROUND(P16+Q17-MIN(N(Crédits!$E$6),P16+Q17),2) -> 1124.39 | Q17: =P16*N(Crédits!$D$6)/12 -> 18.557123 | R17: =W16 -> 1923.55 | S17: =R17*N(Crédits!$D$7)/12 -> 9.8581937 | T17: =MIN(N(Crédits!$E$7),R17+S17) -> 118.75 | U17: =ROUND(R17+S17-T17,2) -> 1814.66 | V17: =IF(Crédits!$K$7="",0,MAX(0,MIN(U17,Plan!$L$19-(IF(Crédits!$K$5="",0,IF(Crédits!$K$5<Crédits!$K$7,E17,0))+IF(Crédits!$K$6="",0,IF(Crédits!$K$6<Crédits!$K$7,M17,0))+IF(Crédits!$K$8="",0,IF(Crédits!$K$8<Crédits!$K$7,AC17,0))+IF(Crédits!$K$9="",0,IF(Crédits!$K$9<Crédits!$K$7,AK17,0))+IF(Crédits!$K$10="",0,IF(Crédits!$K$10<Crédits!$K$7,AS17,0)))))) -> 429.57 | W17: =ROUND(U17-V17,2) -> 1385.09 | X17: =ROUND(X16+Y17-MIN(N(Crédits!$E$7),X16+Y17),2) -> 1824.36 | Y17: =X16*N(Crédits!$D$7)/12 -> 9.90765 | Z17: =AE16 -> 790.91 | AA17: =Z17*N(Crédits!$D$8)/12 -> 0.79091 | AB17: =MIN(N(Crédits!$E$8),Z17+AA17) -> 95 | AC17: =ROUND(Z17+AA17-AB17,2) -> 696.7 | AD17: =IF(Crédits!$K$8="",0,MAX(0,MIN(AC17,Plan!$L$19-(IF(Crédits!$K$5="",0,IF(Crédits!$K$5<Crédits!$K$8,E17,0))+IF(Crédits!$K$6="",0,IF(Crédits!$K$6<Crédits!$K$8,M17,0))+IF(Crédits!$K$7="",0,IF(Crédits!$K$7<Crédits!$K$8,U17,0))+IF(Crédits!$K$9="",0,IF(Crédits!$K$9<Crédits!$K$8,AK17,0))+IF(Crédits!$K$10="",0,IF(Crédits!$K$10<Crédits!$K$8,AS17,0)))))) -> 0 | AE17: =ROUND(AC17-AD17,2) -> 696.7 | AF17: =ROUND(AF16+AG17-MIN(N(Crédits!$E$8),AF16+AG17),2) -> 696.7 | AG17: =AF16*N(Crédits!$D$8)/12 -> 0.79091 | AH17: =AM16 -> 0 | AI17: =AH17*N(Crédits!$D$9)/12 -> 0 | AJ17: =MIN(N(Crédits!$E$9),AH17+AI17) -> 0 | AK17: =ROUND(AH17+AI17-AJ17,2) -> 0 | AL17: =IF(Crédits!$K$9="",0,MAX(0,MIN(AK17,Plan!$L$19-(IF(Crédits!$K$5="",0,IF(Crédits!$K$5<Crédits!$K$9,E17,0))+IF(Crédits!$K$6="",0,IF(Crédits!$K$6<Crédits!$K$9,M17,0))+IF(Crédits!$K$7="",0,IF(Crédits!$K$7<Crédits!$K$9,U17,0))+IF(Crédits!$K$8="",0,IF(Crédits!$K$8<Crédits!$K$9,AC17,0))+IF(Crédits!$K$10="",0,IF(Crédits!$K$10<Crédits!$K$9,AS17,0)))))) -> 0 | AM17: =ROUND(AK17-AL17,2) -> 0 | AN17: =ROUND(AN16+AO17-MIN(N(Crédits!$E$9),AN16+AO17),2) -> 0 | AO17: =AN16*N(Crédits!$D$9)/12 -> 0 | AP17: =AU16 -> 0 | AQ17: =AP17*N(Crédits!$D$10)/12 -> 0 | AR17: =MIN(N(Crédits!$E$10),AP17+AQ17) -> 0 | AS17: =ROUND(AP17+AQ17-AR17,2) -> 0 | AT17: =IF(Crédits!$K$10="",0,MAX(0,MIN(AS17,Plan!$L$19-(IF(Crédits!$K$5="",0,IF(Crédits!$K$5<Crédits!$K$10,E17,0))+IF(Crédits!$K$6="",0,IF(Crédits!$K$6<Crédits!$K$10,M17,0))+IF(Crédits!$K$7="",0,IF(Crédits!$K$7<Crédits!$K$10,U17,0))+IF(Crédits!$K$8="",0,IF(Crédits!$K$8<Crédits!$K$10,AC17,0))+IF(Crédits!$K$9="",0,IF(Crédits!$K$9<Crédits!$K$10,AK17,0)))))) -> 0 | AU17: =ROUND(AS17-AT17,2) -> 0 | AV17: =ROUND(AV16+AW17-MIN(N(Crédits!$E$10),AV16+AW17),2) -> 0 | AW17: =AV16*N(Crédits!$D$10)/12 -> 0 | AX17: =D17+L17+T17+AB17+AJ17+AR17 -> 459.05 | AY17: =F17+N17+V17+AD17+AL17+AT17 -> 429.57 | AZ17: =G17+O17+W17+AE17+AM17+AU17 -> 7012.08 | BA17: =C17+K17+S17+AA17+AI17+AQ17 -> 31.696809 | BB17: =I17+Q17+Y17+AG17+AO17+AW17 -> 50.303387
A18: 16 | B18: =G17 -> 4930.29 | C18: =B18*N(Crédits!$D$5)/12 -> 20.132017 | D18: =MIN(N(Crédits!$E$5),B18+C18) -> 245.3 | E18: =ROUND(B18+C18-D18,2) -> 4705.12 | F18: =IF(Crédits!$K$5="",0,MAX(0,MIN(E18,Plan!$L$20-(IF(Crédits!$K$6="",0,IF(Crédits!$K$6<Crédits!$K$5,M18,0))+IF(Crédits!$K$7="",0,IF(Crédits!$K$7<Crédits!$K$5,U18,0))+IF(Crédits!$K$8="",0,IF(Crédits!$K$8<Crédits!$K$5,AC18,0))+IF(Crédits!$K$9="",0,IF(Crédits!$K$9<Crédits!$K$5,AK18,0))+IF(Crédits!$K$10="",0,IF(Crédits!$K$10<Crédits!$K$5,AS18,0)))))) -> 0 | G18: =ROUND(E18-F18,2) -> 4705.12 | H18: =ROUND(H17+I18-MIN(N(Crédits!$E$5),H17+I18),2) -> 4705.12 | I18: =H17*N(Crédits!$D$5)/12 -> 20.132017 | J18: =O17 -> 0 | K18: =J18*N(Crédits!$D$6)/12 -> 0 | L18: =MIN(N(Crédits!$E$6),J18+K18) -> 0 | M18: =ROUND(J18+K18-L18,2) -> 0 | N18: =IF(Crédits!$K$6="",0,MAX(0,MIN(M18,Plan!$L$20-(IF(Crédits!$K$5="",0,IF(Crédits!$K$5<Crédits!$K$6,E18,0))+IF(Crédits!$K$7="",0,IF(Crédits!$K$7<Crédits!$K$6,U18,0))+IF(Crédits!$K$8="",0,IF(Crédits!$K$8<Crédits!$K$6,AC18,0))+IF(Crédits!$K$9="",0,IF(Crédits!$K$9<Crédits!$K$6,AK18,0))+IF(Crédits!$K$10="",0,IF(Crédits!$K$10<Crédits!$K$6,AS18,0)))))) -> 0 | O18: =ROUND(M18-N18,2) -> 0 | P18: =ROUND(P17+Q18-MIN(N(Crédits!$E$6),P17+Q18),2) -> 1069.7 | Q18: =P17*N(Crédits!$D$6)/12 -> 17.709143 | R18: =W17 -> 1385.09 | S18: =R18*N(Crédits!$D$7)/12 -> 7.0985862 | T18: =MIN(N(Crédits!$E$7),R18+S18) -> 118.75 | U18: =ROUND(R18+S18-T18,2) -> 1273.44 | V18: =IF(Crédits!$K$7="",0,MAX(0,MIN(U18,Plan!$L$20-(IF(Crédits!$K$5="",0,IF(Crédits!$K$5<Crédits!$K$7,E18,0))+IF(Crédits!$K$6="",0,IF(Crédits!$K$6<Crédits!$K$7,M18,0))+IF(Crédits!$K$8="",0,IF(Crédits!$K$8<Crédits!$K$7,AC18,0))+IF(Crédits!$K$9="",0,IF(Crédits!$K$9<Crédits!$K$7,AK18,0))+IF(Crédits!$K$10="",0,IF(Crédits!$K$10<Crédits!$K$7,AS18,0)))))) -> 429.57 | W18: =ROUND(U18-V18,2) -> 843.87 | X18: =ROUND(X17+Y18-MIN(N(Crédits!$E$7),X17+Y18),2) -> 1714.96 | Y18: =X17*N(Crédits!$D$7)/12 -> 9.349845 | Z18: =AE17 -> 696.7 | AA18: =Z18*N(Crédits!$D$8)/12 -> 0.6967 | AB18: =MIN(N(Crédits!$E$8),Z18+AA18) -> 95 | AC18: =ROUND(Z18+AA18-AB18,2) -> 602.4 | AD18: =IF(Crédits!$K$8="",0,MAX(0,MIN(AC18,Plan!$L$20-(IF(Crédits!$K$5="",0,IF(Crédits!$K$5<Crédits!$K$8,E18,0))+IF(Crédits!$K$6="",0,IF(Crédits!$K$6<Crédits!$K$8,M18,0))+IF(Crédits!$K$7="",0,IF(Crédits!$K$7<Crédits!$K$8,U18,0))+IF(Crédits!$K$9="",0,IF(Crédits!$K$9<Crédits!$K$8,AK18,0))+IF(Crédits!$K$10="",0,IF(Crédits!$K$10<Crédits!$K$8,AS18,0)))))) -> 0 | AE18: =ROUND(AC18-AD18,2) -> 602.4 | AF18: =ROUND(AF17+AG18-MIN(N(Crédits!$E$8),AF17+AG18),2) -> 602.4 | AG18: =AF17*N(Crédits!$D$8)/12 -> 0.6967 | AH18: =AM17 -> 0 | AI18: =AH18*N(Crédits!$D$9)/12 -> 0 | AJ18: =MIN(N(Crédits!$E$9),AH18+AI18) -> 0 | AK18: =ROUND(AH18+AI18-AJ18,2) -> 0 | AL18: =IF(Crédits!$K$9="",0,MAX(0,MIN(AK18,Plan!$L$20-(IF(Crédits!$K$5="",0,IF(Crédits!$K$5<Crédits!$K$9,E18,0))+IF(Crédits!$K$6="",0,IF(Crédits!$K$6<Crédits!$K$9,M18,0))+IF(Crédits!$K$7="",0,IF(Crédits!$K$7<Crédits!$K$9,U18,0))+IF(Crédits!$K$8="",0,IF(Crédits!$K$8<Crédits!$K$9,AC18,0))+IF(Crédits!$K$10="",0,IF(Crédits!$K$10<Crédits!$K$9,AS18,0)))))) -> 0 | AM18: =ROUND(AK18-AL18,2) -> 0 | AN18: =ROUND(AN17+AO18-MIN(N(Crédits!$E$9),AN17+AO18),2) -> 0 | AO18: =AN17*N(Crédits!$D$9)/12 -> 0 | AP18: =AU17 -> 0 | AQ18: =AP18*N(Crédits!$D$10)/12 -> 0 | AR18: =MIN(N(Crédits!$E$10),AP18+AQ18) -> 0 | AS18: =ROUND(AP18+AQ18-AR18,2) -> 0 | AT18: =IF(Crédits!$K$10="",0,MAX(0,MIN(AS18,Plan!$L$20-(IF(Crédits!$K$5="",0,IF(Crédits!$K$5<Crédits!$K$10,E18,0))+IF(Crédits!$K$6="",0,IF(Crédits!$K$6<Crédits!$K$10,M18,0))+IF(Crédits!$K$7="",0,IF(Crédits!$K$7<Crédits!$K$10,U18,0))+IF(Crédits!$K$8="",0,IF(Crédits!$K$8<Crédits!$K$10,AC18,0))+IF(Crédits!$K$9="",0,IF(Crédits!$K$9<Crédits!$K$10,AK18,0)))))) -> 0 | AU18: =ROUND(AS18-AT18,2) -> 0 | AV18: =ROUND(AV17+AW18-MIN(N(Crédits!$E$10),AV17+AW18),2) -> 0 | AW18: =AV17*N(Crédits!$D$10)/12 -> 0 | AX18: =D18+L18+T18+AB18+AJ18+AR18 -> 459.05 | AY18: =F18+N18+V18+AD18+AL18+AT18 -> 429.57 | AZ18: =G18+O18+W18+AE18+AM18+AU18 -> 6151.39 | BA18: =C18+K18+S18+AA18+AI18+AQ18 -> 27.927304 | BB18: =I18+Q18+Y18+AG18+AO18+AW18 -> 47.887705
A19: 17 | B19: =G18 -> 4705.12 | C19: =B19*N(Crédits!$D$5)/12 -> 19.212573 | D19: =MIN(N(Crédits!$E$5),B19+C19) -> 245.3 | E19: =ROUND(B19+C19-D19,2) -> 4479.03 | F19: =IF(Crédits!$K$5="",0,MAX(0,MIN(E19,Plan!$L$21-(IF(Crédits!$K$6="",0,IF(Crédits!$K$6<Crédits!$K$5,M19,0))+IF(Crédits!$K$7="",0,IF(Crédits!$K$7<Crédits!$K$5,U19,0))+IF(Crédits!$K$8="",0,IF(Crédits!$K$8<Crédits!$K$5,AC19,0))+IF(Crédits!$K$9="",0,IF(Crédits!$K$9<Crédits!$K$5,AK19,0))+IF(Crédits!$K$10="",0,IF(Crédits!$K$10<Crédits!$K$5,AS19,0)))))) -> 0 | G19: =ROUND(E19-F19,2) -> 4479.03 | H19: =ROUND(H18+I19-MIN(N(Crédits!$E$5),H18+I19),2) -> 4479.03 | I19: =H18*N(Crédits!$D$5)/12 -> 19.212573 | J19: =O18 -> 0 | K19: =J19*N(Crédits!$D$6)/12 -> 0 | L19: =MIN(N(Crédits!$E$6),J19+K19) -> 0 | M19: =ROUND(J19+K19-L19,2) -> 0 | N19: =IF(Crédits!$K$6="",0,MAX(0,MIN(M19,Plan!$L$21-(IF(Crédits!$K$5="",0,IF(Crédits!$K$5<Crédits!$K$6,E19,0))+IF(Crédits!$K$7="",0,IF(Crédits!$K$7<Crédits!$K$6,U19,0))+IF(Crédits!$K$8="",0,IF(Crédits!$K$8<Crédits!$K$6,AC19,0))+IF(Crédits!$K$9="",0,IF(Crédits!$K$9<Crédits!$K$6,AK19,0))+IF(Crédits!$K$10="",0,IF(Crédits!$K$10<Crédits!$K$6,AS19,0)))))) -> 0 | O19: =ROUND(M19-N19,2) -> 0 | P19: =ROUND(P18+Q19-MIN(N(Crédits!$E$6),P18+Q19),2) -> 1014.15 | Q19: =P18*N(Crédits!$D$6)/12 -> 16.847775 | R19: =W18 -> 843.87 | S19: =R19*N(Crédits!$D$7)/12 -> 4.3248337 | T19: =MIN(N(Crédits!$E$7),R19+S19) -> 118.75 | U19: =ROUND(R19+S19-T19,2) -> 729.44 | V19: =IF(Crédits!$K$7="",0,MAX(0,MIN(U19,Plan!$L$21-(IF(Crédits!$K$5="",0,IF(Crédits!$K$5<Crédits!$K$7,E19,0))+IF(Crédits!$K$6="",0,IF(Crédits!$K$6<Crédits!$K$7,M19,0))+IF(Crédits!$K$8="",0,IF(Crédits!$K$8<Crédits!$K$7,AC19,0))+IF(Crédits!$K$9="",0,IF(Crédits!$K$9<Crédits!$K$7,AK19,0))+IF(Crédits!$K$10="",0,IF(Crédits!$K$10<Crédits!$K$7,AS19,0)))))) -> 429.57 | W19: =ROUND(U19-V19,2) -> 299.87 | X19: =ROUND(X18+Y19-MIN(N(Crédits!$E$7),X18+Y19),2) -> 1605 | Y19: =X18*N(Crédits!$D$7)/12 -> 8.78917 | Z19: =AE18 -> 602.4 | AA19: =Z19*N(Crédits!$D$8)/12 -> 0.6024 | AB19: =MIN(N(Crédits!$E$8),Z19+AA19) -> 95 | AC19: =ROUND(Z19+AA19-AB19,2) -> 508 | AD19: =IF(Crédits!$K$8="",0,MAX(0,MIN(AC19,Plan!$L$21-(IF(Crédits!$K$5="",0,IF(Crédits!$K$5<Crédits!$K$8,E19,0))+IF(Crédits!$K$6="",0,IF(Crédits!$K$6<Crédits!$K$8,M19,0))+IF(Crédits!$K$7="",0,IF(Crédits!$K$7<Crédits!$K$8,U19,0))+IF(Crédits!$K$9="",0,IF(Crédits!$K$9<Crédits!$K$8,AK19,0))+IF(Crédits!$K$10="",0,IF(Crédits!$K$10<Crédits!$K$8,AS19,0)))))) -> 0 | AE19: =ROUND(AC19-AD19,2) -> 508 | AF19: =ROUND(AF18+AG19-MIN(N(Crédits!$E$8),AF18+AG19),2) -> 508 | AG19: =AF18*N(Crédits!$D$8)/12 -> 0.6024 | AH19: =AM18 -> 0 | AI19: =AH19*N(Crédits!$D$9)/12 -> 0 | AJ19: =MIN(N(Crédits!$E$9),AH19+AI19) -> 0 | AK19: =ROUND(AH19+AI19-AJ19,2) -> 0 | AL19: =IF(Crédits!$K$9="",0,MAX(0,MIN(AK19,Plan!$L$21-(IF(Crédits!$K$5="",0,IF(Crédits!$K$5<Crédits!$K$9,E19,0))+IF(Crédits!$K$6="",0,IF(Crédits!$K$6<Crédits!$K$9,M19,0))+IF(Crédits!$K$7="",0,IF(Crédits!$K$7<Crédits!$K$9,U19,0))+IF(Crédits!$K$8="",0,IF(Crédits!$K$8<Crédits!$K$9,AC19,0))+IF(Crédits!$K$10="",0,IF(Crédits!$K$10<Crédits!$K$9,AS19,0)))))) -> 0 | AM19: =ROUND(AK19-AL19,2) -> 0 | AN19: =ROUND(AN18+AO19-MIN(N(Crédits!$E$9),AN18+AO19),2) -> 0 | AO19: =AN18*N(Crédits!$D$9)/12 -> 0 | AP19: =AU18 -> 0 | AQ19: =AP19*N(Crédits!$D$10)/12 -> 0 | AR19: =MIN(N(Crédits!$E$10),AP19+AQ19) -> 0 | AS19: =ROUND(AP19+AQ19-AR19,2) -> 0 | AT19: =IF(Crédits!$K$10="",0,MAX(0,MIN(AS19,Plan!$L$21-(IF(Crédits!$K$5="",0,IF(Crédits!$K$5<Crédits!$K$10,E19,0))+IF(Crédits!$K$6="",0,IF(Crédits!$K$6<Crédits!$K$10,M19,0))+IF(Crédits!$K$7="",0,IF(Crédits!$K$7<Crédits!$K$10,U19,0))+IF(Crédits!$K$8="",0,IF(Crédits!$K$8<Crédits!$K$10,AC19,0))+IF(Crédits!$K$9="",0,IF(Crédits!$K$9<Crédits!$K$10,AK19,0)))))) -> 0 | AU19: =ROUND(AS19-AT19,2) -> 0 | AV19: =ROUND(AV18+AW19-MIN(N(Crédits!$E$10),AV18+AW19),2) -> 0 | AW19: =AV18*N(Crédits!$D$10)/12 -> 0 | AX19: =D19+L19+T19+AB19+AJ19+AR19 -> 459.05 | AY19: =F19+N19+V19+AD19+AL19+AT19 -> 429.57 | AZ19: =G19+O19+W19+AE19+AM19+AU19 -> 5286.9 | BA19: =C19+K19+S19+AA19+AI19+AQ19 -> 24.139807 | BB19: =I19+Q19+Y19+AG19+AO19+AW19 -> 45.451918
A20: 18 | B20: =G19 -> 4479.03 | C20: =B20*N(Crédits!$D$5)/12 -> 18.289372 | D20: =MIN(N(Crédits!$E$5),B20+C20) -> 245.3 | E20: =ROUND(B20+C20-D20,2) -> 4252.02 | F20: =IF(Crédits!$K$5="",0,MAX(0,MIN(E20,Plan!$L$22-(IF(Crédits!$K$6="",0,IF(Crédits!$K$6<Crédits!$K$5,M20,0))+IF(Crédits!$K$7="",0,IF(Crédits!$K$7<Crédits!$K$5,U20,0))+IF(Crédits!$K$8="",0,IF(Crédits!$K$8<Crédits!$K$5,AC20,0))+IF(Crédits!$K$9="",0,IF(Crédits!$K$9<Crédits!$K$5,AK20,0))+IF(Crédits!$K$10="",0,IF(Crédits!$K$10<Crédits!$K$5,AS20,0)))))) -> 246.91 | G20: =ROUND(E20-F20,2) -> 4005.11 | H20: =ROUND(H19+I20-MIN(N(Crédits!$E$5),H19+I20),2) -> 4252.02 | I20: =H19*N(Crédits!$D$5)/12 -> 18.289372 | J20: =O19 -> 0 | K20: =J20*N(Crédits!$D$6)/12 -> 0 | L20: =MIN(N(Crédits!$E$6),J20+K20) -> 0 | M20: =ROUND(J20+K20-L20,2) -> 0 | N20: =IF(Crédits!$K$6="",0,MAX(0,MIN(M20,Plan!$L$22-(IF(Crédits!$K$5="",0,IF(Crédits!$K$5<Crédits!$K$6,E20,0))+IF(Crédits!$K$7="",0,IF(Crédits!$K$7<Crédits!$K$6,U20,0))+IF(Crédits!$K$8="",0,IF(Crédits!$K$8<Crédits!$K$6,AC20,0))+IF(Crédits!$K$9="",0,IF(Crédits!$K$9<Crédits!$K$6,AK20,0))+IF(Crédits!$K$10="",0,IF(Crédits!$K$10<Crédits!$K$6,AS20,0)))))) -> 0 | O20: =ROUND(M20-N20,2) -> 0 | P20: =ROUND(P19+Q20-MIN(N(Crédits!$E$6),P19+Q20),2) -> 957.72 | Q20: =P19*N(Crédits!$D$6)/12 -> 15.972862 | R20: =W19 -> 299.87 | S20: =R20*N(Crédits!$D$7)/12 -> 1.5368338 | T20: =MIN(N(Crédits!$E$7),R20+S20) -> 118.75 | U20: =ROUND(R20+S20-T20,2) -> 182.66 | V20: =IF(Crédits!$K$7="",0,MAX(0,MIN(U20,Plan!$L$22-(IF(Crédits!$K$5="",0,IF(Crédits!$K$5<Crédits!$K$7,E20,0))+IF(Crédits!$K$6="",0,IF(Crédits!$K$6<Crédits!$K$7,M20,0))+IF(Crédits!$K$8="",0,IF(Crédits!$K$8<Crédits!$K$7,AC20,0))+IF(Crédits!$K$9="",0,IF(Crédits!$K$9<Crédits!$K$7,AK20,0))+IF(Crédits!$K$10="",0,IF(Crédits!$K$10<Crédits!$K$7,AS20,0)))))) -> 182.66 | W20: =ROUND(U20-V20,2) -> 0 | X20: =ROUND(X19+Y20-MIN(N(Crédits!$E$7),X19+Y20),2) -> 1494.48 | Y20: =X19*N(Crédits!$D$7)/12 -> 8.225625 | Z20: =AE19 -> 508 | AA20: =Z20*N(Crédits!$D$8)/12 -> 0.508 | AB20: =MIN(N(Crédits!$E$8),Z20+AA20) -> 95 | AC20: =ROUND(Z20+AA20-AB20,2) -> 413.51 | AD20: =IF(Crédits!$K$8="",0,MAX(0,MIN(AC20,Plan!$L$22-(IF(Crédits!$K$5="",0,IF(Crédits!$K$5<Crédits!$K$8,E20,0))+IF(Crédits!$K$6="",0,IF(Crédits!$K$6<Crédits!$K$8,M20,0))+IF(Crédits!$K$7="",0,IF(Crédits!$K$7<Crédits!$K$8,U20,0))+IF(Crédits!$K$9="",0,IF(Crédits!$K$9<Crédits!$K$8,AK20,0))+IF(Crédits!$K$10="",0,IF(Crédits!$K$10<Crédits!$K$8,AS20,0)))))) -> 0 | AE20: =ROUND(AC20-AD20,2) -> 413.51 | AF20: =ROUND(AF19+AG20-MIN(N(Crédits!$E$8),AF19+AG20),2) -> 413.51 | AG20: =AF19*N(Crédits!$D$8)/12 -> 0.508 | AH20: =AM19 -> 0 | AI20: =AH20*N(Crédits!$D$9)/12 -> 0 | AJ20: =MIN(N(Crédits!$E$9),AH20+AI20) -> 0 | AK20: =ROUND(AH20+AI20-AJ20,2) -> 0 | AL20: =IF(Crédits!$K$9="",0,MAX(0,MIN(AK20,Plan!$L$22-(IF(Crédits!$K$5="",0,IF(Crédits!$K$5<Crédits!$K$9,E20,0))+IF(Crédits!$K$6="",0,IF(Crédits!$K$6<Crédits!$K$9,M20,0))+IF(Crédits!$K$7="",0,IF(Crédits!$K$7<Crédits!$K$9,U20,0))+IF(Crédits!$K$8="",0,IF(Crédits!$K$8<Crédits!$K$9,AC20,0))+IF(Crédits!$K$10="",0,IF(Crédits!$K$10<Crédits!$K$9,AS20,0)))))) -> 0 | AM20: =ROUND(AK20-AL20,2) -> 0 | AN20: =ROUND(AN19+AO20-MIN(N(Crédits!$E$9),AN19+AO20),2) -> 0 | AO20: =AN19*N(Crédits!$D$9)/12 -> 0 | AP20: =AU19 -> 0 | AQ20: =AP20*N(Crédits!$D$10)/12 -> 0 | AR20: =MIN(N(Crédits!$E$10),AP20+AQ20) -> 0 | AS20: =ROUND(AP20+AQ20-AR20,2) -> 0 | AT20: =IF(Crédits!$K$10="",0,MAX(0,MIN(AS20,Plan!$L$22-(IF(Crédits!$K$5="",0,IF(Crédits!$K$5<Crédits!$K$10,E20,0))+IF(Crédits!$K$6="",0,IF(Crédits!$K$6<Crédits!$K$10,M20,0))+IF(Crédits!$K$7="",0,IF(Crédits!$K$7<Crédits!$K$10,U20,0))+IF(Crédits!$K$8="",0,IF(Crédits!$K$8<Crédits!$K$10,AC20,0))+IF(Crédits!$K$9="",0,IF(Crédits!$K$9<Crédits!$K$10,AK20,0)))))) -> 0 | AU20: =ROUND(AS20-AT20,2) -> 0 | AV20: =ROUND(AV19+AW20-MIN(N(Crédits!$E$10),AV19+AW20),2) -> 0 | AW20: =AV19*N(Crédits!$D$10)/12 -> 0 | AX20: =D20+L20+T20+AB20+AJ20+AR20 -> 459.05 | AY20: =F20+N20+V20+AD20+AL20+AT20 -> 429.57 | AZ20: =G20+O20+W20+AE20+AM20+AU20 -> 4418.62 | BA20: =C20+K20+S20+AA20+AI20+AQ20 -> 20.334206 | BB20: =I20+Q20+Y20+AG20+AO20+AW20 -> 42.99586
A21: 19 | B21: =G20 -> 4005.11 | C21: =B21*N(Crédits!$D$5)/12 -> 16.354199 | D21: =MIN(N(Crédits!$E$5),B21+C21) -> 245.3 | E21: =ROUND(B21+C21-D21,2) -> 3776.16 | F21: =IF(Crédits!$K$5="",0,MAX(0,MIN(E21,Plan!$L$23-(IF(Crédits!$K$6="",0,IF(Crédits!$K$6<Crédits!$K$5,M21,0))+IF(Crédits!$K$7="",0,IF(Crédits!$K$7<Crédits!$K$5,U21,0))+IF(Crédits!$K$8="",0,IF(Crédits!$K$8<Crédits!$K$5,AC21,0))+IF(Crédits!$K$9="",0,IF(Crédits!$K$9<Crédits!$K$5,AK21,0))+IF(Crédits!$K$10="",0,IF(Crédits!$K$10<Crédits!$K$5,AS21,0)))))) -> 500.82 | G21: =ROUND(E21-F21,2) -> 3275.34 | H21: =ROUND(H20+I21-MIN(N(Crédits!$E$5),H20+I21),2) -> 4024.08 | I21: =H20*N(Crédits!$D$5)/12 -> 17.362415 | J21: =O20 -> 0 | K21: =J21*N(Crédits!$D$6)/12 -> 0 | L21: =MIN(N(Crédits!$E$6),J21+K21) -> 0 | M21: =ROUND(J21+K21-L21,2) -> 0 | N21: =IF(Crédits!$K$6="",0,MAX(0,MIN(M21,Plan!$L$23-(IF(Crédits!$K$5="",0,IF(Crédits!$K$5<Crédits!$K$6,E21,0))+IF(Crédits!$K$7="",0,IF(Crédits!$K$7<Crédits!$K$6,U21,0))+IF(Crédits!$K$8="",0,IF(Crédits!$K$8<Crédits!$K$6,AC21,0))+IF(Crédits!$K$9="",0,IF(Crédits!$K$9<Crédits!$K$6,AK21,0))+IF(Crédits!$K$10="",0,IF(Crédits!$K$10<Crédits!$K$6,AS21,0)))))) -> 0 | O21: =ROUND(M21-N21,2) -> 0 | P21: =ROUND(P20+Q21-MIN(N(Crédits!$E$6),P20+Q21),2) -> 900.4 | Q21: =P20*N(Crédits!$D$6)/12 -> 15.08409 | R21: =W20 -> 0 | S21: =R21*N(Crédits!$D$7)/12 -> 0 | T21: =MIN(N(Crédits!$E$7),R21+S21) -> 0 | U21: =ROUND(R21+S21-T21,2) -> 0 | V21: =IF(Crédits!$K$7="",0,MAX(0,MIN(U21,Plan!$L$23-(IF(Crédits!$K$5="",0,IF(Crédits!$K$5<Crédits!$K$7,E21,0))+IF(Crédits!$K$6="",0,IF(Crédits!$K$6<Crédits!$K$7,M21,0))+IF(Crédits!$K$8="",0,IF(Crédits!$K$8<Crédits!$K$7,AC21,0))+IF(Crédits!$K$9="",0,IF(Crédits!$K$9<Crédits!$K$7,AK21,0))+IF(Crédits!$K$10="",0,IF(Crédits!$K$10<Crédits!$K$7,AS21,0)))))) -> 0 | W21: =ROUND(U21-V21,2) -> 0 | X21: =ROUND(X20+Y21-MIN(N(Crédits!$E$7),X20+Y21),2) -> 1383.39 | Y21: =X20*N(Crédits!$D$7)/12 -> 7.65921 | Z21: =AE20 -> 413.51 | AA21: =Z21*N(Crédits!$D$8)/12 -> 0.41351 | AB21: =MIN(N(Crédits!$E$8),Z21+AA21) -> 95 | AC21: =ROUND(Z21+AA21-AB21,2) -> 318.92 | AD21: =IF(Crédits!$K$8="",0,MAX(0,MIN(AC21,Plan!$L$23-(IF(Crédits!$K$5="",0,IF(Crédits!$K$5<Crédits!$K$8,E21,0))+IF(Crédits!$K$6="",0,IF(Crédits!$K$6<Crédits!$K$8,M21,0))+IF(Crédits!$K$7="",0,IF(Crédits!$K$7<Crédits!$K$8,U21,0))+IF(Crédits!$K$9="",0,IF(Crédits!$K$9<Crédits!$K$8,AK21,0))+IF(Crédits!$K$10="",0,IF(Crédits!$K$10<Crédits!$K$8,AS21,0)))))) -> 0 | AE21: =ROUND(AC21-AD21,2) -> 318.92 | AF21: =ROUND(AF20+AG21-MIN(N(Crédits!$E$8),AF20+AG21),2) -> 318.92 | AG21: =AF20*N(Crédits!$D$8)/12 -> 0.41351 | AH21: =AM20 -> 0 | AI21: =AH21*N(Crédits!$D$9)/12 -> 0 | AJ21: =MIN(N(Crédits!$E$9),AH21+AI21) -> 0 | AK21: =ROUND(AH21+AI21-AJ21,2) -> 0 | AL21: =IF(Crédits!$K$9="",0,MAX(0,MIN(AK21,Plan!$L$23-(IF(Crédits!$K$5="",0,IF(Crédits!$K$5<Crédits!$K$9,E21,0))+IF(Crédits!$K$6="",0,IF(Crédits!$K$6<Crédits!$K$9,M21,0))+IF(Crédits!$K$7="",0,IF(Crédits!$K$7<Crédits!$K$9,U21,0))+IF(Crédits!$K$8="",0,IF(Crédits!$K$8<Crédits!$K$9,AC21,0))+IF(Crédits!$K$10="",0,IF(Crédits!$K$10<Crédits!$K$9,AS21,0)))))) -> 0 | AM21: =ROUND(AK21-AL21,2) -> 0 | AN21: =ROUND(AN20+AO21-MIN(N(Crédits!$E$9),AN20+AO21),2) -> 0 | AO21: =AN20*N(Crédits!$D$9)/12 -> 0 | AP21: =AU20 -> 0 | AQ21: =AP21*N(Crédits!$D$10)/12 -> 0 | AR21: =MIN(N(Crédits!$E$10),AP21+AQ21) -> 0 | AS21: =ROUND(AP21+AQ21-AR21,2) -> 0 | AT21: =IF(Crédits!$K$10="",0,MAX(0,MIN(AS21,Plan!$L$23-(IF(Crédits!$K$5="",0,IF(Crédits!$K$5<Crédits!$K$10,E21,0))+IF(Crédits!$K$6="",0,IF(Crédits!$K$6<Crédits!$K$10,M21,0))+IF(Crédits!$K$7="",0,IF(Crédits!$K$7<Crédits!$K$10,U21,0))+IF(Crédits!$K$8="",0,IF(Crédits!$K$8<Crédits!$K$10,AC21,0))+IF(Crédits!$K$9="",0,IF(Crédits!$K$9<Crédits!$K$10,AK21,0)))))) -> 0 | AU21: =ROUND(AS21-AT21,2) -> 0 | AV21: =ROUND(AV20+AW21-MIN(N(Crédits!$E$10),AV20+AW21),2) -> 0 | AW21: =AV20*N(Crédits!$D$10)/12 -> 0 | AX21: =D21+L21+T21+AB21+AJ21+AR21 -> 340.3 | AY21: =F21+N21+V21+AD21+AL21+AT21 -> 500.82 | AZ21: =G21+O21+W21+AE21+AM21+AU21 -> 3594.26 | BA21: =C21+K21+S21+AA21+AI21+AQ21 -> 16.767709 | BB21: =I21+Q21+Y21+AG21+AO21+AW21 -> 40.519225
A22: 20 | B22: =G21 -> 3275.34 | C22: =B22*N(Crédits!$D$5)/12 -> 13.374305 | D22: =MIN(N(Crédits!$E$5),B22+C22) -> 245.3 | E22: =ROUND(B22+C22-D22,2) -> 3043.41 | F22: =IF(Crédits!$K$5="",0,MAX(0,MIN(E22,Plan!$L$24-(IF(Crédits!$K$6="",0,IF(Crédits!$K$6<Crédits!$K$5,M22,0))+IF(Crédits!$K$7="",0,IF(Crédits!$K$7<Crédits!$K$5,U22,0))+IF(Crédits!$K$8="",0,IF(Crédits!$K$8<Crédits!$K$5,AC22,0))+IF(Crédits!$K$9="",0,IF(Crédits!$K$9<Crédits!$K$5,AK22,0))+IF(Crédits!$K$10="",0,IF(Crédits!$K$10<Crédits!$K$5,AS22,0)))))) -> 500.82 | G22: =ROUND(E22-F22,2) -> 2542.59 | H22: =ROUND(H21+I22-MIN(N(Crédits!$E$5),H21+I22),2) -> 3795.21 | I22: =H21*N(Crédits!$D$5)/12 -> 16.43166 | J22: =O21 -> 0 | K22: =J22*N(Crédits!$D$6)/12 -> 0 | L22: =MIN(N(Crédits!$E$6),J22+K22) -> 0 | M22: =ROUND(J22+K22-L22,2) -> 0 | N22: =IF(Crédits!$K$6="",0,MAX(0,MIN(M22,Plan!$L$24-(IF(Crédits!$K$5="",0,IF(Crédits!$K$5<Crédits!$K$6,E22,0))+IF(Crédits!$K$7="",0,IF(Crédits!$K$7<Crédits!$K$6,U22,0))+IF(Crédits!$K$8="",0,IF(Crédits!$K$8<Crédits!$K$6,AC22,0))+IF(Crédits!$K$9="",0,IF(Crédits!$K$9<Crédits!$K$6,AK22,0))+IF(Crédits!$K$10="",0,IF(Crédits!$K$10<Crédits!$K$6,AS22,0)))))) -> 0 | O22: =ROUND(M22-N22,2) -> 0 | P22: =ROUND(P21+Q22-MIN(N(Crédits!$E$6),P21+Q22),2) -> 842.18 | Q22: =P21*N(Crédits!$D$6)/12 -> 14.1813 | R22: =W21 -> 0 | S22: =R22*N(Crédits!$D$7)/12 -> 0 | T22: =MIN(N(Crédits!$E$7),R22+S22) -> 0 | U22: =ROUND(R22+S22-T22,2) -> 0 | V22: =IF(Crédits!$K$7="",0,MAX(0,MIN(U22,Plan!$L$24-(IF(Crédits!$K$5="",0,IF(Crédits!$K$5<Crédits!$K$7,E22,0))+IF(Crédits!$K$6="",0,IF(Crédits!$K$6<Crédits!$K$7,M22,0))+IF(Crédits!$K$8="",0,IF(Crédits!$K$8<Crédits!$K$7,AC22,0))+IF(Crédits!$K$9="",0,IF(Crédits!$K$9<Crédits!$K$7,AK22,0))+IF(Crédits!$K$10="",0,IF(Crédits!$K$10<Crédits!$K$7,AS22,0)))))) -> 0 | W22: =ROUND(U22-V22,2) -> 0 | X22: =ROUND(X21+Y22-MIN(N(Crédits!$E$7),X21+Y22),2) -> 1271.73 | Y22: =X21*N(Crédits!$D$7)/12 -> 7.0898737 | Z22: =AE21 -> 318.92 | AA22: =Z22*N(Crédits!$D$8)/12 -> 0.31892 | AB22: =MIN(N(Crédits!$E$8),Z22+AA22) -> 95 | AC22: =ROUND(Z22+AA22-AB22,2) -> 224.24 | AD22: =IF(Crédits!$K$8="",0,MAX(0,MIN(AC22,Plan!$L$24-(IF(Crédits!$K$5="",0,IF(Crédits!$K$5<Crédits!$K$8,E22,0))+IF(Crédits!$K$6="",0,IF(Crédits!$K$6<Crédits!$K$8,M22,0))+IF(Crédits!$K$7="",0,IF(Crédits!$K$7<Crédits!$K$8,U22,0))+IF(Crédits!$K$9="",0,IF(Crédits!$K$9<Crédits!$K$8,AK22,0))+IF(Crédits!$K$10="",0,IF(Crédits!$K$10<Crédits!$K$8,AS22,0)))))) -> 0 | AE22: =ROUND(AC22-AD22,2) -> 224.24 | AF22: =ROUND(AF21+AG22-MIN(N(Crédits!$E$8),AF21+AG22),2) -> 224.24 | AG22: =AF21*N(Crédits!$D$8)/12 -> 0.31892 | AH22: =AM21 -> 0 | AI22: =AH22*N(Crédits!$D$9)/12 -> 0 | AJ22: =MIN(N(Crédits!$E$9),AH22+AI22) -> 0 | AK22: =ROUND(AH22+AI22-AJ22,2) -> 0 | AL22: =IF(Crédits!$K$9="",0,MAX(0,MIN(AK22,Plan!$L$24-(IF(Crédits!$K$5="",0,IF(Crédits!$K$5<Crédits!$K$9,E22,0))+IF(Crédits!$K$6="",0,IF(Crédits!$K$6<Crédits!$K$9,M22,0))+IF(Crédits!$K$7="",0,IF(Crédits!$K$7<Crédits!$K$9,U22,0))+IF(Crédits!$K$8="",0,IF(Crédits!$K$8<Crédits!$K$9,AC22,0))+IF(Crédits!$K$10="",0,IF(Crédits!$K$10<Crédits!$K$9,AS22,0)))))) -> 0 | AM22: =ROUND(AK22-AL22,2) -> 0 | AN22: =ROUND(AN21+AO22-MIN(N(Crédits!$E$9),AN21+AO22),2) -> 0 | AO22: =AN21*N(Crédits!$D$9)/12 -> 0 | AP22: =AU21 -> 0 | AQ22: =AP22*N(Crédits!$D$10)/12 -> 0 | AR22: =MIN(N(Crédits!$E$10),AP22+AQ22) -> 0 | AS22: =ROUND(AP22+AQ22-AR22,2) -> 0 | AT22: =IF(Crédits!$K$10="",0,MAX(0,MIN(AS22,Plan!$L$24-(IF(Crédits!$K$5="",0,IF(Crédits!$K$5<Crédits!$K$10,E22,0))+IF(Crédits!$K$6="",0,IF(Crédits!$K$6<Crédits!$K$10,M22,0))+IF(Crédits!$K$7="",0,IF(Crédits!$K$7<Crédits!$K$10,U22,0))+IF(Crédits!$K$8="",0,IF(Crédits!$K$8<Crédits!$K$10,AC22,0))+IF(Crédits!$K$9="",0,IF(Crédits!$K$9<Crédits!$K$10,AK22,0)))))) -> 0 | AU22: =ROUND(AS22-AT22,2) -> 0 | AV22: =ROUND(AV21+AW22-MIN(N(Crédits!$E$10),AV21+AW22),2) -> 0 | AW22: =AV21*N(Crédits!$D$10)/12 -> 0 | AX22: =D22+L22+T22+AB22+AJ22+AR22 -> 340.3 | AY22: =F22+N22+V22+AD22+AL22+AT22 -> 500.82 | AZ22: =G22+O22+W22+AE22+AM22+AU22 -> 2766.83 | BA22: =C22+K22+S22+AA22+AI22+AQ22 -> 13.693225 | BB22: =I22+Q22+Y22+AG22+AO22+AW22 -> 38.021754
A23: 21 | B23: =G22 -> 2542.59 | C23: =B23*N(Crédits!$D$5)/12 -> 10.382243 | D23: =MIN(N(Crédits!$E$5),B23+C23) -> 245.3 | E23: =ROUND(B23+C23-D23,2) -> 2307.67 | F23: =IF(Crédits!$K$5="",0,MAX(0,MIN(E23,Plan!$L$25-(IF(Crédits!$K$6="",0,IF(Crédits!$K$6<Crédits!$K$5,M23,0))+IF(Crédits!$K$7="",0,IF(Crédits!$K$7<Crédits!$K$5,U23,0))+IF(Crédits!$K$8="",0,IF(Crédits!$K$8<Crédits!$K$5,AC23,0))+IF(Crédits!$K$9="",0,IF(Crédits!$K$9<Crédits!$K$5,AK23,0))+IF(Crédits!$K$10="",0,IF(Crédits!$K$10<Crédits!$K$5,AS23,0)))))) -> 500.82 | G23: =ROUND(E23-F23,2) -> 1806.85 | H23: =ROUND(H22+I23-MIN(N(Crédits!$E$5),H22+I23),2) -> 3565.41 | I23: =H22*N(Crédits!$D$5)/12 -> 15.497108 | J23: =O22 -> 0 | K23: =J23*N(Crédits!$D$6)/12 -> 0 | L23: =MIN(N(Crédits!$E$6),J23+K23) -> 0 | M23: =ROUND(J23+K23-L23,2) -> 0 | N23: =IF(Crédits!$K$6="",0,MAX(0,MIN(M23,Plan!$L$25-(IF(Crédits!$K$5="",0,IF(Crédits!$K$5<Crédits!$K$6,E23,0))+IF(Crédits!$K$7="",0,IF(Crédits!$K$7<Crédits!$K$6,U23,0))+IF(Crédits!$K$8="",0,IF(Crédits!$K$8<Crédits!$K$6,AC23,0))+IF(Crédits!$K$9="",0,IF(Crédits!$K$9<Crédits!$K$6,AK23,0))+IF(Crédits!$K$10="",0,IF(Crédits!$K$10<Crédits!$K$6,AS23,0)))))) -> 0 | O23: =ROUND(M23-N23,2) -> 0 | P23: =ROUND(P22+Q23-MIN(N(Crédits!$E$6),P22+Q23),2) -> 783.04 | Q23: =P22*N(Crédits!$D$6)/12 -> 13.264335 | R23: =W22 -> 0 | S23: =R23*N(Crédits!$D$7)/12 -> 0 | T23: =MIN(N(Crédits!$E$7),R23+S23) -> 0 | U23: =ROUND(R23+S23-T23,2) -> 0 | V23: =IF(Crédits!$K$7="",0,MAX(0,MIN(U23,Plan!$L$25-(IF(Crédits!$K$5="",0,IF(Crédits!$K$5<Crédits!$K$7,E23,0))+IF(Crédits!$K$6="",0,IF(Crédits!$K$6<Crédits!$K$7,M23,0))+IF(Crédits!$K$8="",0,IF(Crédits!$K$8<Crédits!$K$7,AC23,0))+IF(Crédits!$K$9="",0,IF(Crédits!$K$9<Crédits!$K$7,AK23,0))+IF(Crédits!$K$10="",0,IF(Crédits!$K$10<Crédits!$K$7,AS23,0)))))) -> 0 | W23: =ROUND(U23-V23,2) -> 0 | X23: =ROUND(X22+Y23-MIN(N(Crédits!$E$7),X22+Y23),2) -> 1159.5 | Y23: =X22*N(Crédits!$D$7)/12 -> 6.5176162 | Z23: =AE22 -> 224.24 | AA23: =Z23*N(Crédits!$D$8)/12 -> 0.22424 | AB23: =MIN(N(Crédits!$E$8),Z23+AA23) -> 95 | AC23: =ROUND(Z23+AA23-AB23,2) -> 129.46 | AD23: =IF(Crédits!$K$8="",0,MAX(0,MIN(AC23,Plan!$L$25-(IF(Crédits!$K$5="",0,IF(Crédits!$K$5<Crédits!$K$8,E23,0))+IF(Crédits!$K$6="",0,IF(Crédits!$K$6<Crédits!$K$8,M23,0))+IF(Crédits!$K$7="",0,IF(Crédits!$K$7<Crédits!$K$8,U23,0))+IF(Crédits!$K$9="",0,IF(Crédits!$K$9<Crédits!$K$8,AK23,0))+IF(Crédits!$K$10="",0,IF(Crédits!$K$10<Crédits!$K$8,AS23,0)))))) -> 0 | AE23: =ROUND(AC23-AD23,2) -> 129.46 | AF23: =ROUND(AF22+AG23-MIN(N(Crédits!$E$8),AF22+AG23),2) -> 129.46 | AG23: =AF22*N(Crédits!$D$8)/12 -> 0.22424 | AH23: =AM22 -> 0 | AI23: =AH23*N(Crédits!$D$9)/12 -> 0 | AJ23: =MIN(N(Crédits!$E$9),AH23+AI23) -> 0 | AK23: =ROUND(AH23+AI23-AJ23,2) -> 0 | AL23: =IF(Crédits!$K$9="",0,MAX(0,MIN(AK23,Plan!$L$25-(IF(Crédits!$K$5="",0,IF(Crédits!$K$5<Crédits!$K$9,E23,0))+IF(Crédits!$K$6="",0,IF(Crédits!$K$6<Crédits!$K$9,M23,0))+IF(Crédits!$K$7="",0,IF(Crédits!$K$7<Crédits!$K$9,U23,0))+IF(Crédits!$K$8="",0,IF(Crédits!$K$8<Crédits!$K$9,AC23,0))+IF(Crédits!$K$10="",0,IF(Crédits!$K$10<Crédits!$K$9,AS23,0)))))) -> 0 | AM23: =ROUND(AK23-AL23,2) -> 0 | AN23: =ROUND(AN22+AO23-MIN(N(Crédits!$E$9),AN22+AO23),2) -> 0 | AO23: =AN22*N(Crédits!$D$9)/12 -> 0 | AP23: =AU22 -> 0 | AQ23: =AP23*N(Crédits!$D$10)/12 -> 0 | AR23: =MIN(N(Crédits!$E$10),AP23+AQ23) -> 0 | AS23: =ROUND(AP23+AQ23-AR23,2) -> 0 | AT23: =IF(Crédits!$K$10="",0,MAX(0,MIN(AS23,Plan!$L$25-(IF(Crédits!$K$5="",0,IF(Crédits!$K$5<Crédits!$K$10,E23,0))+IF(Crédits!$K$6="",0,IF(Crédits!$K$6<Crédits!$K$10,M23,0))+IF(Crédits!$K$7="",0,IF(Crédits!$K$7<Crédits!$K$10,U23,0))+IF(Crédits!$K$8="",0,IF(Crédits!$K$8<Crédits!$K$10,AC23,0))+IF(Crédits!$K$9="",0,IF(Crédits!$K$9<Crédits!$K$10,AK23,0)))))) -> 0 | AU23: =ROUND(AS23-AT23,2) -> 0 | AV23: =ROUND(AV22+AW23-MIN(N(Crédits!$E$10),AV22+AW23),2) -> 0 | AW23: =AV22*N(Crédits!$D$10)/12 -> 0 | AX23: =D23+L23+T23+AB23+AJ23+AR23 -> 340.3 | AY23: =F23+N23+V23+AD23+AL23+AT23 -> 500.82 | AZ23: =G23+O23+W23+AE23+AM23+AU23 -> 1936.31 | BA23: =C23+K23+S23+AA23+AI23+AQ23 -> 10.606483 | BB23: =I23+Q23+Y23+AG23+AO23+AW23 -> 35.503299
A24: 22 | B24: =G23 -> 1806.85 | C24: =B24*N(Crédits!$D$5)/12 -> 7.3779708 | D24: =MIN(N(Crédits!$E$5),B24+C24) -> 245.3 | E24: =ROUND(B24+C24-D24,2) -> 1568.93 | F24: =IF(Crédits!$K$5="",0,MAX(0,MIN(E24,Plan!$L$26-(IF(Crédits!$K$6="",0,IF(Crédits!$K$6<Crédits!$K$5,M24,0))+IF(Crédits!$K$7="",0,IF(Crédits!$K$7<Crédits!$K$5,U24,0))+IF(Crédits!$K$8="",0,IF(Crédits!$K$8<Crédits!$K$5,AC24,0))+IF(Crédits!$K$9="",0,IF(Crédits!$K$9<Crédits!$K$5,AK24,0))+IF(Crédits!$K$10="",0,IF(Crédits!$K$10<Crédits!$K$5,AS24,0)))))) -> 500.82 | G24: =ROUND(E24-F24,2) -> 1068.11 | H24: =ROUND(H23+I24-MIN(N(Crédits!$E$5),H23+I24),2) -> 3334.67 | I24: =H23*N(Crédits!$D$5)/12 -> 14.558758 | J24: =O23 -> 0 | K24: =J24*N(Crédits!$D$6)/12 -> 0 | L24: =MIN(N(Crédits!$E$6),J24+K24) -> 0 | M24: =ROUND(J24+K24-L24,2) -> 0 | N24: =IF(Crédits!$K$6="",0,MAX(0,MIN(M24,Plan!$L$26-(IF(Crédits!$K$5="",0,IF(Crédits!$K$5<Crédits!$K$6,E24,0))+IF(Crédits!$K$7="",0,IF(Crédits!$K$7<Crédits!$K$6,U24,0))+IF(Crédits!$K$8="",0,IF(Crédits!$K$8<Crédits!$K$6,AC24,0))+IF(Crédits!$K$9="",0,IF(Crédits!$K$9<Crédits!$K$6,AK24,0))+IF(Crédits!$K$10="",0,IF(Crédits!$K$10<Crédits!$K$6,AS24,0)))))) -> 0 | O24: =ROUND(M24-N24,2) -> 0 | P24: =ROUND(P23+Q24-MIN(N(Crédits!$E$6),P23+Q24),2) -> 722.97 | Q24: =P23*N(Crédits!$D$6)/12 -> 12.33288 | R24: =W23 -> 0 | S24: =R24*N(Crédits!$D$7)/12 -> 0 | T24: =MIN(N(Crédits!$E$7),R24+S24) -> 0 | U24: =ROUND(R24+S24-T24,2) -> 0 | V24: =IF(Crédits!$K$7="",0,MAX(0,MIN(U24,Plan!$L$26-(IF(Crédits!$K$5="",0,IF(Crédits!$K$5<Crédits!$K$7,E24,0))+IF(Crédits!$K$6="",0,IF(Crédits!$K$6<Crédits!$K$7,M24,0))+IF(Crédits!$K$8="",0,IF(Crédits!$K$8<Crédits!$K$7,AC24,0))+IF(Crédits!$K$9="",0,IF(Crédits!$K$9<Crédits!$K$7,AK24,0))+IF(Crédits!$K$10="",0,IF(Crédits!$K$10<Crédits!$K$7,AS24,0)))))) -> 0 | W24: =ROUND(U24-V24,2) -> 0 | X24: =ROUND(X23+Y24-MIN(N(Crédits!$E$7),X23+Y24),2) -> 1046.69 | Y24: =X23*N(Crédits!$D$7)/12 -> 5.9424375 | Z24: =AE23 -> 129.46 | AA24: =Z24*N(Crédits!$D$8)/12 -> 0.12946 | AB24: =MIN(N(Crédits!$E$8),Z24+AA24) -> 95 | AC24: =ROUND(Z24+AA24-AB24,2) -> 34.59 | AD24: =IF(Crédits!$K$8="",0,MAX(0,MIN(AC24,Plan!$L$26-(IF(Crédits!$K$5="",0,IF(Crédits!$K$5<Crédits!$K$8,E24,0))+IF(Crédits!$K$6="",0,IF(Crédits!$K$6<Crédits!$K$8,M24,0))+IF(Crédits!$K$7="",0,IF(Crédits!$K$7<Crédits!$K$8,U24,0))+IF(Crédits!$K$9="",0,IF(Crédits!$K$9<Crédits!$K$8,AK24,0))+IF(Crédits!$K$10="",0,IF(Crédits!$K$10<Crédits!$K$8,AS24,0)))))) -> 0 | AE24: =ROUND(AC24-AD24,2) -> 34.59 | AF24: =ROUND(AF23+AG24-MIN(N(Crédits!$E$8),AF23+AG24),2) -> 34.59 | AG24: =AF23*N(Crédits!$D$8)/12 -> 0.12946 | AH24: =AM23 -> 0 | AI24: =AH24*N(Crédits!$D$9)/12 -> 0 | AJ24: =MIN(N(Crédits!$E$9),AH24+AI24) -> 0 | AK24: =ROUND(AH24+AI24-AJ24,2) -> 0 | AL24: =IF(Crédits!$K$9="",0,MAX(0,MIN(AK24,Plan!$L$26-(IF(Crédits!$K$5="",0,IF(Crédits!$K$5<Crédits!$K$9,E24,0))+IF(Crédits!$K$6="",0,IF(Crédits!$K$6<Crédits!$K$9,M24,0))+IF(Crédits!$K$7="",0,IF(Crédits!$K$7<Crédits!$K$9,U24,0))+IF(Crédits!$K$8="",0,IF(Crédits!$K$8<Crédits!$K$9,AC24,0))+IF(Crédits!$K$10="",0,IF(Crédits!$K$10<Crédits!$K$9,AS24,0)))))) -> 0 | AM24: =ROUND(AK24-AL24,2) -> 0 | AN24: =ROUND(AN23+AO24-MIN(N(Crédits!$E$9),AN23+AO24),2) -> 0 | AO24: =AN23*N(Crédits!$D$9)/12 -> 0 | AP24: =AU23 -> 0 | AQ24: =AP24*N(Crédits!$D$10)/12 -> 0 | AR24: =MIN(N(Crédits!$E$10),AP24+AQ24) -> 0 | AS24: =ROUND(AP24+AQ24-AR24,2) -> 0 | AT24: =IF(Crédits!$K$10="",0,MAX(0,MIN(AS24,Plan!$L$26-(IF(Crédits!$K$5="",0,IF(Crédits!$K$5<Crédits!$K$10,E24,0))+IF(Crédits!$K$6="",0,IF(Crédits!$K$6<Crédits!$K$10,M24,0))+IF(Crédits!$K$7="",0,IF(Crédits!$K$7<Crédits!$K$10,U24,0))+IF(Crédits!$K$8="",0,IF(Crédits!$K$8<Crédits!$K$10,AC24,0))+IF(Crédits!$K$9="",0,IF(Crédits!$K$9<Crédits!$K$10,AK24,0)))))) -> 0 | AU24: =ROUND(AS24-AT24,2) -> 0 | AV24: =ROUND(AV23+AW24-MIN(N(Crédits!$E$10),AV23+AW24),2) -> 0 | AW24: =AV23*N(Crédits!$D$10)/12 -> 0 | AX24: =D24+L24+T24+AB24+AJ24+AR24 -> 340.3 | AY24: =F24+N24+V24+AD24+AL24+AT24 -> 500.82 | AZ24: =G24+O24+W24+AE24+AM24+AU24 -> 1102.7 | BA24: =C24+K24+S24+AA24+AI24+AQ24 -> 7.5074308 | BB24: =I24+Q24+Y24+AG24+AO24+AW24 -> 32.963535
A25: 23 | B25: =G24 -> 1068.11 | C25: =B25*N(Crédits!$D$5)/12 -> 4.3614492 | D25: =MIN(N(Crédits!$E$5),B25+C25) -> 245.3 | E25: =ROUND(B25+C25-D25,2) -> 827.17 | F25: =IF(Crédits!$K$5="",0,MAX(0,MIN(E25,Plan!$L$27-(IF(Crédits!$K$6="",0,IF(Crédits!$K$6<Crédits!$K$5,M25,0))+IF(Crédits!$K$7="",0,IF(Crédits!$K$7<Crédits!$K$5,U25,0))+IF(Crédits!$K$8="",0,IF(Crédits!$K$8<Crédits!$K$5,AC25,0))+IF(Crédits!$K$9="",0,IF(Crédits!$K$9<Crédits!$K$5,AK25,0))+IF(Crédits!$K$10="",0,IF(Crédits!$K$10<Crédits!$K$5,AS25,0)))))) -> 537.04525 | G25: =ROUND(E25-F25,2) -> 290.12 | H25: =ROUND(H24+I25-MIN(N(Crédits!$E$5),H24+I25),2) -> 3102.99 | I25: =H24*N(Crédits!$D$5)/12 -> 13.616569 | J25: =O24 -> 0 | K25: =J25*N(Crédits!$D$6)/12 -> 0 | L25: =MIN(N(Crédits!$E$6),J25+K25) -> 0 | M25: =ROUND(J25+K25-L25,2) -> 0 | N25: =IF(Crédits!$K$6="",0,MAX(0,MIN(M25,Plan!$L$27-(IF(Crédits!$K$5="",0,IF(Crédits!$K$5<Crédits!$K$6,E25,0))+IF(Crédits!$K$7="",0,IF(Crédits!$K$7<Crédits!$K$6,U25,0))+IF(Crédits!$K$8="",0,IF(Crédits!$K$8<Crédits!$K$6,AC25,0))+IF(Crédits!$K$9="",0,IF(Crédits!$K$9<Crédits!$K$6,AK25,0))+IF(Crédits!$K$10="",0,IF(Crédits!$K$10<Crédits!$K$6,AS25,0)))))) -> 0 | O25: =ROUND(M25-N25,2) -> 0 | P25: =ROUND(P24+Q25-MIN(N(Crédits!$E$6),P24+Q25),2) -> 661.96 | Q25: =P24*N(Crédits!$D$6)/12 -> 11.386778 | R25: =W24 -> 0 | S25: =R25*N(Crédits!$D$7)/12 -> 0 | T25: =MIN(N(Crédits!$E$7),R25+S25) -> 0 | U25: =ROUND(R25+S25-T25,2) -> 0 | V25: =IF(Crédits!$K$7="",0,MAX(0,MIN(U25,Plan!$L$27-(IF(Crédits!$K$5="",0,IF(Crédits!$K$5<Crédits!$K$7,E25,0))+IF(Crédits!$K$6="",0,IF(Crédits!$K$6<Crédits!$K$7,M25,0))+IF(Crédits!$K$8="",0,IF(Crédits!$K$8<Crédits!$K$7,AC25,0))+IF(Crédits!$K$9="",0,IF(Crédits!$K$9<Crédits!$K$7,AK25,0))+IF(Crédits!$K$10="",0,IF(Crédits!$K$10<Crédits!$K$7,AS25,0)))))) -> 0 | W25: =ROUND(U25-V25,2) -> 0 | X25: =ROUND(X24+Y25-MIN(N(Crédits!$E$7),X24+Y25),2) -> 933.3 | Y25: =X24*N(Crédits!$D$7)/12 -> 5.3642863 | Z25: =AE24 -> 34.59 | AA25: =Z25*N(Crédits!$D$8)/12 -> 0.03459 | AB25: =MIN(N(Crédits!$E$8),Z25+AA25) -> 34.62459 | AC25: =ROUND(Z25+AA25-AB25,2) -> 0 | AD25: =IF(Crédits!$K$8="",0,MAX(0,MIN(AC25,Plan!$L$27-(IF(Crédits!$K$5="",0,IF(Crédits!$K$5<Crédits!$K$8,E25,0))+IF(Crédits!$K$6="",0,IF(Crédits!$K$6<Crédits!$K$8,M25,0))+IF(Crédits!$K$7="",0,IF(Crédits!$K$7<Crédits!$K$8,U25,0))+IF(Crédits!$K$9="",0,IF(Crédits!$K$9<Crédits!$K$8,AK25,0))+IF(Crédits!$K$10="",0,IF(Crédits!$K$10<Crédits!$K$8,AS25,0)))))) -> 0 | AE25: =ROUND(AC25-AD25,2) -> 0 | AF25: =ROUND(AF24+AG25-MIN(N(Crédits!$E$8),AF24+AG25),2) -> 0 | AG25: =AF24*N(Crédits!$D$8)/12 -> 0.03459 | AH25: =AM24 -> 0 | AI25: =AH25*N(Crédits!$D$9)/12 -> 0 | AJ25: =MIN(N(Crédits!$E$9),AH25+AI25) -> 0 | AK25: =ROUND(AH25+AI25-AJ25,2) -> 0 | AL25: =IF(Crédits!$K$9="",0,MAX(0,MIN(AK25,Plan!$L$27-(IF(Crédits!$K$5="",0,IF(Crédits!$K$5<Crédits!$K$9,E25,0))+IF(Crédits!$K$6="",0,IF(Crédits!$K$6<Crédits!$K$9,M25,0))+IF(Crédits!$K$7="",0,IF(Crédits!$K$7<Crédits!$K$9,U25,0))+IF(Crédits!$K$8="",0,IF(Crédits!$K$8<Crédits!$K$9,AC25,0))+IF(Crédits!$K$10="",0,IF(Crédits!$K$10<Crédits!$K$9,AS25,0)))))) -> 0 | AM25: =ROUND(AK25-AL25,2) -> 0 | AN25: =ROUND(AN24+AO25-MIN(N(Crédits!$E$9),AN24+AO25),2) -> 0 | AO25: =AN24*N(Crédits!$D$9)/12 -> 0 | AP25: =AU24 -> 0 | AQ25: =AP25*N(Crédits!$D$10)/12 -> 0 | AR25: =MIN(N(Crédits!$E$10),AP25+AQ25) -> 0 | AS25: =ROUND(AP25+AQ25-AR25,2) -> 0 | AT25: =IF(Crédits!$K$10="",0,MAX(0,MIN(AS25,Plan!$L$27-(IF(Crédits!$K$5="",0,IF(Crédits!$K$5<Crédits!$K$10,E25,0))+IF(Crédits!$K$6="",0,IF(Crédits!$K$6<Crédits!$K$10,M25,0))+IF(Crédits!$K$7="",0,IF(Crédits!$K$7<Crédits!$K$10,U25,0))+IF(Crédits!$K$8="",0,IF(Crédits!$K$8<Crédits!$K$10,AC25,0))+IF(Crédits!$K$9="",0,IF(Crédits!$K$9<Crédits!$K$10,AK25,0)))))) -> 0 | AU25: =ROUND(AS25-AT25,2) -> 0 | AV25: =ROUND(AV24+AW25-MIN(N(Crédits!$E$10),AV24+AW25),2) -> 0 | AW25: =AV24*N(Crédits!$D$10)/12 -> 0 | AX25: =D25+L25+T25+AB25+AJ25+AR25 -> 279.92459 | AY25: =F25+N25+V25+AD25+AL25+AT25 -> 537.04525 | AZ25: =G25+O25+W25+AE25+AM25+AU25 -> 290.12 | BA25: =C25+K25+S25+AA25+AI25+AQ25 -> 4.3960392 | BB25: =I25+Q25+Y25+AG25+AO25+AW25 -> 30.402223
A26: 24 | B26: =G25 -> 290.12 | C26: =B26*N(Crédits!$D$5)/12 -> 1.1846567 | D26: =MIN(N(Crédits!$E$5),B26+C26) -> 245.3 | E26: =ROUND(B26+C26-D26,2) -> 46 | F26: =IF(Crédits!$K$5="",0,MAX(0,MIN(E26,Plan!$L$28-(IF(Crédits!$K$6="",0,IF(Crédits!$K$6<Crédits!$K$5,M26,0))+IF(Crédits!$K$7="",0,IF(Crédits!$K$7<Crédits!$K$5,U26,0))+IF(Crédits!$K$8="",0,IF(Crédits!$K$8<Crédits!$K$5,AC26,0))+IF(Crédits!$K$9="",0,IF(Crédits!$K$9<Crédits!$K$5,AK26,0))+IF(Crédits!$K$10="",0,IF(Crédits!$K$10<Crédits!$K$5,AS26,0)))))) -> 46 | G26: =ROUND(E26-F26,2) -> 0 | H26: =ROUND(H25+I26-MIN(N(Crédits!$E$5),H25+I26),2) -> 2870.36 | I26: =H25*N(Crédits!$D$5)/12 -> 12.670542 | J26: =O25 -> 0 | K26: =J26*N(Crédits!$D$6)/12 -> 0 | L26: =MIN(N(Crédits!$E$6),J26+K26) -> 0 | M26: =ROUND(J26+K26-L26,2) -> 0 | N26: =IF(Crédits!$K$6="",0,MAX(0,MIN(M26,Plan!$L$28-(IF(Crédits!$K$5="",0,IF(Crédits!$K$5<Crédits!$K$6,E26,0))+IF(Crédits!$K$7="",0,IF(Crédits!$K$7<Crédits!$K$6,U26,0))+IF(Crédits!$K$8="",0,IF(Crédits!$K$8<Crédits!$K$6,AC26,0))+IF(Crédits!$K$9="",0,IF(Crédits!$K$9<Crédits!$K$6,AK26,0))+IF(Crédits!$K$10="",0,IF(Crédits!$K$10<Crédits!$K$6,AS26,0)))))) -> 0 | O26: =ROUND(M26-N26,2) -> 0 | P26: =ROUND(P25+Q26-MIN(N(Crédits!$E$6),P25+Q26),2) -> 599.99 | Q26: =P25*N(Crédits!$D$6)/12 -> 10.42587 | R26: =W25 -> 0 | S26: =R26*N(Crédits!$D$7)/12 -> 0 | T26: =MIN(N(Crédits!$E$7),R26+S26) -> 0 | U26: =ROUND(R26+S26-T26,2) -> 0 | V26: =IF(Crédits!$K$7="",0,MAX(0,MIN(U26,Plan!$L$28-(IF(Crédits!$K$5="",0,IF(Crédits!$K$5<Crédits!$K$7,E26,0))+IF(Crédits!$K$6="",0,IF(Crédits!$K$6<Crédits!$K$7,M26,0))+IF(Crédits!$K$8="",0,IF(Crédits!$K$8<Crédits!$K$7,AC26,0))+IF(Crédits!$K$9="",0,IF(Crédits!$K$9<Crédits!$K$7,AK26,0))+IF(Crédits!$K$10="",0,IF(Crédits!$K$10<Crédits!$K$7,AS26,0)))))) -> 0 | W26: =ROUND(U26-V26,2) -> 0 | X26: =ROUND(X25+Y26-MIN(N(Crédits!$E$7),X25+Y26),2) -> 819.33 | Y26: =X25*N(Crédits!$D$7)/12 -> 4.7831625 | Z26: =AE25 -> 0 | AA26: =Z26*N(Crédits!$D$8)/12 -> 0 | AB26: =MIN(N(Crédits!$E$8),Z26+AA26) -> 0 | AC26: =ROUND(Z26+AA26-AB26,2) -> 0 | AD26: =IF(Crédits!$K$8="",0,MAX(0,MIN(AC26,Plan!$L$28-(IF(Crédits!$K$5="",0,IF(Crédits!$K$5<Crédits!$K$8,E26,0))+IF(Crédits!$K$6="",0,IF(Crédits!$K$6<Crédits!$K$8,M26,0))+IF(Crédits!$K$7="",0,IF(Crédits!$K$7<Crédits!$K$8,U26,0))+IF(Crédits!$K$9="",0,IF(Crédits!$K$9<Crédits!$K$8,AK26,0))+IF(Crédits!$K$10="",0,IF(Crédits!$K$10<Crédits!$K$8,AS26,0)))))) -> 0 | AE26: =ROUND(AC26-AD26,2) -> 0 | AF26: =ROUND(AF25+AG26-MIN(N(Crédits!$E$8),AF25+AG26),2) -> 0 | AG26: =AF25*N(Crédits!$D$8)/12 -> 0 | AH26: =AM25 -> 0 | AI26: =AH26*N(Crédits!$D$9)/12 -> 0 | AJ26: =MIN(N(Crédits!$E$9),AH26+AI26) -> 0 | AK26: =ROUND(AH26+AI26-AJ26,2) -> 0 | AL26: =IF(Crédits!$K$9="",0,MAX(0,MIN(AK26,Plan!$L$28-(IF(Crédits!$K$5="",0,IF(Crédits!$K$5<Crédits!$K$9,E26,0))+IF(Crédits!$K$6="",0,IF(Crédits!$K$6<Crédits!$K$9,M26,0))+IF(Crédits!$K$7="",0,IF(Crédits!$K$7<Crédits!$K$9,U26,0))+IF(Crédits!$K$8="",0,IF(Crédits!$K$8<Crédits!$K$9,AC26,0))+IF(Crédits!$K$10="",0,IF(Crédits!$K$10<Crédits!$K$9,AS26,0)))))) -> 0 | AM26: =ROUND(AK26-AL26,2) -> 0 | AN26: =ROUND(AN25+AO26-MIN(N(Crédits!$E$9),AN25+AO26),2) -> 0 | AO26: =AN25*N(Crédits!$D$9)/12 -> 0 | AP26: =AU25 -> 0 | AQ26: =AP26*N(Crédits!$D$10)/12 -> 0 | AR26: =MIN(N(Crédits!$E$10),AP26+AQ26) -> 0 | AS26: =ROUND(AP26+AQ26-AR26,2) -> 0 | AT26: =IF(Crédits!$K$10="",0,MAX(0,MIN(AS26,Plan!$L$28-(IF(Crédits!$K$5="",0,IF(Crédits!$K$5<Crédits!$K$10,E26,0))+IF(Crédits!$K$6="",0,IF(Crédits!$K$6<Crédits!$K$10,M26,0))+IF(Crédits!$K$7="",0,IF(Crédits!$K$7<Crédits!$K$10,U26,0))+IF(Crédits!$K$8="",0,IF(Crédits!$K$8<Crédits!$K$10,AC26,0))+IF(Crédits!$K$9="",0,IF(Crédits!$K$9<Crédits!$K$10,AK26,0)))))) -> 0 | AU26: =ROUND(AS26-AT26,2) -> 0 | AV26: =ROUND(AV25+AW26-MIN(N(Crédits!$E$10),AV25+AW26),2) -> 0 | AW26: =AV25*N(Crédits!$D$10)/12 -> 0 | AX26: =D26+L26+T26+AB26+AJ26+AR26 -> 245.3 | AY26: =F26+N26+V26+AD26+AL26+AT26 -> 46 | AZ26: =G26+O26+W26+AE26+AM26+AU26 -> 0 | BA26: =C26+K26+S26+AA26+AI26+AQ26 -> 1.1846567 | BB26: =I26+Q26+Y26+AG26+AO26+AW26 -> 27.879575
A27: 25 | B27: =G26 -> 0 | C27: =B27*N(Crédits!$D$5)/12 -> 0 | D27: =MIN(N(Crédits!$E$5),B27+C27) -> 0 | E27: =ROUND(B27+C27-D27,2) -> 0 | F27: =IF(Crédits!$K$5="",0,MAX(0,MIN(E27,Plan!$L$29-(IF(Crédits!$K$6="",0,IF(Crédits!$K$6<Crédits!$K$5,M27,0))+IF(Crédits!$K$7="",0,IF(Crédits!$K$7<Crédits!$K$5,U27,0))+IF(Crédits!$K$8="",0,IF(Crédits!$K$8<Crédits!$K$5,AC27,0))+IF(Crédits!$K$9="",0,IF(Crédits!$K$9<Crédits!$K$5,AK27,0))+IF(Crédits!$K$10="",0,IF(Crédits!$K$10<Crédits!$K$5,AS27,0)))))) -> 0 | G27: =ROUND(E27-F27,2) -> 0 | H27: =ROUND(H26+I27-MIN(N(Crédits!$E$5),H26+I27),2) -> 2636.78 | I27: =H26*N(Crédits!$D$5)/12 -> 11.720637 | J27: =O26 -> 0 | K27: =J27*N(Crédits!$D$6)/12 -> 0 | L27: =MIN(N(Crédits!$E$6),J27+K27) -> 0 | M27: =ROUND(J27+K27-L27,2) -> 0 | N27: =IF(Crédits!$K$6="",0,MAX(0,MIN(M27,Plan!$L$29-(IF(Crédits!$K$5="",0,IF(Crédits!$K$5<Crédits!$K$6,E27,0))+IF(Crédits!$K$7="",0,IF(Crédits!$K$7<Crédits!$K$6,U27,0))+IF(Crédits!$K$8="",0,IF(Crédits!$K$8<Crédits!$K$6,AC27,0))+IF(Crédits!$K$9="",0,IF(Crédits!$K$9<Crédits!$K$6,AK27,0))+IF(Crédits!$K$10="",0,IF(Crédits!$K$10<Crédits!$K$6,AS27,0)))))) -> 0 | O27: =ROUND(M27-N27,2) -> 0 | P27: =ROUND(P26+Q27-MIN(N(Crédits!$E$6),P26+Q27),2) -> 537.04 | Q27: =P26*N(Crédits!$D$6)/12 -> 9.4498425 | R27: =W26 -> 0 | S27: =R27*N(Crédits!$D$7)/12 -> 0 | T27: =MIN(N(Crédits!$E$7),R27+S27) -> 0 | U27: =ROUND(R27+S27-T27,2) -> 0 | V27: =IF(Crédits!$K$7="",0,MAX(0,MIN(U27,Plan!$L$29-(IF(Crédits!$K$5="",0,IF(Crédits!$K$5<Crédits!$K$7,E27,0))+IF(Crédits!$K$6="",0,IF(Crédits!$K$6<Crédits!$K$7,M27,0))+IF(Crédits!$K$8="",0,IF(Crédits!$K$8<Crédits!$K$7,AC27,0))+IF(Crédits!$K$9="",0,IF(Crédits!$K$9<Crédits!$K$7,AK27,0))+IF(Crédits!$K$10="",0,IF(Crédits!$K$10<Crédits!$K$7,AS27,0)))))) -> 0 | W27: =ROUND(U27-V27,2) -> 0 | X27: =ROUND(X26+Y27-MIN(N(Crédits!$E$7),X26+Y27),2) -> 704.78 | Y27: =X26*N(Crédits!$D$7)/12 -> 4.1990663 | Z27: =AE26 -> 0 | AA27: =Z27*N(Crédits!$D$8)/12 -> 0 | AB27: =MIN(N(Crédits!$E$8),Z27+AA27) -> 0 | AC27: =ROUND(Z27+AA27-AB27,2) -> 0 | AD27: =IF(Crédits!$K$8="",0,MAX(0,MIN(AC27,Plan!$L$29-(IF(Crédits!$K$5="",0,IF(Crédits!$K$5<Crédits!$K$8,E27,0))+IF(Crédits!$K$6="",0,IF(Crédits!$K$6<Crédits!$K$8,M27,0))+IF(Crédits!$K$7="",0,IF(Crédits!$K$7<Crédits!$K$8,U27,0))+IF(Crédits!$K$9="",0,IF(Crédits!$K$9<Crédits!$K$8,AK27,0))+IF(Crédits!$K$10="",0,IF(Crédits!$K$10<Crédits!$K$8,AS27,0)))))) -> 0 | AE27: =ROUND(AC27-AD27,2) -> 0 | AF27: =ROUND(AF26+AG27-MIN(N(Crédits!$E$8),AF26+AG27),2) -> 0 | AG27: =AF26*N(Crédits!$D$8)/12 -> 0 | AH27: =AM26 -> 0 | AI27: =AH27*N(Crédits!$D$9)/12 -> 0 | AJ27: =MIN(N(Crédits!$E$9),AH27+AI27) -> 0 | AK27: =ROUND(AH27+AI27-AJ27,2) -> 0 | AL27: =IF(Crédits!$K$9="",0,MAX(0,MIN(AK27,Plan!$L$29-(IF(Crédits!$K$5="",0,IF(Crédits!$K$5<Crédits!$K$9,E27,0))+IF(Crédits!$K$6="",0,IF(Crédits!$K$6<Crédits!$K$9,M27,0))+IF(Crédits!$K$7="",0,IF(Crédits!$K$7<Crédits!$K$9,U27,0))+IF(Crédits!$K$8="",0,IF(Crédits!$K$8<Crédits!$K$9,AC27,0))+IF(Crédits!$K$10="",0,IF(Crédits!$K$10<Crédits!$K$9,AS27,0)))))) -> 0 | AM27: =ROUND(AK27-AL27,2) -> 0 | AN27: =ROUND(AN26+AO27-MIN(N(Crédits!$E$9),AN26+AO27),2) -> 0 | AO27: =AN26*N(Crédits!$D$9)/12 -> 0 | AP27: =AU26 -> 0 | AQ27: =AP27*N(Crédits!$D$10)/12 -> 0 | AR27: =MIN(N(Crédits!$E$10),AP27+AQ27) -> 0 | AS27: =ROUND(AP27+AQ27-AR27,2) -> 0 | AT27: =IF(Crédits!$K$10="",0,MAX(0,MIN(AS27,Plan!$L$29-(IF(Crédits!$K$5="",0,IF(Crédits!$K$5<Crédits!$K$10,E27,0))+IF(Crédits!$K$6="",0,IF(Crédits!$K$6<Crédits!$K$10,M27,0))+IF(Crédits!$K$7="",0,IF(Crédits!$K$7<Crédits!$K$10,U27,0))+IF(Crédits!$K$8="",0,IF(Crédits!$K$8<Crédits!$K$10,AC27,0))+IF(Crédits!$K$9="",0,IF(Crédits!$K$9<Crédits!$K$10,AK27,0)))))) -> 0 | AU27: =ROUND(AS27-AT27,2) -> 0 | AV27: =ROUND(AV26+AW27-MIN(N(Crédits!$E$10),AV26+AW27),2) -> 0 | AW27: =AV26*N(Crédits!$D$10)/12 -> 0 | AX27: =D27+L27+T27+AB27+AJ27+AR27 -> 0 | AY27: =F27+N27+V27+AD27+AL27+AT27 -> 0 | AZ27: =G27+O27+W27+AE27+AM27+AU27 -> 0 | BA27: =C27+K27+S27+AA27+AI27+AQ27 -> 0 | BB27: =I27+Q27+Y27+AG27+AO27+AW27 -> 25.369545
A28: 26 | B28: =G27 -> 0 | C28: =B28*N(Crédits!$D$5)/12 -> 0 | D28: =MIN(N(Crédits!$E$5),B28+C28) -> 0 | E28: =ROUND(B28+C28-D28,2) -> 0 | F28: =IF(Crédits!$K$5="",0,MAX(0,MIN(E28,Plan!$L$30-(IF(Crédits!$K$6="",0,IF(Crédits!$K$6<Crédits!$K$5,M28,0))+IF(Crédits!$K$7="",0,IF(Crédits!$K$7<Crédits!$K$5,U28,0))+IF(Crédits!$K$8="",0,IF(Crédits!$K$8<Crédits!$K$5,AC28,0))+IF(Crédits!$K$9="",0,IF(Crédits!$K$9<Crédits!$K$5,AK28,0))+IF(Crédits!$K$10="",0,IF(Crédits!$K$10<Crédits!$K$5,AS28,0)))))) -> 0 | G28: =ROUND(E28-F28,2) -> 0 | H28: =ROUND(H27+I28-MIN(N(Crédits!$E$5),H27+I28),2) -> 2402.25 | I28: =H27*N(Crédits!$D$5)/12 -> 10.766852 | J28: =O27 -> 0 | K28: =J28*N(Crédits!$D$6)/12 -> 0 | L28: =MIN(N(Crédits!$E$6),J28+K28) -> 0 | M28: =ROUND(J28+K28-L28,2) -> 0 | N28: =IF(Crédits!$K$6="",0,MAX(0,MIN(M28,Plan!$L$30-(IF(Crédits!$K$5="",0,IF(Crédits!$K$5<Crédits!$K$6,E28,0))+IF(Crédits!$K$7="",0,IF(Crédits!$K$7<Crédits!$K$6,U28,0))+IF(Crédits!$K$8="",0,IF(Crédits!$K$8<Crédits!$K$6,AC28,0))+IF(Crédits!$K$9="",0,IF(Crédits!$K$9<Crédits!$K$6,AK28,0))+IF(Crédits!$K$10="",0,IF(Crédits!$K$10<Crédits!$K$6,AS28,0)))))) -> 0 | O28: =ROUND(M28-N28,2) -> 0 | P28: =ROUND(P27+Q28-MIN(N(Crédits!$E$6),P27+Q28),2) -> 473.1 | Q28: =P27*N(Crédits!$D$6)/12 -> 8.45838 | R28: =W27 -> 0 | S28: =R28*N(Crédits!$D$7)/12 -> 0 | T28: =MIN(N(Crédits!$E$7),R28+S28) -> 0 | U28: =ROUND(R28+S28-T28,2) -> 0 | V28: =IF(Crédits!$K$7="",0,MAX(0,MIN(U28,Plan!$L$30-(IF(Crédits!$K$5="",0,IF(Crédits!$K$5<Crédits!$K$7,E28,0))+IF(Crédits!$K$6="",0,IF(Crédits!$K$6<Crédits!$K$7,M28,0))+IF(Crédits!$K$8="",0,IF(Crédits!$K$8<Crédits!$K$7,AC28,0))+IF(Crédits!$K$9="",0,IF(Crédits!$K$9<Crédits!$K$7,AK28,0))+IF(Crédits!$K$10="",0,IF(Crédits!$K$10<Crédits!$K$7,AS28,0)))))) -> 0 | W28: =ROUND(U28-V28,2) -> 0 | X28: =ROUND(X27+Y28-MIN(N(Crédits!$E$7),X27+Y28),2) -> 589.64 | Y28: =X27*N(Crédits!$D$7)/12 -> 3.6119975 | Z28: =AE27 -> 0 | AA28: =Z28*N(Crédits!$D$8)/12 -> 0 | AB28: =MIN(N(Crédits!$E$8),Z28+AA28) -> 0 | AC28: =ROUND(Z28+AA28-AB28,2) -> 0 | AD28: =IF(Crédits!$K$8="",0,MAX(0,MIN(AC28,Plan!$L$30-(IF(Crédits!$K$5="",0,IF(Crédits!$K$5<Crédits!$K$8,E28,0))+IF(Crédits!$K$6="",0,IF(Crédits!$K$6<Crédits!$K$8,M28,0))+IF(Crédits!$K$7="",0,IF(Crédits!$K$7<Crédits!$K$8,U28,0))+IF(Crédits!$K$9="",0,IF(Crédits!$K$9<Crédits!$K$8,AK28,0))+IF(Crédits!$K$10="",0,IF(Crédits!$K$10<Crédits!$K$8,AS28,0)))))) -> 0 | AE28: =ROUND(AC28-AD28,2) -> 0 | AF28: =ROUND(AF27+AG28-MIN(N(Crédits!$E$8),AF27+AG28),2) -> 0 | AG28: =AF27*N(Crédits!$D$8)/12 -> 0 | AH28: =AM27 -> 0 | AI28: =AH28*N(Crédits!$D$9)/12 -> 0 | AJ28: =MIN(N(Crédits!$E$9),AH28+AI28) -> 0 | AK28: =ROUND(AH28+AI28-AJ28,2) -> 0 | AL28: =IF(Crédits!$K$9="",0,MAX(0,MIN(AK28,Plan!$L$30-(IF(Crédits!$K$5="",0,IF(Crédits!$K$5<Crédits!$K$9,E28,0))+IF(Crédits!$K$6="",0,IF(Crédits!$K$6<Crédits!$K$9,M28,0))+IF(Crédits!$K$7="",0,IF(Crédits!$K$7<Crédits!$K$9,U28,0))+IF(Crédits!$K$8="",0,IF(Crédits!$K$8<Crédits!$K$9,AC28,0))+IF(Crédits!$K$10="",0,IF(Crédits!$K$10<Crédits!$K$9,AS28,0)))))) -> 0 | AM28: =ROUND(AK28-AL28,2) -> 0 | AN28: =ROUND(AN27+AO28-MIN(N(Crédits!$E$9),AN27+AO28),2) -> 0 | AO28: =AN27*N(Crédits!$D$9)/12 -> 0 | AP28: =AU27 -> 0 | AQ28: =AP28*N(Crédits!$D$10)/12 -> 0 | AR28: =MIN(N(Crédits!$E$10),AP28+AQ28) -> 0 | AS28: =ROUND(AP28+AQ28-AR28,2) -> 0 | AT28: =IF(Crédits!$K$10="",0,MAX(0,MIN(AS28,Plan!$L$30-(IF(Crédits!$K$5="",0,IF(Crédits!$K$5<Crédits!$K$10,E28,0))+IF(Crédits!$K$6="",0,IF(Crédits!$K$6<Crédits!$K$10,M28,0))+IF(Crédits!$K$7="",0,IF(Crédits!$K$7<Crédits!$K$10,U28,0))+IF(Crédits!$K$8="",0,IF(Crédits!$K$8<Crédits!$K$10,AC28,0))+IF(Crédits!$K$9="",0,IF(Crédits!$K$9<Crédits!$K$10,AK28,0)))))) -> 0 | AU28: =ROUND(AS28-AT28,2) -> 0 | AV28: =ROUND(AV27+AW28-MIN(N(Crédits!$E$10),AV27+AW28),2) -> 0 | AW28: =AV27*N(Crédits!$D$10)/12 -> 0 | AX28: =D28+L28+T28+AB28+AJ28+AR28 -> 0 | AY28: =F28+N28+V28+AD28+AL28+AT28 -> 0 | AZ28: =G28+O28+W28+AE28+AM28+AU28 -> 0 | BA28: =C28+K28+S28+AA28+AI28+AQ28 -> 0 | BB28: =I28+Q28+Y28+AG28+AO28+AW28 -> 22.837229
A29: 27 | B29: =G28 -> 0 | C29: =B29*N(Crédits!$D$5)/12 -> 0 | D29: =MIN(N(Crédits!$E$5),B29+C29) -> 0 | E29: =ROUND(B29+C29-D29,2) -> 0 | F29: =IF(Crédits!$K$5="",0,MAX(0,MIN(E29,Plan!$L$31-(IF(Crédits!$K$6="",0,IF(Crédits!$K$6<Crédits!$K$5,M29,0))+IF(Crédits!$K$7="",0,IF(Crédits!$K$7<Crédits!$K$5,U29,0))+IF(Crédits!$K$8="",0,IF(Crédits!$K$8<Crédits!$K$5,AC29,0))+IF(Crédits!$K$9="",0,IF(Crédits!$K$9<Crédits!$K$5,AK29,0))+IF(Crédits!$K$10="",0,IF(Crédits!$K$10<Crédits!$K$5,AS29,0)))))) -> 0 | G29: =ROUND(E29-F29,2) -> 0 | H29: =ROUND(H28+I29-MIN(N(Crédits!$E$5),H28+I29),2) -> 2166.76 | I29: =H28*N(Crédits!$D$5)/12 -> 9.8091875 | J29: =O28 -> 0 | K29: =J29*N(Crédits!$D$6)/12 -> 0 | L29: =MIN(N(Crédits!$E$6),J29+K29) -> 0 | M29: =ROUND(J29+K29-L29,2) -> 0 | N29: =IF(Crédits!$K$6="",0,MAX(0,MIN(M29,Plan!$L$31-(IF(Crédits!$K$5="",0,IF(Crédits!$K$5<Crédits!$K$6,E29,0))+IF(Crédits!$K$7="",0,IF(Crédits!$K$7<Crédits!$K$6,U29,0))+IF(Crédits!$K$8="",0,IF(Crédits!$K$8<Crédits!$K$6,AC29,0))+IF(Crédits!$K$9="",0,IF(Crédits!$K$9<Crédits!$K$6,AK29,0))+IF(Crédits!$K$10="",0,IF(Crédits!$K$10<Crédits!$K$6,AS29,0)))))) -> 0 | O29: =ROUND(M29-N29,2) -> 0 | P29: =ROUND(P28+Q29-MIN(N(Crédits!$E$6),P28+Q29),2) -> 408.15 | Q29: =P28*N(Crédits!$D$6)/12 -> 7.451325 | R29: =W28 -> 0 | S29: =R29*N(Crédits!$D$7)/12 -> 0 | T29: =MIN(N(Crédits!$E$7),R29+S29) -> 0 | U29: =ROUND(R29+S29-T29,2) -> 0 | V29: =IF(Crédits!$K$7="",0,MAX(0,MIN(U29,Plan!$L$31-(IF(Crédits!$K$5="",0,IF(Crédits!$K$5<Crédits!$K$7,E29,0))+IF(Crédits!$K$6="",0,IF(Crédits!$K$6<Crédits!$K$7,M29,0))+IF(Crédits!$K$8="",0,IF(Crédits!$K$8<Crédits!$K$7,AC29,0))+IF(Crédits!$K$9="",0,IF(Crédits!$K$9<Crédits!$K$7,AK29,0))+IF(Crédits!$K$10="",0,IF(Crédits!$K$10<Crédits!$K$7,AS29,0)))))) -> 0 | W29: =ROUND(U29-V29,2) -> 0 | X29: =ROUND(X28+Y29-MIN(N(Crédits!$E$7),X28+Y29),2) -> 473.91 | Y29: =X28*N(Crédits!$D$7)/12 -> 3.021905 | Z29: =AE28 -> 0 | AA29: =Z29*N(Crédits!$D$8)/12 -> 0 | AB29: =MIN(N(Crédits!$E$8),Z29+AA29) -> 0 | AC29: =ROUND(Z29+AA29-AB29,2) -> 0 | AD29: =IF(Crédits!$K$8="",0,MAX(0,MIN(AC29,Plan!$L$31-(IF(Crédits!$K$5="",0,IF(Crédits!$K$5<Crédits!$K$8,E29,0))+IF(Crédits!$K$6="",0,IF(Crédits!$K$6<Crédits!$K$8,M29,0))+IF(Crédits!$K$7="",0,IF(Crédits!$K$7<Crédits!$K$8,U29,0))+IF(Crédits!$K$9="",0,IF(Crédits!$K$9<Crédits!$K$8,AK29,0))+IF(Crédits!$K$10="",0,IF(Crédits!$K$10<Crédits!$K$8,AS29,0)))))) -> 0 | AE29: =ROUND(AC29-AD29,2) -> 0 | AF29: =ROUND(AF28+AG29-MIN(N(Crédits!$E$8),AF28+AG29),2) -> 0 | AG29: =AF28*N(Crédits!$D$8)/12 -> 0 | AH29: =AM28 -> 0 | AI29: =AH29*N(Crédits!$D$9)/12 -> 0 | AJ29: =MIN(N(Crédits!$E$9),AH29+AI29) -> 0 | AK29: =ROUND(AH29+AI29-AJ29,2) -> 0 | AL29: =IF(Crédits!$K$9="",0,MAX(0,MIN(AK29,Plan!$L$31-(IF(Crédits!$K$5="",0,IF(Crédits!$K$5<Crédits!$K$9,E29,0))+IF(Crédits!$K$6="",0,IF(Crédits!$K$6<Crédits!$K$9,M29,0))+IF(Crédits!$K$7="",0,IF(Crédits!$K$7<Crédits!$K$9,U29,0))+IF(Crédits!$K$8="",0,IF(Crédits!$K$8<Crédits!$K$9,AC29,0))+IF(Crédits!$K$10="",0,IF(Crédits!$K$10<Crédits!$K$9,AS29,0)))))) -> 0 | AM29: =ROUND(AK29-AL29,2) -> 0 | AN29: =ROUND(AN28+AO29-MIN(N(Crédits!$E$9),AN28+AO29),2) -> 0 | AO29: =AN28*N(Crédits!$D$9)/12 -> 0 | AP29: =AU28 -> 0 | AQ29: =AP29*N(Crédits!$D$10)/12 -> 0 | AR29: =MIN(N(Crédits!$E$10),AP29+AQ29) -> 0 | AS29: =ROUND(AP29+AQ29-AR29,2) -> 0 | AT29: =IF(Crédits!$K$10="",0,MAX(0,MIN(AS29,Plan!$L$31-(IF(Crédits!$K$5="",0,IF(Crédits!$K$5<Crédits!$K$10,E29,0))+IF(Crédits!$K$6="",0,IF(Crédits!$K$6<Crédits!$K$10,M29,0))+IF(Crédits!$K$7="",0,IF(Crédits!$K$7<Crédits!$K$10,U29,0))+IF(Crédits!$K$8="",0,IF(Crédits!$K$8<Crédits!$K$10,AC29,0))+IF(Crédits!$K$9="",0,IF(Crédits!$K$9<Crédits!$K$10,AK29,0)))))) -> 0 | AU29: =ROUND(AS29-AT29,2) -> 0 | AV29: =ROUND(AV28+AW29-MIN(N(Crédits!$E$10),AV28+AW29),2) -> 0 | AW29: =AV28*N(Crédits!$D$10)/12 -> 0 | AX29: =D29+L29+T29+AB29+AJ29+AR29 -> 0 | AY29: =F29+N29+V29+AD29+AL29+AT29 -> 0 | AZ29: =G29+O29+W29+AE29+AM29+AU29 -> 0 | BA29: =C29+K29+S29+AA29+AI29+AQ29 -> 0 | BB29: =I29+Q29+Y29+AG29+AO29+AW29 -> 20.282418
A30: 28 | B30: =G29 -> 0 | C30: =B30*N(Crédits!$D$5)/12 -> 0 | D30: =MIN(N(Crédits!$E$5),B30+C30) -> 0 | E30: =ROUND(B30+C30-D30,2) -> 0 | F30: =IF(Crédits!$K$5="",0,MAX(0,MIN(E30,Plan!$L$32-(IF(Crédits!$K$6="",0,IF(Crédits!$K$6<Crédits!$K$5,M30,0))+IF(Crédits!$K$7="",0,IF(Crédits!$K$7<Crédits!$K$5,U30,0))+IF(Crédits!$K$8="",0,IF(Crédits!$K$8<Crédits!$K$5,AC30,0))+IF(Crédits!$K$9="",0,IF(Crédits!$K$9<Crédits!$K$5,AK30,0))+IF(Crédits!$K$10="",0,IF(Crédits!$K$10<Crédits!$K$5,AS30,0)))))) -> 0 | G30: =ROUND(E30-F30,2) -> 0 | H30: =ROUND(H29+I30-MIN(N(Crédits!$E$5),H29+I30),2) -> 1930.31 | I30: =H29*N(Crédits!$D$5)/12 -> 8.8476033 | J30: =O29 -> 0 | K30: =J30*N(Crédits!$D$6)/12 -> 0 | L30: =MIN(N(Crédits!$E$6),J30+K30) -> 0 | M30: =ROUND(J30+K30-L30,2) -> 0 | N30: =IF(Crédits!$K$6="",0,MAX(0,MIN(M30,Plan!$L$32-(IF(Crédits!$K$5="",0,IF(Crédits!$K$5<Crédits!$K$6,E30,0))+IF(Crédits!$K$7="",0,IF(Crédits!$K$7<Crédits!$K$6,U30,0))+IF(Crédits!$K$8="",0,IF(Crédits!$K$8<Crédits!$K$6,AC30,0))+IF(Crédits!$K$9="",0,IF(Crédits!$K$9<Crédits!$K$6,AK30,0))+IF(Crédits!$K$10="",0,IF(Crédits!$K$10<Crédits!$K$6,AS30,0)))))) -> 0 | O30: =ROUND(M30-N30,2) -> 0 | P30: =ROUND(P29+Q30-MIN(N(Crédits!$E$6),P29+Q30),2) -> 342.18 | Q30: =P29*N(Crédits!$D$6)/12 -> 6.4283625 | R30: =W29 -> 0 | S30: =R30*N(Crédits!$D$7)/12 -> 0 | T30: =MIN(N(Crédits!$E$7),R30+S30) -> 0 | U30: =ROUND(R30+S30-T30,2) -> 0 | V30: =IF(Crédits!$K$7="",0,MAX(0,MIN(U30,Plan!$L$32-(IF(Crédits!$K$5="",0,IF(Crédits!$K$5<Crédits!$K$7,E30,0))+IF(Crédits!$K$6="",0,IF(Crédits!$K$6<Crédits!$K$7,M30,0))+IF(Crédits!$K$8="",0,IF(Crédits!$K$8<Crédits!$K$7,AC30,0))+IF(Crédits!$K$9="",0,IF(Crédits!$K$9<Crédits!$K$7,AK30,0))+IF(Crédits!$K$10="",0,IF(Crédits!$K$10<Crédits!$K$7,AS30,0)))))) -> 0 | W30: =ROUND(U30-V30,2) -> 0 | X30: =ROUND(X29+Y30-MIN(N(Crédits!$E$7),X29+Y30),2) -> 357.59 | Y30: =X29*N(Crédits!$D$7)/12 -> 2.4287888 | Z30: =AE29 -> 0 | AA30: =Z30*N(Crédits!$D$8)/12 -> 0 | AB30: =MIN(N(Crédits!$E$8),Z30+AA30) -> 0 | AC30: =ROUND(Z30+AA30-AB30,2) -> 0 | AD30: =IF(Crédits!$K$8="",0,MAX(0,MIN(AC30,Plan!$L$32-(IF(Crédits!$K$5="",0,IF(Crédits!$K$5<Crédits!$K$8,E30,0))+IF(Crédits!$K$6="",0,IF(Crédits!$K$6<Crédits!$K$8,M30,0))+IF(Crédits!$K$7="",0,IF(Crédits!$K$7<Crédits!$K$8,U30,0))+IF(Crédits!$K$9="",0,IF(Crédits!$K$9<Crédits!$K$8,AK30,0))+IF(Crédits!$K$10="",0,IF(Crédits!$K$10<Crédits!$K$8,AS30,0)))))) -> 0 | AE30: =ROUND(AC30-AD30,2) -> 0 | AF30: =ROUND(AF29+AG30-MIN(N(Crédits!$E$8),AF29+AG30),2) -> 0 | AG30: =AF29*N(Crédits!$D$8)/12 -> 0 | AH30: =AM29 -> 0 | AI30: =AH30*N(Crédits!$D$9)/12 -> 0 | AJ30: =MIN(N(Crédits!$E$9),AH30+AI30) -> 0 | AK30: =ROUND(AH30+AI30-AJ30,2) -> 0 | AL30: =IF(Crédits!$K$9="",0,MAX(0,MIN(AK30,Plan!$L$32-(IF(Crédits!$K$5="",0,IF(Crédits!$K$5<Crédits!$K$9,E30,0))+IF(Crédits!$K$6="",0,IF(Crédits!$K$6<Crédits!$K$9,M30,0))+IF(Crédits!$K$7="",0,IF(Crédits!$K$7<Crédits!$K$9,U30,0))+IF(Crédits!$K$8="",0,IF(Crédits!$K$8<Crédits!$K$9,AC30,0))+IF(Crédits!$K$10="",0,IF(Crédits!$K$10<Crédits!$K$9,AS30,0)))))) -> 0 | AM30: =ROUND(AK30-AL30,2) -> 0 | AN30: =ROUND(AN29+AO30-MIN(N(Crédits!$E$9),AN29+AO30),2) -> 0 | AO30: =AN29*N(Crédits!$D$9)/12 -> 0 | AP30: =AU29 -> 0 | AQ30: =AP30*N(Crédits!$D$10)/12 -> 0 | AR30: =MIN(N(Crédits!$E$10),AP30+AQ30) -> 0 | AS30: =ROUND(AP30+AQ30-AR30,2) -> 0 | AT30: =IF(Crédits!$K$10="",0,MAX(0,MIN(AS30,Plan!$L$32-(IF(Crédits!$K$5="",0,IF(Crédits!$K$5<Crédits!$K$10,E30,0))+IF(Crédits!$K$6="",0,IF(Crédits!$K$6<Crédits!$K$10,M30,0))+IF(Crédits!$K$7="",0,IF(Crédits!$K$7<Crédits!$K$10,U30,0))+IF(Crédits!$K$8="",0,IF(Crédits!$K$8<Crédits!$K$10,AC30,0))+IF(Crédits!$K$9="",0,IF(Crédits!$K$9<Crédits!$K$10,AK30,0)))))) -> 0 | AU30: =ROUND(AS30-AT30,2) -> 0 | AV30: =ROUND(AV29+AW30-MIN(N(Crédits!$E$10),AV29+AW30),2) -> 0 | AW30: =AV29*N(Crédits!$D$10)/12 -> 0 | AX30: =D30+L30+T30+AB30+AJ30+AR30 -> 0 | AY30: =F30+N30+V30+AD30+AL30+AT30 -> 0 | AZ30: =G30+O30+W30+AE30+AM30+AU30 -> 0 | BA30: =C30+K30+S30+AA30+AI30+AQ30 -> 0 | BB30: =I30+Q30+Y30+AG30+AO30+AW30 -> 17.704755
A31: 29 | B31: =G30 -> 0 | C31: =B31*N(Crédits!$D$5)/12 -> 0 | D31: =MIN(N(Crédits!$E$5),B31+C31) -> 0 | E31: =ROUND(B31+C31-D31,2) -> 0 | F31: =IF(Crédits!$K$5="",0,MAX(0,MIN(E31,Plan!$L$33-(IF(Crédits!$K$6="",0,IF(Crédits!$K$6<Crédits!$K$5,M31,0))+IF(Crédits!$K$7="",0,IF(Crédits!$K$7<Crédits!$K$5,U31,0))+IF(Crédits!$K$8="",0,IF(Crédits!$K$8<Crédits!$K$5,AC31,0))+IF(Crédits!$K$9="",0,IF(Crédits!$K$9<Crédits!$K$5,AK31,0))+IF(Crédits!$K$10="",0,IF(Crédits!$K$10<Crédits!$K$5,AS31,0)))))) -> 0 | G31: =ROUND(E31-F31,2) -> 0 | H31: =ROUND(H30+I31-MIN(N(Crédits!$E$5),H30+I31),2) -> 1692.89 | I31: =H30*N(Crédits!$D$5)/12 -> 7.8820992 | J31: =O30 -> 0 | K31: =J31*N(Crédits!$D$6)/12 -> 0 | L31: =MIN(N(Crédits!$E$6),J31+K31) -> 0 | M31: =ROUND(J31+K31-L31,2) -> 0 | N31: =IF(Crédits!$K$6="",0,MAX(0,MIN(M31,Plan!$L$33-(IF(Crédits!$K$5="",0,IF(Crédits!$K$5<Crédits!$K$6,E31,0))+IF(Crédits!$K$7="",0,IF(Crédits!$K$7<Crédits!$K$6,U31,0))+IF(Crédits!$K$8="",0,IF(Crédits!$K$8<Crédits!$K$6,AC31,0))+IF(Crédits!$K$9="",0,IF(Crédits!$K$9<Crédits!$K$6,AK31,0))+IF(Crédits!$K$10="",0,IF(Crédits!$K$10<Crédits!$K$6,AS31,0)))))) -> 0 | O31: =ROUND(M31-N31,2) -> 0 | P31: =ROUND(P30+Q31-MIN(N(Crédits!$E$6),P30+Q31),2) -> 275.17 | Q31: =P30*N(Crédits!$D$6)/12 -> 5.389335 | R31: =W30 -> 0 | S31: =R31*N(Crédits!$D$7)/12 -> 0 | T31: =MIN(N(Crédits!$E$7),R31+S31) -> 0 | U31: =ROUND(R31+S31-T31,2) -> 0 | V31: =IF(Crédits!$K$7="",0,MAX(0,MIN(U31,Plan!$L$33-(IF(Crédits!$K$5="",0,IF(Crédits!$K$5<Crédits!$K$7,E31,0))+IF(Crédits!$K$6="",0,IF(Crédits!$K$6<Crédits!$K$7,M31,0))+IF(Crédits!$K$8="",0,IF(Crédits!$K$8<Crédits!$K$7,AC31,0))+IF(Crédits!$K$9="",0,IF(Crédits!$K$9<Crédits!$K$7,AK31,0))+IF(Crédits!$K$10="",0,IF(Crédits!$K$10<Crédits!$K$7,AS31,0)))))) -> 0 | W31: =ROUND(U31-V31,2) -> 0 | X31: =ROUND(X30+Y31-MIN(N(Crédits!$E$7),X30+Y31),2) -> 240.67 | Y31: =X30*N(Crédits!$D$7)/12 -> 1.8326487 | Z31: =AE30 -> 0 | AA31: =Z31*N(Crédits!$D$8)/12 -> 0 | AB31: =MIN(N(Crédits!$E$8),Z31+AA31) -> 0 | AC31: =ROUND(Z31+AA31-AB31,2) -> 0 | AD31: =IF(Crédits!$K$8="",0,MAX(0,MIN(AC31,Plan!$L$33-(IF(Crédits!$K$5="",0,IF(Crédits!$K$5<Crédits!$K$8,E31,0))+IF(Crédits!$K$6="",0,IF(Crédits!$K$6<Crédits!$K$8,M31,0))+IF(Crédits!$K$7="",0,IF(Crédits!$K$7<Crédits!$K$8,U31,0))+IF(Crédits!$K$9="",0,IF(Crédits!$K$9<Crédits!$K$8,AK31,0))+IF(Crédits!$K$10="",0,IF(Crédits!$K$10<Crédits!$K$8,AS31,0)))))) -> 0 | AE31: =ROUND(AC31-AD31,2) -> 0 | AF31: =ROUND(AF30+AG31-MIN(N(Crédits!$E$8),AF30+AG31),2) -> 0 | AG31: =AF30*N(Crédits!$D$8)/12 -> 0 | AH31: =AM30 -> 0 | AI31: =AH31*N(Crédits!$D$9)/12 -> 0 | AJ31: =MIN(N(Crédits!$E$9),AH31+AI31) -> 0 | AK31: =ROUND(AH31+AI31-AJ31,2) -> 0 | AL31: =IF(Crédits!$K$9="",0,MAX(0,MIN(AK31,Plan!$L$33-(IF(Crédits!$K$5="",0,IF(Crédits!$K$5<Crédits!$K$9,E31,0))+IF(Crédits!$K$6="",0,IF(Crédits!$K$6<Crédits!$K$9,M31,0))+IF(Crédits!$K$7="",0,IF(Crédits!$K$7<Crédits!$K$9,U31,0))+IF(Crédits!$K$8="",0,IF(Crédits!$K$8<Crédits!$K$9,AC31,0))+IF(Crédits!$K$10="",0,IF(Crédits!$K$10<Crédits!$K$9,AS31,0)))))) -> 0 | AM31: =ROUND(AK31-AL31,2) -> 0 | AN31: =ROUND(AN30+AO31-MIN(N(Crédits!$E$9),AN30+AO31),2) -> 0 | AO31: =AN30*N(Crédits!$D$9)/12 -> 0 | AP31: =AU30 -> 0 | AQ31: =AP31*N(Crédits!$D$10)/12 -> 0 | AR31: =MIN(N(Crédits!$E$10),AP31+AQ31) -> 0 | AS31: =ROUND(AP31+AQ31-AR31,2) -> 0 | AT31: =IF(Crédits!$K$10="",0,MAX(0,MIN(AS31,Plan!$L$33-(IF(Crédits!$K$5="",0,IF(Crédits!$K$5<Crédits!$K$10,E31,0))+IF(Crédits!$K$6="",0,IF(Crédits!$K$6<Crédits!$K$10,M31,0))+IF(Crédits!$K$7="",0,IF(Crédits!$K$7<Crédits!$K$10,U31,0))+IF(Crédits!$K$8="",0,IF(Crédits!$K$8<Crédits!$K$10,AC31,0))+IF(Crédits!$K$9="",0,IF(Crédits!$K$9<Crédits!$K$10,AK31,0)))))) -> 0 | AU31: =ROUND(AS31-AT31,2) -> 0 | AV31: =ROUND(AV30+AW31-MIN(N(Crédits!$E$10),AV30+AW31),2) -> 0 | AW31: =AV30*N(Crédits!$D$10)/12 -> 0 | AX31: =D31+L31+T31+AB31+AJ31+AR31 -> 0 | AY31: =F31+N31+V31+AD31+AL31+AT31 -> 0 | AZ31: =G31+O31+W31+AE31+AM31+AU31 -> 0 | BA31: =C31+K31+S31+AA31+AI31+AQ31 -> 0 | BB31: =I31+Q31+Y31+AG31+AO31+AW31 -> 15.104083
A32: 30 | B32: =G31 -> 0 | C32: =B32*N(Crédits!$D$5)/12 -> 0 | D32: =MIN(N(Crédits!$E$5),B32+C32) -> 0 | E32: =ROUND(B32+C32-D32,2) -> 0 | F32: =IF(Crédits!$K$5="",0,MAX(0,MIN(E32,Plan!$L$34-(IF(Crédits!$K$6="",0,IF(Crédits!$K$6<Crédits!$K$5,M32,0))+IF(Crédits!$K$7="",0,IF(Crédits!$K$7<Crédits!$K$5,U32,0))+IF(Crédits!$K$8="",0,IF(Crédits!$K$8<Crédits!$K$5,AC32,0))+IF(Crédits!$K$9="",0,IF(Crédits!$K$9<Crédits!$K$5,AK32,0))+IF(Crédits!$K$10="",0,IF(Crédits!$K$10<Crédits!$K$5,AS32,0)))))) -> 0 | G32: =ROUND(E32-F32,2) -> 0 | H32: =ROUND(H31+I32-MIN(N(Crédits!$E$5),H31+I32),2) -> 1454.5 | I32: =H31*N(Crédits!$D$5)/12 -> 6.9126342 | J32: =O31 -> 0 | K32: =J32*N(Crédits!$D$6)/12 -> 0 | L32: =MIN(N(Crédits!$E$6),J32+K32) -> 0 | M32: =ROUND(J32+K32-L32,2) -> 0 | N32: =IF(Crédits!$K$6="",0,MAX(0,MIN(M32,Plan!$L$34-(IF(Crédits!$K$5="",0,IF(Crédits!$K$5<Crédits!$K$6,E32,0))+IF(Crédits!$K$7="",0,IF(Crédits!$K$7<Crédits!$K$6,U32,0))+IF(Crédits!$K$8="",0,IF(Crédits!$K$8<Crédits!$K$6,AC32,0))+IF(Crédits!$K$9="",0,IF(Crédits!$K$9<Crédits!$K$6,AK32,0))+IF(Crédits!$K$10="",0,IF(Crédits!$K$10<Crédits!$K$6,AS32,0)))))) -> 0 | O32: =ROUND(M32-N32,2) -> 0 | P32: =ROUND(P31+Q32-MIN(N(Crédits!$E$6),P31+Q32),2) -> 207.1 | Q32: =P31*N(Crédits!$D$6)/12 -> 4.3339275 | R32: =W31 -> 0 | S32: =R32*N(Crédits!$D$7)/12 -> 0 | T32: =MIN(N(Crédits!$E$7),R32+S32) -> 0 | U32: =ROUND(R32+S32-T32,2) -> 0 | V32: =IF(Crédits!$K$7="",0,MAX(0,MIN(U32,Plan!$L$34-(IF(Crédits!$K$5="",0,IF(Crédits!$K$5<Crédits!$K$7,E32,0))+IF(Crédits!$K$6="",0,IF(Crédits!$K$6<Crédits!$K$7,M32,0))+IF(Crédits!$K$8="",0,IF(Crédits!$K$8<Crédits!$K$7,AC32,0))+IF(Crédits!$K$9="",0,IF(Crédits!$K$9<Crédits!$K$7,AK32,0))+IF(Crédits!$K$10="",0,IF(Crédits!$K$10<Crédits!$K$7,AS32,0)))))) -> 0 | W32: =ROUND(U32-V32,2) -> 0 | X32: =ROUND(X31+Y32-MIN(N(Crédits!$E$7),X31+Y32),2) -> 123.15 | Y32: =X31*N(Crédits!$D$7)/12 -> 1.2334337 | Z32: =AE31 -> 0 | AA32: =Z32*N(Crédits!$D$8)/12 -> 0 | AB32: =MIN(N(Crédits!$E$8),Z32+AA32) -> 0 | AC32: =ROUND(Z32+AA32-AB32,2) -> 0 | AD32: =IF(Crédits!$K$8="",0,MAX(0,MIN(AC32,Plan!$L$34-(IF(Crédits!$K$5="",0,IF(Crédits!$K$5<Crédits!$K$8,E32,0))+IF(Crédits!$K$6="",0,IF(Crédits!$K$6<Crédits!$K$8,M32,0))+IF(Crédits!$K$7="",0,IF(Crédits!$K$7<Crédits!$K$8,U32,0))+IF(Crédits!$K$9="",0,IF(Crédits!$K$9<Crédits!$K$8,AK32,0))+IF(Crédits!$K$10="",0,IF(Crédits!$K$10<Crédits!$K$8,AS32,0)))))) -> 0 | AE32: =ROUND(AC32-AD32,2) -> 0 | AF32: =ROUND(AF31+AG32-MIN(N(Crédits!$E$8),AF31+AG32),2) -> 0 | AG32: =AF31*N(Crédits!$D$8)/12 -> 0 | AH32: =AM31 -> 0 | AI32: =AH32*N(Crédits!$D$9)/12 -> 0 | AJ32: =MIN(N(Crédits!$E$9),AH32+AI32) -> 0 | AK32: =ROUND(AH32+AI32-AJ32,2) -> 0 | AL32: =IF(Crédits!$K$9="",0,MAX(0,MIN(AK32,Plan!$L$34-(IF(Crédits!$K$5="",0,IF(Crédits!$K$5<Crédits!$K$9,E32,0))+IF(Crédits!$K$6="",0,IF(Crédits!$K$6<Crédits!$K$9,M32,0))+IF(Crédits!$K$7="",0,IF(Crédits!$K$7<Crédits!$K$9,U32,0))+IF(Crédits!$K$8="",0,IF(Crédits!$K$8<Crédits!$K$9,AC32,0))+IF(Crédits!$K$10="",0,IF(Crédits!$K$10<Crédits!$K$9,AS32,0)))))) -> 0 | AM32: =ROUND(AK32-AL32,2) -> 0 | AN32: =ROUND(AN31+AO32-MIN(N(Crédits!$E$9),AN31+AO32),2) -> 0 | AO32: =AN31*N(Crédits!$D$9)/12 -> 0 | AP32: =AU31 -> 0 | AQ32: =AP32*N(Crédits!$D$10)/12 -> 0 | AR32: =MIN(N(Crédits!$E$10),AP32+AQ32) -> 0 | AS32: =ROUND(AP32+AQ32-AR32,2) -> 0 | AT32: =IF(Crédits!$K$10="",0,MAX(0,MIN(AS32,Plan!$L$34-(IF(Crédits!$K$5="",0,IF(Crédits!$K$5<Crédits!$K$10,E32,0))+IF(Crédits!$K$6="",0,IF(Crédits!$K$6<Crédits!$K$10,M32,0))+IF(Crédits!$K$7="",0,IF(Crédits!$K$7<Crédits!$K$10,U32,0))+IF(Crédits!$K$8="",0,IF(Crédits!$K$8<Crédits!$K$10,AC32,0))+IF(Crédits!$K$9="",0,IF(Crédits!$K$9<Crédits!$K$10,AK32,0)))))) -> 0 | AU32: =ROUND(AS32-AT32,2) -> 0 | AV32: =ROUND(AV31+AW32-MIN(N(Crédits!$E$10),AV31+AW32),2) -> 0 | AW32: =AV31*N(Crédits!$D$10)/12 -> 0 | AX32: =D32+L32+T32+AB32+AJ32+AR32 -> 0 | AY32: =F32+N32+V32+AD32+AL32+AT32 -> 0 | AZ32: =G32+O32+W32+AE32+AM32+AU32 -> 0 | BA32: =C32+K32+S32+AA32+AI32+AQ32 -> 0 | BB32: =I32+Q32+Y32+AG32+AO32+AW32 -> 12.479995
A33: 31 | B33: =G32 -> 0 | C33: =B33*N(Crédits!$D$5)/12 -> 0 | D33: =MIN(N(Crédits!$E$5),B33+C33) -> 0 | E33: =ROUND(B33+C33-D33,2) -> 0 | F33: =IF(Crédits!$K$5="",0,MAX(0,MIN(E33,Plan!$L$35-(IF(Crédits!$K$6="",0,IF(Crédits!$K$6<Crédits!$K$5,M33,0))+IF(Crédits!$K$7="",0,IF(Crédits!$K$7<Crédits!$K$5,U33,0))+IF(Crédits!$K$8="",0,IF(Crédits!$K$8<Crédits!$K$5,AC33,0))+IF(Crédits!$K$9="",0,IF(Crédits!$K$9<Crédits!$K$5,AK33,0))+IF(Crédits!$K$10="",0,IF(Crédits!$K$10<Crédits!$K$5,AS33,0)))))) -> 0 | G33: =ROUND(E33-F33,2) -> 0 | H33: =ROUND(H32+I33-MIN(N(Crédits!$E$5),H32+I33),2) -> 1215.14 | I33: =H32*N(Crédits!$D$5)/12 -> 5.9392083 | J33: =O32 -> 0 | K33: =J33*N(Crédits!$D$6)/12 -> 0 | L33: =MIN(N(Crédits!$E$6),J33+K33) -> 0 | M33: =ROUND(J33+K33-L33,2) -> 0 | N33: =IF(Crédits!$K$6="",0,MAX(0,MIN(M33,Plan!$L$35-(IF(Crédits!$K$5="",0,IF(Crédits!$K$5<Crédits!$K$6,E33,0))+IF(Crédits!$K$7="",0,IF(Crédits!$K$7<Crédits!$K$6,U33,0))+IF(Crédits!$K$8="",0,IF(Crédits!$K$8<Crédits!$K$6,AC33,0))+IF(Crédits!$K$9="",0,IF(Crédits!$K$9<Crédits!$K$6,AK33,0))+IF(Crédits!$K$10="",0,IF(Crédits!$K$10<Crédits!$K$6,AS33,0)))))) -> 0 | O33: =ROUND(M33-N33,2) -> 0 | P33: =ROUND(P32+Q33-MIN(N(Crédits!$E$6),P32+Q33),2) -> 137.96 | Q33: =P32*N(Crédits!$D$6)/12 -> 3.261825 | R33: =W32 -> 0 | S33: =R33*N(Crédits!$D$7)/12 -> 0 | T33: =MIN(N(Crédits!$E$7),R33+S33) -> 0 | U33: =ROUND(R33+S33-T33,2) -> 0 | V33: =IF(Crédits!$K$7="",0,MAX(0,MIN(U33,Plan!$L$35-(IF(Crédits!$K$5="",0,IF(Crédits!$K$5<Crédits!$K$7,E33,0))+IF(Crédits!$K$6="",0,IF(Crédits!$K$6<Crédits!$K$7,M33,0))+IF(Crédits!$K$8="",0,IF(Crédits!$K$8<Crédits!$K$7,AC33,0))+IF(Crédits!$K$9="",0,IF(Crédits!$K$9<Crédits!$K$7,AK33,0))+IF(Crédits!$K$10="",0,IF(Crédits!$K$10<Crédits!$K$7,AS33,0)))))) -> 0 | W33: =ROUND(U33-V33,2) -> 0 | X33: =ROUND(X32+Y33-MIN(N(Crédits!$E$7),X32+Y33),2) -> 5.03 | Y33: =X32*N(Crédits!$D$7)/12 -> 0.63114375 | Z33: =AE32 -> 0 | AA33: =Z33*N(Crédits!$D$8)/12 -> 0 | AB33: =MIN(N(Crédits!$E$8),Z33+AA33) -> 0 | AC33: =ROUND(Z33+AA33-AB33,2) -> 0 | AD33: =IF(Crédits!$K$8="",0,MAX(0,MIN(AC33,Plan!$L$35-(IF(Crédits!$K$5="",0,IF(Crédits!$K$5<Crédits!$K$8,E33,0))+IF(Crédits!$K$6="",0,IF(Crédits!$K$6<Crédits!$K$8,M33,0))+IF(Crédits!$K$7="",0,IF(Crédits!$K$7<Crédits!$K$8,U33,0))+IF(Crédits!$K$9="",0,IF(Crédits!$K$9<Crédits!$K$8,AK33,0))+IF(Crédits!$K$10="",0,IF(Crédits!$K$10<Crédits!$K$8,AS33,0)))))) -> 0 | AE33: =ROUND(AC33-AD33,2) -> 0 | AF33: =ROUND(AF32+AG33-MIN(N(Crédits!$E$8),AF32+AG33),2) -> 0 | AG33: =AF32*N(Crédits!$D$8)/12 -> 0 | AH33: =AM32 -> 0 | AI33: =AH33*N(Crédits!$D$9)/12 -> 0 | AJ33: =MIN(N(Crédits!$E$9),AH33+AI33) -> 0 | AK33: =ROUND(AH33+AI33-AJ33,2) -> 0 | AL33: =IF(Crédits!$K$9="",0,MAX(0,MIN(AK33,Plan!$L$35-(IF(Crédits!$K$5="",0,IF(Crédits!$K$5<Crédits!$K$9,E33,0))+IF(Crédits!$K$6="",0,IF(Crédits!$K$6<Crédits!$K$9,M33,0))+IF(Crédits!$K$7="",0,IF(Crédits!$K$7<Crédits!$K$9,U33,0))+IF(Crédits!$K$8="",0,IF(Crédits!$K$8<Crédits!$K$9,AC33,0))+IF(Crédits!$K$10="",0,IF(Crédits!$K$10<Crédits!$K$9,AS33,0)))))) -> 0 | AM33: =ROUND(AK33-AL33,2) -> 0 | AN33: =ROUND(AN32+AO33-MIN(N(Crédits!$E$9),AN32+AO33),2) -> 0 | AO33: =AN32*N(Crédits!$D$9)/12 -> 0 | AP33: =AU32 -> 0 | AQ33: =AP33*N(Crédits!$D$10)/12 -> 0 | AR33: =MIN(N(Crédits!$E$10),AP33+AQ33) -> 0 | AS33: =ROUND(AP33+AQ33-AR33,2) -> 0 | AT33: =IF(Crédits!$K$10="",0,MAX(0,MIN(AS33,Plan!$L$35-(IF(Crédits!$K$5="",0,IF(Crédits!$K$5<Crédits!$K$10,E33,0))+IF(Crédits!$K$6="",0,IF(Crédits!$K$6<Crédits!$K$10,M33,0))+IF(Crédits!$K$7="",0,IF(Crédits!$K$7<Crédits!$K$10,U33,0))+IF(Crédits!$K$8="",0,IF(Crédits!$K$8<Crédits!$K$10,AC33,0))+IF(Crédits!$K$9="",0,IF(Crédits!$K$9<Crédits!$K$10,AK33,0)))))) -> 0 | AU33: =ROUND(AS33-AT33,2) -> 0 | AV33: =ROUND(AV32+AW33-MIN(N(Crédits!$E$10),AV32+AW33),2) -> 0 | AW33: =AV32*N(Crédits!$D$10)/12 -> 0 | AX33: =D33+L33+T33+AB33+AJ33+AR33 -> 0 | AY33: =F33+N33+V33+AD33+AL33+AT33 -> 0 | AZ33: =G33+O33+W33+AE33+AM33+AU33 -> 0 | BA33: =C33+K33+S33+AA33+AI33+AQ33 -> 0 | BB33: =I33+Q33+Y33+AG33+AO33+AW33 -> 9.8321771
A34: 32 | B34: =G33 -> 0 | C34: =B34*N(Crédits!$D$5)/12 -> 0 | D34: =MIN(N(Crédits!$E$5),B34+C34) -> 0 | E34: =ROUND(B34+C34-D34,2) -> 0 | F34: =IF(Crédits!$K$5="",0,MAX(0,MIN(E34,Plan!$L$36-(IF(Crédits!$K$6="",0,IF(Crédits!$K$6<Crédits!$K$5,M34,0))+IF(Crédits!$K$7="",0,IF(Crédits!$K$7<Crédits!$K$5,U34,0))+IF(Crédits!$K$8="",0,IF(Crédits!$K$8<Crédits!$K$5,AC34,0))+IF(Crédits!$K$9="",0,IF(Crédits!$K$9<Crédits!$K$5,AK34,0))+IF(Crédits!$K$10="",0,IF(Crédits!$K$10<Crédits!$K$5,AS34,0)))))) -> 0 | G34: =ROUND(E34-F34,2) -> 0 | H34: =ROUND(H33+I34-MIN(N(Crédits!$E$5),H33+I34),2) -> 974.8 | I34: =H33*N(Crédits!$D$5)/12 -> 4.9618217 | J34: =O33 -> 0 | K34: =J34*N(Crédits!$D$6)/12 -> 0 | L34: =MIN(N(Crédits!$E$6),J34+K34) -> 0 | M34: =ROUND(J34+K34-L34,2) -> 0 | N34: =IF(Crédits!$K$6="",0,MAX(0,MIN(M34,Plan!$L$36-(IF(Crédits!$K$5="",0,IF(Crédits!$K$5<Crédits!$K$6,E34,0))+IF(Crédits!$K$7="",0,IF(Crédits!$K$7<Crédits!$K$6,U34,0))+IF(Crédits!$K$8="",0,IF(Crédits!$K$8<Crédits!$K$6,AC34,0))+IF(Crédits!$K$9="",0,IF(Crédits!$K$9<Crédits!$K$6,AK34,0))+IF(Crédits!$K$10="",0,IF(Crédits!$K$10<Crédits!$K$6,AS34,0)))))) -> 0 | O34: =ROUND(M34-N34,2) -> 0 | P34: =ROUND(P33+Q34-MIN(N(Crédits!$E$6),P33+Q34),2) -> 67.73 | Q34: =P33*N(Crédits!$D$6)/12 -> 2.17287 | R34: =W33 -> 0 | S34: =R34*N(Crédits!$D$7)/12 -> 0 | T34: =MIN(N(Crédits!$E$7),R34+S34) -> 0 | U34: =ROUND(R34+S34-T34,2) -> 0 | V34: =IF(Crédits!$K$7="",0,MAX(0,MIN(U34,Plan!$L$36-(IF(Crédits!$K$5="",0,IF(Crédits!$K$5<Crédits!$K$7,E34,0))+IF(Crédits!$K$6="",0,IF(Crédits!$K$6<Crédits!$K$7,M34,0))+IF(Crédits!$K$8="",0,IF(Crédits!$K$8<Crédits!$K$7,AC34,0))+IF(Crédits!$K$9="",0,IF(Crédits!$K$9<Crédits!$K$7,AK34,0))+IF(Crédits!$K$10="",0,IF(Crédits!$K$10<Crédits!$K$7,AS34,0)))))) -> 0 | W34: =ROUND(U34-V34,2) -> 0 | X34: =ROUND(X33+Y34-MIN(N(Crédits!$E$7),X33+Y34),2) -> 0 | Y34: =X33*N(Crédits!$D$7)/12 -> 0.02577875 | Z34: =AE33 -> 0 | AA34: =Z34*N(Crédits!$D$8)/12 -> 0 | AB34: =MIN(N(Crédits!$E$8),Z34+AA34) -> 0 | AC34: =ROUND(Z34+AA34-AB34,2) -> 0 | AD34: =IF(Crédits!$K$8="",0,MAX(0,MIN(AC34,Plan!$L$36-(IF(Crédits!$K$5="",0,IF(Crédits!$K$5<Crédits!$K$8,E34,0))+IF(Crédits!$K$6="",0,IF(Crédits!$K$6<Crédits!$K$8,M34,0))+IF(Crédits!$K$7="",0,IF(Crédits!$K$7<Crédits!$K$8,U34,0))+IF(Crédits!$K$9="",0,IF(Crédits!$K$9<Crédits!$K$8,AK34,0))+IF(Crédits!$K$10="",0,IF(Crédits!$K$10<Crédits!$K$8,AS34,0)))))) -> 0 | AE34: =ROUND(AC34-AD34,2) -> 0 | AF34: =ROUND(AF33+AG34-MIN(N(Crédits!$E$8),AF33+AG34),2) -> 0 | AG34: =AF33*N(Crédits!$D$8)/12 -> 0 | AH34: =AM33 -> 0 | AI34: =AH34*N(Crédits!$D$9)/12 -> 0 | AJ34: =MIN(N(Crédits!$E$9),AH34+AI34) -> 0 | AK34: =ROUND(AH34+AI34-AJ34,2) -> 0 | AL34: =IF(Crédits!$K$9="",0,MAX(0,MIN(AK34,Plan!$L$36-(IF(Crédits!$K$5="",0,IF(Crédits!$K$5<Crédits!$K$9,E34,0))+IF(Crédits!$K$6="",0,IF(Crédits!$K$6<Crédits!$K$9,M34,0))+IF(Crédits!$K$7="",0,IF(Crédits!$K$7<Crédits!$K$9,U34,0))+IF(Crédits!$K$8="",0,IF(Crédits!$K$8<Crédits!$K$9,AC34,0))+IF(Crédits!$K$10="",0,IF(Crédits!$K$10<Crédits!$K$9,AS34,0)))))) -> 0 | AM34: =ROUND(AK34-AL34,2) -> 0 | AN34: =ROUND(AN33+AO34-MIN(N(Crédits!$E$9),AN33+AO34),2) -> 0 | AO34: =AN33*N(Crédits!$D$9)/12 -> 0 | AP34: =AU33 -> 0 | AQ34: =AP34*N(Crédits!$D$10)/12 -> 0 | AR34: =MIN(N(Crédits!$E$10),AP34+AQ34) -> 0 | AS34: =ROUND(AP34+AQ34-AR34,2) -> 0 | AT34: =IF(Crédits!$K$10="",0,MAX(0,MIN(AS34,Plan!$L$36-(IF(Crédits!$K$5="",0,IF(Crédits!$K$5<Crédits!$K$10,E34,0))+IF(Crédits!$K$6="",0,IF(Crédits!$K$6<Crédits!$K$10,M34,0))+IF(Crédits!$K$7="",0,IF(Crédits!$K$7<Crédits!$K$10,U34,0))+IF(Crédits!$K$8="",0,IF(Crédits!$K$8<Crédits!$K$10,AC34,0))+IF(Crédits!$K$9="",0,IF(Crédits!$K$9<Crédits!$K$10,AK34,0)))))) -> 0 | AU34: =ROUND(AS34-AT34,2) -> 0 | AV34: =ROUND(AV33+AW34-MIN(N(Crédits!$E$10),AV33+AW34),2) -> 0 | AW34: =AV33*N(Crédits!$D$10)/12 -> 0 | AX34: =D34+L34+T34+AB34+AJ34+AR34 -> 0 | AY34: =F34+N34+V34+AD34+AL34+AT34 -> 0 | AZ34: =G34+O34+W34+AE34+AM34+AU34 -> 0 | BA34: =C34+K34+S34+AA34+AI34+AQ34 -> 0 | BB34: =I34+Q34+Y34+AG34+AO34+AW34 -> 7.1604704
A35: 33 | B35: =G34 -> 0 | C35: =B35*N(Crédits!$D$5)/12 -> 0 | D35: =MIN(N(Crédits!$E$5),B35+C35) -> 0 | E35: =ROUND(B35+C35-D35,2) -> 0 | F35: =IF(Crédits!$K$5="",0,MAX(0,MIN(E35,Plan!$L$37-(IF(Crédits!$K$6="",0,IF(Crédits!$K$6<Crédits!$K$5,M35,0))+IF(Crédits!$K$7="",0,IF(Crédits!$K$7<Crédits!$K$5,U35,0))+IF(Crédits!$K$8="",0,IF(Crédits!$K$8<Crédits!$K$5,AC35,0))+IF(Crédits!$K$9="",0,IF(Crédits!$K$9<Crédits!$K$5,AK35,0))+IF(Crédits!$K$10="",0,IF(Crédits!$K$10<Crédits!$K$5,AS35,0)))))) -> 0 | G35: =ROUND(E35-F35,2) -> 0 | H35: =ROUND(H34+I35-MIN(N(Crédits!$E$5),H34+I35),2) -> 733.48 | I35: =H34*N(Crédits!$D$5)/12 -> 3.9804333 | J35: =O34 -> 0 | K35: =J35*N(Crédits!$D$6)/12 -> 0 | L35: =MIN(N(Crédits!$E$6),J35+K35) -> 0 | M35: =ROUND(J35+K35-L35,2) -> 0 | N35: =IF(Crédits!$K$6="",0,MAX(0,MIN(M35,Plan!$L$37-(IF(Crédits!$K$5="",0,IF(Crédits!$K$5<Crédits!$K$6,E35,0))+IF(Crédits!$K$7="",0,IF(Crédits!$K$7<Crédits!$K$6,U35,0))+IF(Crédits!$K$8="",0,IF(Crédits!$K$8<Crédits!$K$6,AC35,0))+IF(Crédits!$K$9="",0,IF(Crédits!$K$9<Crédits!$K$6,AK35,0))+IF(Crédits!$K$10="",0,IF(Crédits!$K$10<Crédits!$K$6,AS35,0)))))) -> 0 | O35: =ROUND(M35-N35,2) -> 0 | P35: =ROUND(P34+Q35-MIN(N(Crédits!$E$6),P34+Q35),2) -> 0 | Q35: =P34*N(Crédits!$D$6)/12 -> 1.0667475 | R35: =W34 -> 0 | S35: =R35*N(Crédits!$D$7)/12 -> 0 | T35: =MIN(N(Crédits!$E$7),R35+S35) -> 0 | U35: =ROUND(R35+S35-T35,2) -> 0 | V35: =IF(Crédits!$K$7="",0,MAX(0,MIN(U35,Plan!$L$37-(IF(Crédits!$K$5="",0,IF(Crédits!$K$5<Crédits!$K$7,E35,0))+IF(Crédits!$K$6="",0,IF(Crédits!$K$6<Crédits!$K$7,M35,0))+IF(Crédits!$K$8="",0,IF(Crédits!$K$8<Crédits!$K$7,AC35,0))+IF(Crédits!$K$9="",0,IF(Crédits!$K$9<Crédits!$K$7,AK35,0))+IF(Crédits!$K$10="",0,IF(Crédits!$K$10<Crédits!$K$7,AS35,0)))))) -> 0 | W35: =ROUND(U35-V35,2) -> 0 | X35: =ROUND(X34+Y35-MIN(N(Crédits!$E$7),X34+Y35),2) -> 0 | Y35: =X34*N(Crédits!$D$7)/12 -> 0 | Z35: =AE34 -> 0 | AA35: =Z35*N(Crédits!$D$8)/12 -> 0 | AB35: =MIN(N(Crédits!$E$8),Z35+AA35) -> 0 | AC35: =ROUND(Z35+AA35-AB35,2) -> 0 | AD35: =IF(Crédits!$K$8="",0,MAX(0,MIN(AC35,Plan!$L$37-(IF(Crédits!$K$5="",0,IF(Crédits!$K$5<Crédits!$K$8,E35,0))+IF(Crédits!$K$6="",0,IF(Crédits!$K$6<Crédits!$K$8,M35,0))+IF(Crédits!$K$7="",0,IF(Crédits!$K$7<Crédits!$K$8,U35,0))+IF(Crédits!$K$9="",0,IF(Crédits!$K$9<Crédits!$K$8,AK35,0))+IF(Crédits!$K$10="",0,IF(Crédits!$K$10<Crédits!$K$8,AS35,0)))))) -> 0 | AE35: =ROUND(AC35-AD35,2) -> 0 | AF35: =ROUND(AF34+AG35-MIN(N(Crédits!$E$8),AF34+AG35),2) -> 0 | AG35: =AF34*N(Crédits!$D$8)/12 -> 0 | AH35: =AM34 -> 0 | AI35: =AH35*N(Crédits!$D$9)/12 -> 0 | AJ35: =MIN(N(Crédits!$E$9),AH35+AI35) -> 0 | AK35: =ROUND(AH35+AI35-AJ35,2) -> 0 | AL35: =IF(Crédits!$K$9="",0,MAX(0,MIN(AK35,Plan!$L$37-(IF(Crédits!$K$5="",0,IF(Crédits!$K$5<Crédits!$K$9,E35,0))+IF(Crédits!$K$6="",0,IF(Crédits!$K$6<Crédits!$K$9,M35,0))+IF(Crédits!$K$7="",0,IF(Crédits!$K$7<Crédits!$K$9,U35,0))+IF(Crédits!$K$8="",0,IF(Crédits!$K$8<Crédits!$K$9,AC35,0))+IF(Crédits!$K$10="",0,IF(Crédits!$K$10<Crédits!$K$9,AS35,0)))))) -> 0 | AM35: =ROUND(AK35-AL35,2) -> 0 | AN35: =ROUND(AN34+AO35-MIN(N(Crédits!$E$9),AN34+AO35),2) -> 0 | AO35: =AN34*N(Crédits!$D$9)/12 -> 0 | AP35: =AU34 -> 0 | AQ35: =AP35*N(Crédits!$D$10)/12 -> 0 | AR35: =MIN(N(Crédits!$E$10),AP35+AQ35) -> 0 | AS35: =ROUND(AP35+AQ35-AR35,2) -> 0 | AT35: =IF(Crédits!$K$10="",0,MAX(0,MIN(AS35,Plan!$L$37-(IF(Crédits!$K$5="",0,IF(Crédits!$K$5<Crédits!$K$10,E35,0))+IF(Crédits!$K$6="",0,IF(Crédits!$K$6<Crédits!$K$10,M35,0))+IF(Crédits!$K$7="",0,IF(Crédits!$K$7<Crédits!$K$10,U35,0))+IF(Crédits!$K$8="",0,IF(Crédits!$K$8<Crédits!$K$10,AC35,0))+IF(Crédits!$K$9="",0,IF(Crédits!$K$9<Crédits!$K$10,AK35,0)))))) -> 0 | AU35: =ROUND(AS35-AT35,2) -> 0 | AV35: =ROUND(AV34+AW35-MIN(N(Crédits!$E$10),AV34+AW35),2) -> 0 | AW35: =AV34*N(Crédits!$D$10)/12 -> 0 | AX35: =D35+L35+T35+AB35+AJ35+AR35 -> 0 | AY35: =F35+N35+V35+AD35+AL35+AT35 -> 0 | AZ35: =G35+O35+W35+AE35+AM35+AU35 -> 0 | BA35: =C35+K35+S35+AA35+AI35+AQ35 -> 0 | BB35: =I35+Q35+Y35+AG35+AO35+AW35 -> 5.0471808
A36: 34 | B36: =G35 -> 0 | C36: =B36*N(Crédits!$D$5)/12 -> 0 | D36: =MIN(N(Crédits!$E$5),B36+C36) -> 0 | E36: =ROUND(B36+C36-D36,2) -> 0 | F36: =IF(Crédits!$K$5="",0,MAX(0,MIN(E36,Plan!$L$38-(IF(Crédits!$K$6="",0,IF(Crédits!$K$6<Crédits!$K$5,M36,0))+IF(Crédits!$K$7="",0,IF(Crédits!$K$7<Crédits!$K$5,U36,0))+IF(Crédits!$K$8="",0,IF(Crédits!$K$8<Crédits!$K$5,AC36,0))+IF(Crédits!$K$9="",0,IF(Crédits!$K$9<Crédits!$K$5,AK36,0))+IF(Crédits!$K$10="",0,IF(Crédits!$K$10<Crédits!$K$5,AS36,0)))))) -> 0 | G36: =ROUND(E36-F36,2) -> 0 | H36: =ROUND(H35+I36-MIN(N(Crédits!$E$5),H35+I36),2) -> 491.18 | I36: =H35*N(Crédits!$D$5)/12 -> 2.9950433 | J36: =O35 -> 0 | K36: =J36*N(Crédits!$D$6)/12 -> 0 | L36: =MIN(N(Crédits!$E$6),J36+K36) -> 0 | M36: =ROUND(J36+K36-L36,2) -> 0 | N36: =IF(Crédits!$K$6="",0,MAX(0,MIN(M36,Plan!$L$38-(IF(Crédits!$K$5="",0,IF(Crédits!$K$5<Crédits!$K$6,E36,0))+IF(Crédits!$K$7="",0,IF(Crédits!$K$7<Crédits!$K$6,U36,0))+IF(Crédits!$K$8="",0,IF(Crédits!$K$8<Crédits!$K$6,AC36,0))+IF(Crédits!$K$9="",0,IF(Crédits!$K$9<Crédits!$K$6,AK36,0))+IF(Crédits!$K$10="",0,IF(Crédits!$K$10<Crédits!$K$6,AS36,0)))))) -> 0 | O36: =ROUND(M36-N36,2) -> 0 | P36: =ROUND(P35+Q36-MIN(N(Crédits!$E$6),P35+Q36),2) -> 0 | Q36: =P35*N(Crédits!$D$6)/12 -> 0 | R36: =W35 -> 0 | S36: =R36*N(Crédits!$D$7)/12 -> 0 | T36: =MIN(N(Crédits!$E$7),R36+S36) -> 0 | U36: =ROUND(R36+S36-T36,2) -> 0 | V36: =IF(Crédits!$K$7="",0,MAX(0,MIN(U36,Plan!$L$38-(IF(Crédits!$K$5="",0,IF(Crédits!$K$5<Crédits!$K$7,E36,0))+IF(Crédits!$K$6="",0,IF(Crédits!$K$6<Crédits!$K$7,M36,0))+IF(Crédits!$K$8="",0,IF(Crédits!$K$8<Crédits!$K$7,AC36,0))+IF(Crédits!$K$9="",0,IF(Crédits!$K$9<Crédits!$K$7,AK36,0))+IF(Crédits!$K$10="",0,IF(Crédits!$K$10<Crédits!$K$7,AS36,0)))))) -> 0 | W36: =ROUND(U36-V36,2) -> 0 | X36: =ROUND(X35+Y36-MIN(N(Crédits!$E$7),X35+Y36),2) -> 0 | Y36: =X35*N(Crédits!$D$7)/12 -> 0 | Z36: =AE35 -> 0 | AA36: =Z36*N(Crédits!$D$8)/12 -> 0 | AB36: =MIN(N(Crédits!$E$8),Z36+AA36) -> 0 | AC36: =ROUND(Z36+AA36-AB36,2) -> 0 | AD36: =IF(Crédits!$K$8="",0,MAX(0,MIN(AC36,Plan!$L$38-(IF(Crédits!$K$5="",0,IF(Crédits!$K$5<Crédits!$K$8,E36,0))+IF(Crédits!$K$6="",0,IF(Crédits!$K$6<Crédits!$K$8,M36,0))+IF(Crédits!$K$7="",0,IF(Crédits!$K$7<Crédits!$K$8,U36,0))+IF(Crédits!$K$9="",0,IF(Crédits!$K$9<Crédits!$K$8,AK36,0))+IF(Crédits!$K$10="",0,IF(Crédits!$K$10<Crédits!$K$8,AS36,0)))))) -> 0 | AE36: =ROUND(AC36-AD36,2) -> 0 | AF36: =ROUND(AF35+AG36-MIN(N(Crédits!$E$8),AF35+AG36),2) -> 0 | AG36: =AF35*N(Crédits!$D$8)/12 -> 0 | AH36: =AM35 -> 0 | AI36: =AH36*N(Crédits!$D$9)/12 -> 0 | AJ36: =MIN(N(Crédits!$E$9),AH36+AI36) -> 0 | AK36: =ROUND(AH36+AI36-AJ36,2) -> 0 | AL36: =IF(Crédits!$K$9="",0,MAX(0,MIN(AK36,Plan!$L$38-(IF(Crédits!$K$5="",0,IF(Crédits!$K$5<Crédits!$K$9,E36,0))+IF(Crédits!$K$6="",0,IF(Crédits!$K$6<Crédits!$K$9,M36,0))+IF(Crédits!$K$7="",0,IF(Crédits!$K$7<Crédits!$K$9,U36,0))+IF(Crédits!$K$8="",0,IF(Crédits!$K$8<Crédits!$K$9,AC36,0))+IF(Crédits!$K$10="",0,IF(Crédits!$K$10<Crédits!$K$9,AS36,0)))))) -> 0 | AM36: =ROUND(AK36-AL36,2) -> 0 | AN36: =ROUND(AN35+AO36-MIN(N(Crédits!$E$9),AN35+AO36),2) -> 0 | AO36: =AN35*N(Crédits!$D$9)/12 -> 0 | AP36: =AU35 -> 0 | AQ36: =AP36*N(Crédits!$D$10)/12 -> 0 | AR36: =MIN(N(Crédits!$E$10),AP36+AQ36) -> 0 | AS36: =ROUND(AP36+AQ36-AR36,2) -> 0 | AT36: =IF(Crédits!$K$10="",0,MAX(0,MIN(AS36,Plan!$L$38-(IF(Crédits!$K$5="",0,IF(Crédits!$K$5<Crédits!$K$10,E36,0))+IF(Crédits!$K$6="",0,IF(Crédits!$K$6<Crédits!$K$10,M36,0))+IF(Crédits!$K$7="",0,IF(Crédits!$K$7<Crédits!$K$10,U36,0))+IF(Crédits!$K$8="",0,IF(Crédits!$K$8<Crédits!$K$10,AC36,0))+IF(Crédits!$K$9="",0,IF(Crédits!$K$9<Crédits!$K$10,AK36,0)))))) -> 0 | AU36: =ROUND(AS36-AT36,2) -> 0 | AV36: =ROUND(AV35+AW36-MIN(N(Crédits!$E$10),AV35+AW36),2) -> 0 | AW36: =AV35*N(Crédits!$D$10)/12 -> 0 | AX36: =D36+L36+T36+AB36+AJ36+AR36 -> 0 | AY36: =F36+N36+V36+AD36+AL36+AT36 -> 0 | AZ36: =G36+O36+W36+AE36+AM36+AU36 -> 0 | BA36: =C36+K36+S36+AA36+AI36+AQ36 -> 0 | BB36: =I36+Q36+Y36+AG36+AO36+AW36 -> 2.9950433
A37: 35 | B37: =G36 -> 0 | C37: =B37*N(Crédits!$D$5)/12 -> 0 | D37: =MIN(N(Crédits!$E$5),B37+C37) -> 0 | E37: =ROUND(B37+C37-D37,2) -> 0 | F37: =IF(Crédits!$K$5="",0,MAX(0,MIN(E37,Plan!$L$39-(IF(Crédits!$K$6="",0,IF(Crédits!$K$6<Crédits!$K$5,M37,0))+IF(Crédits!$K$7="",0,IF(Crédits!$K$7<Crédits!$K$5,U37,0))+IF(Crédits!$K$8="",0,IF(Crédits!$K$8<Crédits!$K$5,AC37,0))+IF(Crédits!$K$9="",0,IF(Crédits!$K$9<Crédits!$K$5,AK37,0))+IF(Crédits!$K$10="",0,IF(Crédits!$K$10<Crédits!$K$5,AS37,0)))))) -> 0 | G37: =ROUND(E37-F37,2) -> 0 | H37: =ROUND(H36+I37-MIN(N(Crédits!$E$5),H36+I37),2) -> 247.89 | I37: =H36*N(Crédits!$D$5)/12 -> 2.0056517 | J37: =O36 -> 0 | K37: =J37*N(Crédits!$D$6)/12 -> 0 | L37: =MIN(N(Crédits!$E$6),J37+K37) -> 0 | M37: =ROUND(J37+K37-L37,2) -> 0 | N37: =IF(Crédits!$K$6="",0,MAX(0,MIN(M37,Plan!$L$39-(IF(Crédits!$K$5="",0,IF(Crédits!$K$5<Crédits!$K$6,E37,0))+IF(Crédits!$K$7="",0,IF(Crédits!$K$7<Crédits!$K$6,U37,0))+IF(Crédits!$K$8="",0,IF(Crédits!$K$8<Crédits!$K$6,AC37,0))+IF(Crédits!$K$9="",0,IF(Crédits!$K$9<Crédits!$K$6,AK37,0))+IF(Crédits!$K$10="",0,IF(Crédits!$K$10<Crédits!$K$6,AS37,0)))))) -> 0 | O37: =ROUND(M37-N37,2) -> 0 | P37: =ROUND(P36+Q37-MIN(N(Crédits!$E$6),P36+Q37),2) -> 0 | Q37: =P36*N(Crédits!$D$6)/12 -> 0 | R37: =W36 -> 0 | S37: =R37*N(Crédits!$D$7)/12 -> 0 | T37: =MIN(N(Crédits!$E$7),R37+S37) -> 0 | U37: =ROUND(R37+S37-T37,2) -> 0 | V37: =IF(Crédits!$K$7="",0,MAX(0,MIN(U37,Plan!$L$39-(IF(Crédits!$K$5="",0,IF(Crédits!$K$5<Crédits!$K$7,E37,0))+IF(Crédits!$K$6="",0,IF(Crédits!$K$6<Crédits!$K$7,M37,0))+IF(Crédits!$K$8="",0,IF(Crédits!$K$8<Crédits!$K$7,AC37,0))+IF(Crédits!$K$9="",0,IF(Crédits!$K$9<Crédits!$K$7,AK37,0))+IF(Crédits!$K$10="",0,IF(Crédits!$K$10<Crédits!$K$7,AS37,0)))))) -> 0 | W37: =ROUND(U37-V37,2) -> 0 | X37: =ROUND(X36+Y37-MIN(N(Crédits!$E$7),X36+Y37),2) -> 0 | Y37: =X36*N(Crédits!$D$7)/12 -> 0 | Z37: =AE36 -> 0 | AA37: =Z37*N(Crédits!$D$8)/12 -> 0 | AB37: =MIN(N(Crédits!$E$8),Z37+AA37) -> 0 | AC37: =ROUND(Z37+AA37-AB37,2) -> 0 | AD37: =IF(Crédits!$K$8="",0,MAX(0,MIN(AC37,Plan!$L$39-(IF(Crédits!$K$5="",0,IF(Crédits!$K$5<Crédits!$K$8,E37,0))+IF(Crédits!$K$6="",0,IF(Crédits!$K$6<Crédits!$K$8,M37,0))+IF(Crédits!$K$7="",0,IF(Crédits!$K$7<Crédits!$K$8,U37,0))+IF(Crédits!$K$9="",0,IF(Crédits!$K$9<Crédits!$K$8,AK37,0))+IF(Crédits!$K$10="",0,IF(Crédits!$K$10<Crédits!$K$8,AS37,0)))))) -> 0 | AE37: =ROUND(AC37-AD37,2) -> 0 | AF37: =ROUND(AF36+AG37-MIN(N(Crédits!$E$8),AF36+AG37),2) -> 0 | AG37: =AF36*N(Crédits!$D$8)/12 -> 0 | AH37: =AM36 -> 0 | AI37: =AH37*N(Crédits!$D$9)/12 -> 0 | AJ37: =MIN(N(Crédits!$E$9),AH37+AI37) -> 0 | AK37: =ROUND(AH37+AI37-AJ37,2) -> 0 | AL37: =IF(Crédits!$K$9="",0,MAX(0,MIN(AK37,Plan!$L$39-(IF(Crédits!$K$5="",0,IF(Crédits!$K$5<Crédits!$K$9,E37,0))+IF(Crédits!$K$6="",0,IF(Crédits!$K$6<Crédits!$K$9,M37,0))+IF(Crédits!$K$7="",0,IF(Crédits!$K$7<Crédits!$K$9,U37,0))+IF(Crédits!$K$8="",0,IF(Crédits!$K$8<Crédits!$K$9,AC37,0))+IF(Crédits!$K$10="",0,IF(Crédits!$K$10<Crédits!$K$9,AS37,0)))))) -> 0 | AM37: =ROUND(AK37-AL37,2) -> 0 | AN37: =ROUND(AN36+AO37-MIN(N(Crédits!$E$9),AN36+AO37),2) -> 0 | AO37: =AN36*N(Crédits!$D$9)/12 -> 0 | AP37: =AU36 -> 0 | AQ37: =AP37*N(Crédits!$D$10)/12 -> 0 | AR37: =MIN(N(Crédits!$E$10),AP37+AQ37) -> 0 | AS37: =ROUND(AP37+AQ37-AR37,2) -> 0 | AT37: =IF(Crédits!$K$10="",0,MAX(0,MIN(AS37,Plan!$L$39-(IF(Crédits!$K$5="",0,IF(Crédits!$K$5<Crédits!$K$10,E37,0))+IF(Crédits!$K$6="",0,IF(Crédits!$K$6<Crédits!$K$10,M37,0))+IF(Crédits!$K$7="",0,IF(Crédits!$K$7<Crédits!$K$10,U37,0))+IF(Crédits!$K$8="",0,IF(Crédits!$K$8<Crédits!$K$10,AC37,0))+IF(Crédits!$K$9="",0,IF(Crédits!$K$9<Crédits!$K$10,AK37,0)))))) -> 0 | AU37: =ROUND(AS37-AT37,2) -> 0 | AV37: =ROUND(AV36+AW37-MIN(N(Crédits!$E$10),AV36+AW37),2) -> 0 | AW37: =AV36*N(Crédits!$D$10)/12 -> 0 | AX37: =D37+L37+T37+AB37+AJ37+AR37 -> 0 | AY37: =F37+N37+V37+AD37+AL37+AT37 -> 0 | AZ37: =G37+O37+W37+AE37+AM37+AU37 -> 0 | BA37: =C37+K37+S37+AA37+AI37+AQ37 -> 0 | BB37: =I37+Q37+Y37+AG37+AO37+AW37 -> 2.0056517
A38: 36 | B38: =G37 -> 0 | C38: =B38*N(Crédits!$D$5)/12 -> 0 | D38: =MIN(N(Crédits!$E$5),B38+C38) -> 0 | E38: =ROUND(B38+C38-D38,2) -> 0 | F38: =IF(Crédits!$K$5="",0,MAX(0,MIN(E38,Plan!$L$40-(IF(Crédits!$K$6="",0,IF(Crédits!$K$6<Crédits!$K$5,M38,0))+IF(Crédits!$K$7="",0,IF(Crédits!$K$7<Crédits!$K$5,U38,0))+IF(Crédits!$K$8="",0,IF(Crédits!$K$8<Crédits!$K$5,AC38,0))+IF(Crédits!$K$9="",0,IF(Crédits!$K$9<Crédits!$K$5,AK38,0))+IF(Crédits!$K$10="",0,IF(Crédits!$K$10<Crédits!$K$5,AS38,0)))))) -> 0 | G38: =ROUND(E38-F38,2) -> 0 | H38: =ROUND(H37+I38-MIN(N(Crédits!$E$5),H37+I38),2) -> 3.6 | I38: =H37*N(Crédits!$D$5)/12 -> 1.0122175 | J38: =O37 -> 0 | K38: =J38*N(Crédits!$D$6)/12 -> 0 | L38: =MIN(N(Crédits!$E$6),J38+K38) -> 0 | M38: =ROUND(J38+K38-L38,2) -> 0 | N38: =IF(Crédits!$K$6="",0,MAX(0,MIN(M38,Plan!$L$40-(IF(Crédits!$K$5="",0,IF(Crédits!$K$5<Crédits!$K$6,E38,0))+IF(Crédits!$K$7="",0,IF(Crédits!$K$7<Crédits!$K$6,U38,0))+IF(Crédits!$K$8="",0,IF(Crédits!$K$8<Crédits!$K$6,AC38,0))+IF(Crédits!$K$9="",0,IF(Crédits!$K$9<Crédits!$K$6,AK38,0))+IF(Crédits!$K$10="",0,IF(Crédits!$K$10<Crédits!$K$6,AS38,0)))))) -> 0 | O38: =ROUND(M38-N38,2) -> 0 | P38: =ROUND(P37+Q38-MIN(N(Crédits!$E$6),P37+Q38),2) -> 0 | Q38: =P37*N(Crédits!$D$6)/12 -> 0 | R38: =W37 -> 0 | S38: =R38*N(Crédits!$D$7)/12 -> 0 | T38: =MIN(N(Crédits!$E$7),R38+S38) -> 0 | U38: =ROUND(R38+S38-T38,2) -> 0 | V38: =IF(Crédits!$K$7="",0,MAX(0,MIN(U38,Plan!$L$40-(IF(Crédits!$K$5="",0,IF(Crédits!$K$5<Crédits!$K$7,E38,0))+IF(Crédits!$K$6="",0,IF(Crédits!$K$6<Crédits!$K$7,M38,0))+IF(Crédits!$K$8="",0,IF(Crédits!$K$8<Crédits!$K$7,AC38,0))+IF(Crédits!$K$9="",0,IF(Crédits!$K$9<Crédits!$K$7,AK38,0))+IF(Crédits!$K$10="",0,IF(Crédits!$K$10<Crédits!$K$7,AS38,0)))))) -> 0 | W38: =ROUND(U38-V38,2) -> 0 | X38: =ROUND(X37+Y38-MIN(N(Crédits!$E$7),X37+Y38),2) -> 0 | Y38: =X37*N(Crédits!$D$7)/12 -> 0 | Z38: =AE37 -> 0 | AA38: =Z38*N(Crédits!$D$8)/12 -> 0 | AB38: =MIN(N(Crédits!$E$8),Z38+AA38) -> 0 | AC38: =ROUND(Z38+AA38-AB38,2) -> 0 | AD38: =IF(Crédits!$K$8="",0,MAX(0,MIN(AC38,Plan!$L$40-(IF(Crédits!$K$5="",0,IF(Crédits!$K$5<Crédits!$K$8,E38,0))+IF(Crédits!$K$6="",0,IF(Crédits!$K$6<Crédits!$K$8,M38,0))+IF(Crédits!$K$7="",0,IF(Crédits!$K$7<Crédits!$K$8,U38,0))+IF(Crédits!$K$9="",0,IF(Crédits!$K$9<Crédits!$K$8,AK38,0))+IF(Crédits!$K$10="",0,IF(Crédits!$K$10<Crédits!$K$8,AS38,0)))))) -> 0 | AE38: =ROUND(AC38-AD38,2) -> 0 | AF38: =ROUND(AF37+AG38-MIN(N(Crédits!$E$8),AF37+AG38),2) -> 0 | AG38: =AF37*N(Crédits!$D$8)/12 -> 0 | AH38: =AM37 -> 0 | AI38: =AH38*N(Crédits!$D$9)/12 -> 0 | AJ38: =MIN(N(Crédits!$E$9),AH38+AI38) -> 0 | AK38: =ROUND(AH38+AI38-AJ38,2) -> 0 | AL38: =IF(Crédits!$K$9="",0,MAX(0,MIN(AK38,Plan!$L$40-(IF(Crédits!$K$5="",0,IF(Crédits!$K$5<Crédits!$K$9,E38,0))+IF(Crédits!$K$6="",0,IF(Crédits!$K$6<Crédits!$K$9,M38,0))+IF(Crédits!$K$7="",0,IF(Crédits!$K$7<Crédits!$K$9,U38,0))+IF(Crédits!$K$8="",0,IF(Crédits!$K$8<Crédits!$K$9,AC38,0))+IF(Crédits!$K$10="",0,IF(Crédits!$K$10<Crédits!$K$9,AS38,0)))))) -> 0 | AM38: =ROUND(AK38-AL38,2) -> 0 | AN38: =ROUND(AN37+AO38-MIN(N(Crédits!$E$9),AN37+AO38),2) -> 0 | AO38: =AN37*N(Crédits!$D$9)/12 -> 0 | AP38: =AU37 -> 0 | AQ38: =AP38*N(Crédits!$D$10)/12 -> 0 | AR38: =MIN(N(Crédits!$E$10),AP38+AQ38) -> 0 | AS38: =ROUND(AP38+AQ38-AR38,2) -> 0 | AT38: =IF(Crédits!$K$10="",0,MAX(0,MIN(AS38,Plan!$L$40-(IF(Crédits!$K$5="",0,IF(Crédits!$K$5<Crédits!$K$10,E38,0))+IF(Crédits!$K$6="",0,IF(Crédits!$K$6<Crédits!$K$10,M38,0))+IF(Crédits!$K$7="",0,IF(Crédits!$K$7<Crédits!$K$10,U38,0))+IF(Crédits!$K$8="",0,IF(Crédits!$K$8<Crédits!$K$10,AC38,0))+IF(Crédits!$K$9="",0,IF(Crédits!$K$9<Crédits!$K$10,AK38,0)))))) -> 0 | AU38: =ROUND(AS38-AT38,2) -> 0 | AV38: =ROUND(AV37+AW38-MIN(N(Crédits!$E$10),AV37+AW38),2) -> 0 | AW38: =AV37*N(Crédits!$D$10)/12 -> 0 | AX38: =D38+L38+T38+AB38+AJ38+AR38 -> 0 | AY38: =F38+N38+V38+AD38+AL38+AT38 -> 0 | AZ38: =G38+O38+W38+AE38+AM38+AU38 -> 0 | BA38: =C38+K38+S38+AA38+AI38+AQ38 -> 0 | BB38: =I38+Q38+Y38+AG38+AO38+AW38 -> 1.0122175
A39: 37 | B39: =G38 -> 0 | C39: =B39*N(Crédits!$D$5)/12 -> 0 | D39: =MIN(N(Crédits!$E$5),B39+C39) -> 0 | E39: =ROUND(B39+C39-D39,2) -> 0 | F39: =IF(Crédits!$K$5="",0,MAX(0,MIN(E39,Plan!$L$41-(IF(Crédits!$K$6="",0,IF(Crédits!$K$6<Crédits!$K$5,M39,0))+IF(Crédits!$K$7="",0,IF(Crédits!$K$7<Crédits!$K$5,U39,0))+IF(Crédits!$K$8="",0,IF(Crédits!$K$8<Crédits!$K$5,AC39,0))+IF(Crédits!$K$9="",0,IF(Crédits!$K$9<Crédits!$K$5,AK39,0))+IF(Crédits!$K$10="",0,IF(Crédits!$K$10<Crédits!$K$5,AS39,0)))))) -> 0 | G39: =ROUND(E39-F39,2) -> 0 | H39: =ROUND(H38+I39-MIN(N(Crédits!$E$5),H38+I39),2) -> 0 | I39: =H38*N(Crédits!$D$5)/12 -> 0.0147 | J39: =O38 -> 0 | K39: =J39*N(Crédits!$D$6)/12 -> 0 | L39: =MIN(N(Crédits!$E$6),J39+K39) -> 0 | M39: =ROUND(J39+K39-L39,2) -> 0 | N39: =IF(Crédits!$K$6="",0,MAX(0,MIN(M39,Plan!$L$41-(IF(Crédits!$K$5="",0,IF(Crédits!$K$5<Crédits!$K$6,E39,0))+IF(Crédits!$K$7="",0,IF(Crédits!$K$7<Crédits!$K$6,U39,0))+IF(Crédits!$K$8="",0,IF(Crédits!$K$8<Crédits!$K$6,AC39,0))+IF(Crédits!$K$9="",0,IF(Crédits!$K$9<Crédits!$K$6,AK39,0))+IF(Crédits!$K$10="",0,IF(Crédits!$K$10<Crédits!$K$6,AS39,0)))))) -> 0 | O39: =ROUND(M39-N39,2) -> 0 | P39: =ROUND(P38+Q39-MIN(N(Crédits!$E$6),P38+Q39),2) -> 0 | Q39: =P38*N(Crédits!$D$6)/12 -> 0 | R39: =W38 -> 0 | S39: =R39*N(Crédits!$D$7)/12 -> 0 | T39: =MIN(N(Crédits!$E$7),R39+S39) -> 0 | U39: =ROUND(R39+S39-T39,2) -> 0 | V39: =IF(Crédits!$K$7="",0,MAX(0,MIN(U39,Plan!$L$41-(IF(Crédits!$K$5="",0,IF(Crédits!$K$5<Crédits!$K$7,E39,0))+IF(Crédits!$K$6="",0,IF(Crédits!$K$6<Crédits!$K$7,M39,0))+IF(Crédits!$K$8="",0,IF(Crédits!$K$8<Crédits!$K$7,AC39,0))+IF(Crédits!$K$9="",0,IF(Crédits!$K$9<Crédits!$K$7,AK39,0))+IF(Crédits!$K$10="",0,IF(Crédits!$K$10<Crédits!$K$7,AS39,0)))))) -> 0 | W39: =ROUND(U39-V39,2) -> 0 | X39: =ROUND(X38+Y39-MIN(N(Crédits!$E$7),X38+Y39),2) -> 0 | Y39: =X38*N(Crédits!$D$7)/12 -> 0 | Z39: =AE38 -> 0 | AA39: =Z39*N(Crédits!$D$8)/12 -> 0 | AB39: =MIN(N(Crédits!$E$8),Z39+AA39) -> 0 | AC39: =ROUND(Z39+AA39-AB39,2) -> 0 | AD39: =IF(Crédits!$K$8="",0,MAX(0,MIN(AC39,Plan!$L$41-(IF(Crédits!$K$5="",0,IF(Crédits!$K$5<Crédits!$K$8,E39,0))+IF(Crédits!$K$6="",0,IF(Crédits!$K$6<Crédits!$K$8,M39,0))+IF(Crédits!$K$7="",0,IF(Crédits!$K$7<Crédits!$K$8,U39,0))+IF(Crédits!$K$9="",0,IF(Crédits!$K$9<Crédits!$K$8,AK39,0))+IF(Crédits!$K$10="",0,IF(Crédits!$K$10<Crédits!$K$8,AS39,0)))))) -> 0 | AE39: =ROUND(AC39-AD39,2) -> 0 | AF39: =ROUND(AF38+AG39-MIN(N(Crédits!$E$8),AF38+AG39),2) -> 0 | AG39: =AF38*N(Crédits!$D$8)/12 -> 0 | AH39: =AM38 -> 0 | AI39: =AH39*N(Crédits!$D$9)/12 -> 0 | AJ39: =MIN(N(Crédits!$E$9),AH39+AI39) -> 0 | AK39: =ROUND(AH39+AI39-AJ39,2) -> 0 | AL39: =IF(Crédits!$K$9="",0,MAX(0,MIN(AK39,Plan!$L$41-(IF(Crédits!$K$5="",0,IF(Crédits!$K$5<Crédits!$K$9,E39,0))+IF(Crédits!$K$6="",0,IF(Crédits!$K$6<Crédits!$K$9,M39,0))+IF(Crédits!$K$7="",0,IF(Crédits!$K$7<Crédits!$K$9,U39,0))+IF(Crédits!$K$8="",0,IF(Crédits!$K$8<Crédits!$K$9,AC39,0))+IF(Crédits!$K$10="",0,IF(Crédits!$K$10<Crédits!$K$9,AS39,0)))))) -> 0 | AM39: =ROUND(AK39-AL39,2) -> 0 | AN39: =ROUND(AN38+AO39-MIN(N(Crédits!$E$9),AN38+AO39),2) -> 0 | AO39: =AN38*N(Crédits!$D$9)/12 -> 0 | AP39: =AU38 -> 0 | AQ39: =AP39*N(Crédits!$D$10)/12 -> 0 | AR39: =MIN(N(Crédits!$E$10),AP39+AQ39) -> 0 | AS39: =ROUND(AP39+AQ39-AR39,2) -> 0 | AT39: =IF(Crédits!$K$10="",0,MAX(0,MIN(AS39,Plan!$L$41-(IF(Crédits!$K$5="",0,IF(Crédits!$K$5<Crédits!$K$10,E39,0))+IF(Crédits!$K$6="",0,IF(Crédits!$K$6<Crédits!$K$10,M39,0))+IF(Crédits!$K$7="",0,IF(Crédits!$K$7<Crédits!$K$10,U39,0))+IF(Crédits!$K$8="",0,IF(Crédits!$K$8<Crédits!$K$10,AC39,0))+IF(Crédits!$K$9="",0,IF(Crédits!$K$9<Crédits!$K$10,AK39,0)))))) -> 0 | AU39: =ROUND(AS39-AT39,2) -> 0 | AV39: =ROUND(AV38+AW39-MIN(N(Crédits!$E$10),AV38+AW39),2) -> 0 | AW39: =AV38*N(Crédits!$D$10)/12 -> 0 | AX39: =D39+L39+T39+AB39+AJ39+AR39 -> 0 | AY39: =F39+N39+V39+AD39+AL39+AT39 -> 0 | AZ39: =G39+O39+W39+AE39+AM39+AU39 -> 0 | BA39: =C39+K39+S39+AA39+AI39+AQ39 -> 0 | BB39: =I39+Q39+Y39+AG39+AO39+AW39 -> 0.0147
